Workbook

Sheet 1_Assumptions
A1: Apple Inc. (AAPL) — DCF 假设页（百万美元，US GAAP）
A2: SIC 3571 Electronic Computers ｜ 财年末 0926 ｜ 现价 $326.57 ｜ 评估日 2026-09-11
A3: 蓝色=可编辑输入 黑色=公式 绿色=跨表链接 黄底=判断项（模板不外推，请自行拉开）
A5: 一、情景开关
A6: 选择情景 1=Bull / 2=Base / 3=Bear | B6: 2 | F6: ◀ 改这一格切换全模型情景
A7: 当前情景 | B7: =CHOOSE(B6,"Bull","Base","Bear")
A9: 二、判断项 —— 模板不做外推，三档初始同值，请自行拉开
A10: 假设项 | B10: Bull | C10: Base | D10: Bear | E10: 生效值 | F10: 历史参考
A11: FY2026E 营收增速 | B11: 0.0643 | C11: 0.0643 | D11: 0.0643 | E11: =IF($B$39=1,B44/$B$87-1,CHOOSE($B$6,B11,C11,D11)+$B$35) | F11: ⚠ 锚定开启时本行输入不生效 —— 生效值由已披露季度反推（见上方第三节）
A12: FY2027E 营收增速 | B12: 0.0544 | C12: 0.0544 | D12: 0.0544 | E12: =CHOOSE($B$6,B12,C12,D12)
A13: FY2028E 营收增速 | B13: 0.0446 | C13: 0.0446 | D13: 0.0446 | E13: =CHOOSE($B$6,B13,C13,D13)
A14: FY2029E 营收增速 | B14: 0.0348 | C14: 0.0348 | D14: 0.0348 | E14: =CHOOSE($B$6,B14,C14,D14)
A15: FY2030E 营收增速 | B15: 0.025 | C15: 0.025 | D15: 0.025 | E15: =CHOOSE($B$6,B15,C15,D15)
A17: FY2026E 毛利率 | B17: 0.4575 | C17: 0.4575 | D17: 0.4575 | E17: =IF($B$39=1,1-B46/B44,CHOOSE($B$6,B17,C17,D17)+$B$36) | F17: ⚠ 锚定开启时本行输入不生效 —— 生效值由已披露季度反推（见上方第三节）
A18: FY2027E 毛利率 | B18: 0.4575 | C18: 0.4575 | D18: 0.4575 | E18: =CHOOSE($B$6,B18,C18,D18)
A19: FY2028E 毛利率 | B19: 0.4575 | C19: 0.4575 | D19: 0.4575 | E19: =CHOOSE($B$6,B19,C19,D19)
A20: FY2029E 毛利率 | B20: 0.4575 | C20: 0.4575 | D20: 0.4575 | E20: =CHOOSE($B$6,B20,C20,D20)
A21: FY2030E 毛利率 | B21: 0.4575 | C21: 0.4575 | D21: 0.4575 | E21: =CHOOSE($B$6,B21,C21,D21)
A23: FY2026E 资本开支 / 营收 | B23: 0.0278 | C23: 0.0278 | D23: 0.0278 | E23: =CHOOSE($B$6,B23,C23,D23) | F23: 近3年均值 2.8%
A24: FY2027E 资本开支 / 营收 | B24: 0.0278 | C24: 0.0278 | D24: 0.0278 | E24: =CHOOSE($B$6,B24,C24,D24)
A25: FY2028E 资本开支 / 营收 | B25: 0.0278 | C25: 0.0278 | D25: 0.0278 | E25: =CHOOSE($B$6,B25,C25,D25)
A26: FY2029E 资本开支 / 营收 | B26: 0.0278 | C26: 0.0278 | D26: 0.0278 | E26: =CHOOSE($B$6,B26,C26,D26)
A27: FY2030E 资本开支 / 营收 | B27: 0.0278 | C27: 0.0278 | D27: 0.0278 | E27: =CHOOSE($B$6,B27,C27,D27)
A29: FY2026E SBC / 营收 | B29: 0.02969 | C29: 0.02969 | D29: 0.02969 | E29: =CHOOSE($B$6,B29,C29,D29) | F29: 近3年均值 2.97%｜美股特有的大额非现金费用
A30: FY2027E SBC / 营收 | B30: 0.02969 | C30: 0.02969 | D30: 0.02969 | E30: =CHOOSE($B$6,B30,C30,D30)
A31: FY2028E SBC / 营收 | B31: 0.02969 | C31: 0.02969 | D31: 0.02969 | E31: =CHOOSE($B$6,B31,C31,D31)
A32: FY2029E SBC / 营收 | B32: 0.02969 | C32: 0.02969 | D32: 0.02969 | E32: =CHOOSE($B$6,B32,C32,D32)
A33: FY2030E SBC / 营收 | B33: 0.02969 | C33: 0.02969 | D33: 0.02969 | E33: =CHOOSE($B$6,B33,C33,D33)
A35: 全期营收增速 Δ（敏感性用） | B35: 0 | F35: 加在每一年的生效增速上
A36: 全期毛利率 Δ（敏感性用） | B36: 0 | F36: 加在每一年的生效毛利率上
A38: 三、锚定已披露季度（2025-09-28 ~ 2026-06-27，前 3 个季度实际已确定，首个预测年不再靠增速假设外推）
A39: 锚定开关（1=锚定 0=按增速外推） | B39: 1 | F39: 1 时首个预测年营收 = 已披露实际 ÷ 占比，忽略上方该年的营收增速假设
A40: 已披露期占全年营收比重 | B40: 0.7622 | F40: 近4年同期占比：77.1%｜76.6%｜75.7%｜75.4%｜均值 76.22% 标准差 0.70pp
A41: 剩余期毛利率 | B41: 0.49068 | F41: 默认沿用已披露期毛利率 49.07%；判断剩余期是否改善请自行调整
A42: 已披露期营业收入（实际） | B42: 364357 | F42: 3 个季度合计，取自 10-Q
A43: 已披露期营业成本（实际） | B43: 185575 | F43: 3 个季度合计，取自 10-Q
A44: → 隐含全年营业收入（占比法） | B44: =B42/B40 | F44: 锚定开关=1 时，首个预测年营收即取此值
A45: 〔交叉口径〕隐含全年营业收入（同期同比法） | B45: 483371.34 | F45: 已披露期同比增速 × 上年全年。占比法假设年内形状稳定，同比法假设同比增速延续——两者差得远说明这一年不好锚
A46: → 隐含全年营业成本 | B46: =B43+(B44-B42)*(1-B41)
A48: 四、自动校准假设（从历史推导；可覆盖）
A49: 研发费用 / 营收 | B49: 0.08043 | F49: 近3年均值｜US GAAP 全额费用化（不含可资本化软件成本）
A50: 销售及管理费用 / 营收 | B50: 0.06604 | F50: 近3年均值｜标签缺失时由「销售费用+管理费用」相加
A51: 其他经营损益 / 营收 | B51: 0 | F51: 残差项：令重建的经营利润【精确】等于报表 Operating Income。重组、减值、诉讼和解等未被上面几项捕捉的科目都落在这里，不会凭空消失
A52: 有效所得税率 | B52: 0.1814 | F52: 近3年 所得税/税前利润，夹于 5%–35%
A53: 少数股东损益占比 | B53: 0 | F53: 最近年报实际
A54: 其他流动资产 / 营收 | B54: 0.11858 | F54: 近3年均值
A55: 其他流动负债 / 营收 | B55: 0.19238 | F55: 近3年均值
A56: 应收周转天数 DSO | B56: 31.4 | F56: 应收 / 营收 × 365
A57: 存货周转天数 DIO | B57: 11 | F57: 存货 / 营业成本 × 365
A58: 应付周转天数 DPO | B58: 113.9 | F58: 应付 / 营业成本 × 365
A59: 折旧率（占期初固定资产净额） | B59: 0.1882 | F59: 分子用纯 PP&E 折旧（XBRL Depreciation），不含无形摊销 —— 与分母口径一致
A60: 无形摊销 / 营收 | B60: 0.00835 | F60: 无形资产与融资租赁摊销，单独按营收比例建模
... A65: 现金归集阈值 | B65: 20808.1 | F65: 超出最低现金此数则还短贷
A67: 五、FY2025A 期初余额（模型起点，来自 SEC EDGAR 实际申报）
A68: 现金及等价物 | B68: 35934
A69: 短期投资 | B69: 18763
A70: 应收账款 | B70: 39777
A71: 存货 | B71: 5718
A72: 其他流动资产 | B72: 47765
A73: 固定资产净额 | B73: 49834
A74: 长期投资 | B74: 77723
A75: 商誉与无形资产 | B75: 0
A76: 其他非流动资产 | B76: 83727
A77: 应付账款 | B77: 69860
A78: 其他流动负债 | B78: 75442
A79: 一年内到期债务 | B79: 12350
... A89: 现价（美元） | B89: 326.57001
A90: ★ 期初平衡校验 = 资产 −（负债+权益） | B90: =SUM(B68:B76)-SUM(B77:B85) | F90: 必须为 0
A91: （备查）经营租赁负债 — 非流动 | B91: 10911 | F91: ASC 842 下经营租赁费用仍在营业费用内，Operating Income 已扣过租金；故【不】计入净负债，否则重复扣一次。此处仅备查
A93: 六、DCF 参数
A94: 无风险利率 Rf（10Y UST） | B94: 0.0483 | F94: FRED DGS10，2026-09-09
A95: 股权风险溢价 ERP | B95: =B116+B123 | F95: 默认 = Damodaran 市场隐含 ERP，自动抓取（2026-09-01，Damodaran ERPbymonth.xlsx）。隐含 ERP 是【由市场当前价格反解出来】的折现率溢价；用高于它的值估个股，等于结构上保证「看什么都贵」—— 实测由 5.0% 降到隐含值，四只大盘科技股的低估幅度平均收窄约 10pp。 其他口径：T12m（默认，他每月对外引用的口径） 4.09%、T12m + 可持续派息 4.14%、T12m + 调整无风险利率 4.31%、正常化 3.56%、平滑 6.05%、净现金收益率 3.80% 可选：实务惯例 5.0%（更保守）；课程历史口径 6–8%。 注意：隐含 ERP 是相对他表内的 T.Bond Rate 4.75% 算出来的，本模型的无风险利率取自 FRED，两者可能差几个 bp
A96: Beta（5年对标普500回归+Blume） | B96: 1.1247 | F96: 原始 1.186，样本 1260 日｜2年窗口 1.1029→1.069（504 日）。课程：5年平滑异常，2年更适合动态高成长或刚重组的公司 —— 窗口长度是判断项
A97: 股权成本 Ke | B97: =B94+B96*B95 | F97: Ke = Rf + Beta × ERP
A98: 信用评级（可覆盖） | B98: AAA | F98: 合成评级仅作默认值。投资级顶端 Z 无分辨力（D 项占 82%），且实测系统性高估 1–2 个子级（实际 S&P：MSFT AAA、AAPL AA+、GOOGL AA+、NVDA AA）。已知实际评级时请直接改「信用评级」这一格。
A99: 信用利差 | B99: 0.0042 | F99: ICE BofA AAA OAS（FRED BAMLC0A1CAAA，2026-09-09）
A100: 债务成本 Kd（税前） | B100: =B94+B99 | F100: Kd = Rf + 信用利差（课程 Ch.4 公式）
A101: 债务权重 D/(D+E) | B101: 0.0203 | F101: 有息负债 ÷（有息负债 + 现价×股数）
A102: WACC | B102: =(1-B101)*B97+B101*B100*(1-B52) | F102: WACC = (1−Wd)×Ke + Wd×Kd×(1−t)
A103: 永续增长率 g | B103: 0.025 | F103: Damodaran 规则：g 不应超过无风险利率（当前 Rf 即上限）；美国长期名义 GDP 增速约 4%
A104: 终值所得税率 t_term | B104: 0.25 | F104: 【合并边际税率】21%（联邦）+ 5%（州加权）×(1−21%) = 24.95% ≈ 25%。州税可在联邦税前扣除，所以不是简单相加。只填 21% 会让终值 NOPAT 高估 5.06%，而终值占 EV 约 67–75%。永续期不应假设税收优惠永存 —— 明细期仍用历史有效税率（见上方自动校准）
A105: 期中折现开关（1=是 0=否） | B105: 1 | F105: 现金流全年均匀发生时取 1
A106: 估值基准日滚动年数 | B106: 0.956 | F106: 2025-09-27 → 2026-09-11（非 12-31 财年在此体现）
A107: 非经营资产（加回） | B107: 77723 | F107: 长期有价证券与权益法投资；短期投资已在净负债中扣除
A108: 少数股东扣除方式（1=账面 2=价值） | B108: 2 | F108: 价值法按其利润分成折算
A109: 研发资本化开关（1=开 0=关） | B109: 1 | F109: Damodaran 口径：研发是投资不是费用。开启后【只影响投入资本与 ROIC】，不改 FCFF —— 明确期现金流仍与申报报表一一对应（可审计），而终值的 g = 再投资率 × ROIC 才有意义。关掉会怎样：AAPL 的 ROIC 从 82% 跳到 272%（回购把账面权益冲小所致），再投资率随之接近 0，终值等于把当前超额回报永续化
A110: 研发摊销年限（年） | B110: 5 | F110: 按 SIC 3571 自动映射（软件/互联网 3 年、半导体与硬件 5 年、制药 10 年）
A111: 终值 ROIC 处理（1=沿用末年 2=收敛至 WACC+溢价） | B111: 1 | F111: 沿用末年 = 假设当前超额回报永续，对高 ROIC 公司过于乐观；收敛 = 竞争终将侵蚀超额回报（Damodaran 更倾向此法）
A112: 终值 ROIC 收敛溢价（模式2 用） | B112: 0.03 | F112: 收敛后的终值 ROIC = WACC + 本溢价。3% 代表仍保有温和护城河
A113: SBC 加回开关（0=费用化 1=加回） | B113: 0 | F113: 0 = Damodaran 口径（默认）：SBC 已含在 R&D/SG&A 内，不加回，且【股数不因 SBC 摊薄】。1 = 卖方惯例：加回 SBC，同时股数按 SBC/股价 摊薄。两件事绑在同一开关上，无法只做一半
A115: 〔ERP 明细〕收入地域加权（Damodaran 国别风险溢价） | F115: 口径：成熟市场基准 = 标普隐含 ERP − 美国 CRP；加权 ERP = 基准 + Σ(收入权重 × 国别CRP)。纯美国收入时自动还原为标普隐含 ERP。分地域收入取自 FMP FY2025
A116: 成熟市场基准（标普隐含 ERP − 美国 CRP） | B116: 0.03857
A117: 地域 | B117: 收入权重 | C117: 映射到 | D117: 国别CRP
A118: Americas Segment | B118: 0.4286 | C118: North America | D118: 0.00216
A119: Europe Segment | B119: 0.2668 | C119: Western Europe | D119: 0.00969
A120: Greater China Segment | B120: 0.1547 | C120: CHINA | D120: 0.00913
A121: Rest of Asia Pacific Segment | B121: 0.081 | C121: Asia | D121: 0.02474
A122: Japan Segment | B122: 0.069 | C122: JAPAN | D122: 0.00913
A123: 加权 CRP | B123: =B118*D118+B119*D119+B120*D120+B121*D121+B122*D122 | F123: 权重与 CRP 都可改；映射不确定时直接改右侧 CRP 即可
A124: ★ 权重合计（应为 100%） | B124: =SUM(B118:B122)
...

Sheet 2_Income
A1: Apple Inc. (AAPL) — Income（百万美元，US GAAP）
A2: B:F = 历史实际（斜体静态，来自 SEC EDGAR） ｜ G:K = 公式预测 ｜ 基数 = FY2025A（F 列）
A4: Income
A5: 科目（百万美元） | B5: FY2021A | C5: FY2022A | D5: FY2023A | E5: FY2024A | F5: FY2025A | G5: FY2026E | H5: FY2027E | I5: FY2028E | J5: FY2029E | K5: FY2030E
A6: Revenue 营业收入 | B6: 365817 | C6: 394328 | D6: 383285 | E6: 391035 | F6: 416161 | G6: =F6*(1+'1_Assumptions'!$E$11+'1_Assumptions'!$B$35) | H6: =G6*(1+'1_Assumptions'!$E$12+'1_Assumptions'!$B$35) | I6: =H6*(1+'1_Assumptions'!$E$13+'1_Assumptions'!$B$35) | J6: =I6*(1+'1_Assumptions'!$E$14+'1_Assumptions'!$B$35) | K6: =J6*(1+'1_Assumptions'!$E$15+'1_Assumptions'!$B$35)
A7: 营收增速 | C7: 0.077938 | D7: -0.028005 | E7: 0.02022 | F7: 0.064255 | G7: =G6/F6-1 | H7: =H6/G6-1 | I7: =I6/H6-1 | J7: =J6/I6-1 | K7: =K6/J6-1
A8: Cost of revenue 营业成本 | B8: 212981 | C8: 223546 | D8: 214137 | E8: 210352 | F8: 220960 | G8: =G6*(1-'1_Assumptions'!$E$17-'1_Assumptions'!$B$36) | H8: =H6*(1-'1_Assumptions'!$E$18-'1_Assumptions'!$B$36) | I8: =I6*(1-'1_Assumptions'!$E$19-'1_Assumptions'!$B$36) | J8: =J6*(1-'1_Assumptions'!$E$20-'1_Assumptions'!$B$36) | K8: =K6*(1-'1_Assumptions'!$E$21-'1_Assumptions'!$B$36)
A9: Gross profit 毛利 | B9: 152836 | C9: 170782 | D9: 169148 | E9: 180683 | F9: 195201 | G9: =G6-G8 | H9: =H6-H8 | I9: =I6-I8 | J9: =J6-J8 | K9: =K6-K8
A10: 毛利率 | B10: 0.417794 | C10: 0.433096 | D10: 0.441311 | E10: 0.462063 | F10: 0.469052 | G10: =G9/G6 | H10: =H9/H6 | I10: =I9/I6 | J10: =J9/J6 | K10: =K9/K6
A11: R&D 研发费用 | B11: 21914 | C11: 26251 | D11: 29915 | E11: 31370 | F11: 34550 | G11: =G6*'1_Assumptions'!$B$49 | H11: =H6*'1_Assumptions'!$B$49 | I11: =I6*'1_Assumptions'!$B$49 | J11: =J6*'1_Assumptions'!$B$49 | K11: =K6*'1_Assumptions'!$B$49
A12: SG&A 销售及管理费用 | B12: 21973 | C12: 25094 | D12: 24932 | E12: 26097 | F12: 27601 | G12: =G6*'1_Assumptions'!$B$50 | H12: =H6*'1_Assumptions'!$B$50 | I12: =I6*'1_Assumptions'!$B$50 | J12: =J6*'1_Assumptions'!$B$50 | K12: =K6*'1_Assumptions'!$B$50
A13: Other operating 其他经营损益 | G13: =G6*'1_Assumptions'!$B$51 | H13: =H6*'1_Assumptions'!$B$51 | I13: =I6*'1_Assumptions'!$B$51 | J13: =J6*'1_Assumptions'!$B$51 | K13: =K6*'1_Assumptions'!$B$51
A14: Operating income (EBIT) 经营利润 | B14: 108949 | C14: 119437 | D14: 114301 | E14: 123216 | F14: 133050 | G14: =G9-G11-G12+G13 | H14: =H9-H11-H12+H13 | I14: =I9-I11-I12+I13 | J14: =J9-J11-J12+J13 | K14: =K9-K11-K12+K13
A15: Interest expense 利息支出 | B15: 2645 | C15: 2931 | D15: 3933 | G15: =('3_Balance'!F18+'3_Balance'!F19+'3_Balance'!F21)*'1_Assumptions'!$B$61 | H15: =('3_Balance'!G18+'3_Balance'!G19+'3_Balance'!G21)*'1_Assumptions'!$B$61 | I15: =('3_Balance'!H18+'3_Balance'!H19+'3_Balance'!H21)*'1_Assumptions'!$B$61 | J15: =('3_Balance'!I18+'3_Balance'!I19+'3_Balance'!I21)*'1_Assumptions'!$B$61 | K15: =('3_Balance'!J18+'3_Balance'!J19+'3_Balance'!J21)*'1_Assumptions'!$B$61
A16: Interest & investment income 利息与投资收益 | G16: =('3_Balance'!F6+'3_Balance'!F7)*'1_Assumptions'!$B$62 | H16: =('3_Balance'!G6+'3_Balance'!G7)*'1_Assumptions'!$B$62 | I16: =('3_Balance'!H6+'3_Balance'!H7)*'1_Assumptions'!$B$62 | J16: =('3_Balance'!I6+'3_Balance'!I7)*'1_Assumptions'!$B$62 | K16: =('3_Balance'!J6+'3_Balance'!J7)*'1_Assumptions'!$B$62
A17: Other non-operating 其他非经营损益 | B17: 258 | C17: -334 | D17: -565 | E17: 269 | F17: -321 | G17: =0 | H17: =0 | I17: =0 | J17: =0 | K17: =0
A18: Pretax income 税前利润 | B18: 109207 | C18: 119103 | D18: 113736 | E18: 123485 | F18: 132729 | G18: =G14-G15+G16+G17 | H18: =H14-H15+H16+H17 | I18: =I14-I15+I16+I17 | J18: =J14-J15+J16+J17 | K18: =K14-K15+K16+K17
A19: Income tax 所得税 | B19: 14527 | C19: 19300 | D19: 16741 | E19: 29749 | F19: 20719 | G19: =G18*'1_Assumptions'!$B$52 | H19: =H18*'1_Assumptions'!$B$52 | I19: =I18*'1_Assumptions'!$B$52 | J19: =J18*'1_Assumptions'!$B$52 | K19: =K18*'1_Assumptions'!$B$52
A20: Net income 净利润 | B20: 94680 | C20: 99803 | D20: 96995 | E20: 93736 | F20: 112010 | G20: =G18-G19 | H20: =H18-H19 | I20: =I18-I19 | J20: =J18-J19 | K20: =K18-K19
A21: less: NCI 少数股东损益 | G21: =G20*'1_Assumptions'!$B$53 | H21: =H20*'1_Assumptions'!$B$53 | I21: =I20*'1_Assumptions'!$B$53 | J21: =J20*'1_Assumptions'!$B$53 | K21: =K20*'1_Assumptions'!$B$53
A22: Net income to parent 归母净利润 | B22: 94680 | C22: 99803 | D22: 96995 | E22: 93736 | F22: 112010 | G22: =G20-G21 | H22: =H20-H21 | I22: =I20-I21 | J22: =J20-J21 | K22: =K20-K21
A23: Diluted shares 摊薄股数（百万股） | B23: 16864.92 | C23: 16325.82 | D23: 15812.55 | E23: 15408.09 | F23: 15004.7 | G23: ='4_CashFlow'!G30 | H23: ='4_CashFlow'!H30 | I23: ='4_CashFlow'!I30 | J23: ='4_CashFlow'!J30 | K23: ='4_CashFlow'!K30
A24: Diluted EPS | G24: =G22/G23 | H24: =H22/H23 | I24: =I22/I23 | J24: =J22/J23 | K24: =K22/K23
A25: P/E（按现价） | G25: ='1_Assumptions'!$B$89/G24 | H25: ='1_Assumptions'!$B$89/H24 | I25: ='1_Assumptions'!$B$89/I24 | J25: ='1_Assumptions'!$B$89/J24 | K25: ='1_Assumptions'!$B$89/K24
A26: （备查）SBC 股份支付 | B26: 7906 | C26: 9038 | D26: 10833 | E26: 11688 | F26: 12863 | G26: =G6*'1_Assumptions'!$E$29 | H26: =H6*'1_Assumptions'!$E$30 | I26: =I6*'1_Assumptions'!$E$31 | J26: =J6*'1_Assumptions'!$E$32 | K26: =K6*'1_Assumptions'!$E$33

Sheet 3_Balance
A1: Apple Inc. (AAPL) — Balance（百万美元，US GAAP）
A2: B:F = 历史实际（斜体静态，来自 SEC EDGAR） ｜ G:K = 公式预测 ｜ 基数 = FY2025A（F 列）
A4: Balance
A5: 科目（百万美元） | B5: FY2021A | C5: FY2022A | D5: FY2023A | E5: FY2024A | F5: FY2025A | G5: FY2026E | H5: FY2027E | I5: FY2028E | J5: FY2029E | K5: FY2030E
A6: Cash & equivalents 现金 | B6: 34940 | C6: 23646 | D6: 29965 | E6: 29943 | F6: 35934 | G6: ='4_CashFlow'!G27 | H6: ='4_CashFlow'!H27 | I6: ='4_CashFlow'!I27 | J6: ='4_CashFlow'!J27 | K6: ='4_CashFlow'!K27
A7: Short-term investments 短期投资 | B7: 27699 | C7: 24658 | D7: 31590 | E7: 35228 | F7: 18763 | G7: =F7 | H7: =G7 | I7: =H7 | J7: =I7 | K7: =J7
A8: Accounts receivable 应收账款 | B8: 26278 | C8: 28184 | D8: 29508 | E8: 33410 | F8: 39777 | G8: ='2_Income'!G6*'1_Assumptions'!$B$56/365 | H8: ='2_Income'!H6*'1_Assumptions'!$B$56/365 | I8: ='2_Income'!I6*'1_Assumptions'!$B$56/365 | J8: ='2_Income'!J6*'1_Assumptions'!$B$56/365 | K8: ='2_Income'!K6*'1_Assumptions'!$B$56/365
A9: Inventory 存货 | B9: 6580 | C9: 4946 | D9: 6331 | E9: 7286 | F9: 5718 | G9: ='2_Income'!G8*'1_Assumptions'!$B$57/365 | H9: ='2_Income'!H8*'1_Assumptions'!$B$57/365 | I9: ='2_Income'!I8*'1_Assumptions'!$B$57/365 | J9: ='2_Income'!J8*'1_Assumptions'!$B$57/365 | K9: ='2_Income'!K8*'1_Assumptions'!$B$57/365
A10: Other current assets 其他流动资产 | B10: 39339 | C10: 53971 | D10: 46172 | E10: 47120 | F10: 47765 | G10: ='2_Income'!G6*'1_Assumptions'!$B$54 | H10: ='2_Income'!H6*'1_Assumptions'!$B$54 | I10: ='2_Income'!I6*'1_Assumptions'!$B$54 | J10: ='2_Income'!J6*'1_Assumptions'!$B$54 | K10: ='2_Income'!K6*'1_Assumptions'!$B$54
A11: Total current assets 流动资产合计 | G11: =SUM(G6:G10) | H11: =SUM(H6:H10) | I11: =SUM(I6:I10) | J11: =SUM(J6:J10) | K11: =SUM(K6:K10)
A12: PP&E, net 固定资产净额 | B12: 39440 | C12: 42117 | D12: 43715 | E12: 45680 | F12: 49834 | G12: =F12-'4_CashFlow'!G16-'4_CashFlow'!G7 | H12: =G12-'4_CashFlow'!H16-'4_CashFlow'!H7 | I12: =H12-'4_CashFlow'!I16-'4_CashFlow'!I7 | J12: =I12-'4_CashFlow'!J16-'4_CashFlow'!J7 | K12: =J12-'4_CashFlow'!K16-'4_CashFlow'!K7
A13: Long-term investments 长期投资 | B13: 127877 | C13: 120805 | D13: 100544 | E13: 91479 | F13: 77723 | G13: =F13 | H13: =G13 | I13: =H13 | J13: =I13 | K13: =J13
A14: Goodwill & intangibles 商誉与无形资产 | G14: =F14-'4_CashFlow'!G8 | H14: =G14-'4_CashFlow'!H8 | I14: =H14-'4_CashFlow'!I8 | J14: =I14-'4_CashFlow'!J8 | K14: =J14-'4_CashFlow'!K8
A15: Other non-current assets 其他非流动资产 | B15: 48849 | C15: 54428 | D15: 64758 | E15: 74834 | F15: 83727 | G15: =F15 | H15: =G15 | I15: =H15 | J15: =I15 | K15: =J15
A16: Total assets 资产总计 | G16: =G11+SUM(G12:G15) | H16: =H11+SUM(H12:H15) | I16: =I11+SUM(I12:I15) | J16: =J11+SUM(J12:J15) | K16: =K11+SUM(K12:K15)
A17: Liabilities & equity 负债与所有者权益
A18: Short-term borrowings 短期借款 | B18: 6000 | C18: 9982 | D18: 5985 | E18: 9967 | F18: 7979 | G18: =F18+'4_CashFlow'!G23 | H18: =G18+'4_CashFlow'!H23 | I18: =H18+'4_CashFlow'!I23 | J18: =I18+'4_CashFlow'!J23 | K18: =J18+'4_CashFlow'!K23
A19: Current portion of LT debt 一年内到期债务 | B19: 9613 | C19: 11128 | D19: 9822 | E19: 10912 | F19: 12350 | G19: =F19 | H19: =G19 | I19: =H19 | J19: =I19 | K19: =J19
A20: Accounts payable 应付账款 | B20: 54763 | C20: 64115 | D20: 62611 | E20: 68960 | F20: 69860 | G20: ='2_Income'!G8*'1_Assumptions'!$B$58/365 | H20: ='2_Income'!H8*'1_Assumptions'!$B$58/365 | I20: ='2_Income'!I8*'1_Assumptions'!$B$58/365 | J20: ='2_Income'!J8*'1_Assumptions'!$B$58/365 | K20: ='2_Income'!K8*'1_Assumptions'!$B$58/365
A21: Long-term debt 长期债务 | B21: 109106 | C21: 98959 | D21: 95281 | E21: 85750 | F21: 78328 | G21: =F21 | H21: =G21 | I21: =H21 | J21: =I21 | K21: =J21
A22: Other current liabilities 其他流动负债 | B22: 55105 | C22: 68757 | D22: 66890 | E22: 86553 | F22: 75442 | G22: ='2_Income'!G6*'1_Assumptions'!$B$55 | H22: ='2_Income'!H6*'1_Assumptions'!$B$55 | I22: ='2_Income'!I6*'1_Assumptions'!$B$55 | J22: ='2_Income'!J6*'1_Assumptions'!$B$55 | K22: ='2_Income'!K6*'1_Assumptions'!$B$55
A23: Other non-current liabilities 其他非流动负债 | B23: 53325 | C23: 49142 | D23: 49848 | E23: 45888 | F23: 41549 | G23: =F23 | H23: =G23 | I23: =H23 | J23: =I23 | K23: =J23
A24: Total liabilities 负债合计 | G24: =SUM(G18:G23) | H24: =SUM(H18:H23) | I24: =SUM(I18:I23) | J24: =SUM(J18:J23) | K24: =SUM(K18:K23)
A25: Stockholders' equity 归母权益 | B25: 63090 | C25: 50672 | D25: 62146 | E25: 56950 | F25: 73733 | G25: =F25+'2_Income'!G22+'4_CashFlow'!G20+'4_CashFlow'!G21+'4_CashFlow'!G22+'2_Income'!G26 | H25: =G25+'2_Income'!H22+'4_CashFlow'!H20+'4_CashFlow'!H21+'4_CashFlow'!H22+'2_Income'!H26 | I25: =H25+'2_Income'!I22+'4_CashFlow'!I20+'4_CashFlow'!I21+'4_CashFlow'!I22+'2_Income'!I26 | J25: =I25+'2_Income'!J22+'4_CashFlow'!J20+'4_CashFlow'!J21+'4_CashFlow'!J22+'2_Income'!J26 | K25: =J25+'2_Income'!K22+'4_CashFlow'!K20+'4_CashFlow'!K21+'4_CashFlow'!K22+'2_Income'!K26
A26: Noncontrolling interests 少数股东权益 | G26: =F26+'2_Income'!G21 | H26: =G26+'2_Income'!H21 | I26: =H26+'2_Income'!I21 | J26: =I26+'2_Income'!J21 | K26: =J26+'2_Income'!K21
A27: Total equity 权益合计 | G27: =G25+G26 | H27: =H25+H26 | I27: =I25+I26 | J27: =J25+J26 | K27: =K25+K26
A28: Total liabilities & equity 负债和权益总计 | G28: =G24+G27 | H28: =H24+H27 | I28: =I24+I27 | J28: =J24+J27 | K28: =K24+K27
A29: ★ 平衡校验 = 资产 −（负债+权益） | G29: =G16-G28 | H29: =H16-H28 | I29: =I16-I28 | J29: =J16-J28 | K29: =K16-K28
A30: Net debt 净负债 | G30: =G18+G19+G21-G6-G7 | H30: =H18+H19+H21-H6-H7 | I30: =I18+I19+I21-I6-I7 | J30: =J18+J19+J21-J6-J7 | K30: =K18+K19+K21-K6-K7
A31: NWC 营运资本 | G31: =G8+G9+G10-G20-G22 | H31: =H8+H9+H10-H20-H22 | I31: =I8+I9+I10-I20-I22 | J31: =J8+J9+J10-J20-J22 | K31: =K8+K9+K10-K20-K22
A32: 〔备查〕研发摊销 R&D amortization | G32: =F33/'1_Assumptions'!$B$110 | H32: =G33/'1_Assumptions'!$B$110 | I32: =H33/'1_Assumptions'!$B$110 | J32: =I33/'1_Assumptions'!$B$110 | K32: =J33/'1_Assumptions'!$B$110
A33: 〔备查〕研发资本 Research asset | F33: 92478.2 | G33: =F33+'2_Income'!G11-G32 | H33: =G33+'2_Income'!H11-H32 | I33: =H33+'2_Income'!I11-I32 | J33: =I33+'2_Income'!J11-J32 | K33: =J33+'2_Income'!K11-K32
A34: 〔备查〕投入资本 IC（申报口径） | G34: =G31+G12+G14+G15-G23 | H34: =H31+H12+H14+H15-H23 | I34: =I31+I12+I14+I15-I23 | J34: =J31+J12+J14+J15-J23 | K34: =K31+K12+K14+K15-K23
A35: 〔备查〕投入资本 IC（含研发资本） | G35: =G34+IF('1_Assumptions'!$B$109=1,G33,0) | H35: =H34+IF('1_Assumptions'!$B$109=1,H33,0) | I35: =I34+IF('1_Assumptions'!$B$109=1,I33,0) | J35: =J34+IF('1_Assumptions'!$B$109=1,J33,0) | K35: =K34+IF('1_Assumptions'!$B$109=1,K33,0)
A36: 〔备查〕生效投入资本 IC | G36: =G35 | H36: =H35 | I36: =I35 | J36: =J35 | K36: =K35

Sheet 4_CashFlow
A1: Apple Inc. (AAPL) — CashFlow（百万美元，US GAAP）
A2: B:F = 历史实际（斜体静态，来自 SEC EDGAR） ｜ G:K = 公式预测 ｜ 基数 = FY2025A（F 列）
A3: 注：历史列仅填报表已披露科目；营运资本明细变动、循环贷与股数滚动为模型专用行，历史留空。
A4: CashFlow
A5: 科目（百万美元） | B5: FY2021A | C5: FY2022A | D5: FY2023A | E5: FY2024A | F5: FY2025A | G5: FY2026E | H5: FY2027E | I5: FY2028E | J5: FY2029E | K5: FY2030E
A6: Net income 净利润 | B6: 94680 | C6: 99803 | D6: 96995 | E6: 93736 | F6: 112010 | G6: ='2_Income'!G20 | H6: ='2_Income'!H20 | I6: ='2_Income'!I20 | J6: ='2_Income'!J20 | K6: ='2_Income'!K20
A7: + Depreciation 折旧 | B7: 9500 | C7: 8700 | D7: 8500 | E7: 8200 | F7: 8000 | G7: ='3_Balance'!F12*'1_Assumptions'!$B$59 | H7: ='3_Balance'!G12*'1_Assumptions'!$B$59 | I7: ='3_Balance'!H12*'1_Assumptions'!$B$59 | J7: ='3_Balance'!I12*'1_Assumptions'!$B$59 | K7: ='3_Balance'!J12*'1_Assumptions'!$B$59
A8: + Amortization 无形摊销 | B8: 1784 | C8: 2404 | D8: 3019 | E8: 3245 | F8: 3698 | G8: ='2_Income'!G6*'1_Assumptions'!$B$60 | H8: ='2_Income'!H6*'1_Assumptions'!$B$60 | I8: ='2_Income'!I6*'1_Assumptions'!$B$60 | J8: ='2_Income'!J6*'1_Assumptions'!$B$60 | K8: ='2_Income'!K6*'1_Assumptions'!$B$60
A9: + SBC 股份支付 | B9: 7906 | C9: 9038 | D9: 10833 | E9: 11688 | F9: 12863 | G9: ='2_Income'!G26 | H9: ='2_Income'!H26 | I9: ='2_Income'!I26 | J9: ='2_Income'!J26 | K9: ='2_Income'!K26
A10: − ΔAccounts receivable 应收增加 | G10: =-('3_Balance'!G8-'3_Balance'!F8) | H10: =-('3_Balance'!H8-'3_Balance'!G8) | I10: =-('3_Balance'!I8-'3_Balance'!H8) | J10: =-('3_Balance'!J8-'3_Balance'!I8) | K10: =-('3_Balance'!K8-'3_Balance'!J8)
A11: − ΔInventory 存货增加 | G11: =-('3_Balance'!G9-'3_Balance'!F9) | H11: =-('3_Balance'!H9-'3_Balance'!G9) | I11: =-('3_Balance'!I9-'3_Balance'!H9) | J11: =-('3_Balance'!J9-'3_Balance'!I9) | K11: =-('3_Balance'!K9-'3_Balance'!J9)
A12: − ΔOther current assets 其他流动资产增加 | G12: =-('3_Balance'!G10-'3_Balance'!F10) | H12: =-('3_Balance'!H10-'3_Balance'!G10) | I12: =-('3_Balance'!I10-'3_Balance'!H10) | J12: =-('3_Balance'!J10-'3_Balance'!I10) | K12: =-('3_Balance'!K10-'3_Balance'!J10)
A13: + ΔAccounts payable 应付增加 | G13: ='3_Balance'!G20-'3_Balance'!F20 | H13: ='3_Balance'!H20-'3_Balance'!G20 | I13: ='3_Balance'!I20-'3_Balance'!H20 | J13: ='3_Balance'!J20-'3_Balance'!I20 | K13: ='3_Balance'!K20-'3_Balance'!J20
A14: + ΔOther current liabilities 其他流动负债增加 | G14: ='3_Balance'!G22-'3_Balance'!F22 | H14: ='3_Balance'!H22-'3_Balance'!G22 | I14: ='3_Balance'!I22-'3_Balance'!H22 | J14: ='3_Balance'!J22-'3_Balance'!I22 | K14: ='3_Balance'!K22-'3_Balance'!J22
A15: Operating cash flow 经营活动现金流 | B15: 104038 | C15: 122151 | D15: 110543 | E15: 118254 | F15: 111482 | G15: =SUM(G6:G14) | H15: =SUM(H6:H14) | I15: =SUM(I6:I14) | J15: =SUM(J6:J14) | K15: =SUM(K6:K14)
A16: − Capital expenditure 资本开支 | B16: -11085 | C16: -10708 | D16: -10959 | E16: -9447 | F16: -12715 | G16: =-'2_Income'!G6*'1_Assumptions'!$E$23-IF(AND('1_Assumptions'!$B$134>0,1>='1_Assumptions'!$B$133,1<='1_Assumptions'!$B$133+2),'1_Assumptions'!$B$134/3,0) | H16: =-'2_Income'!H6*'1_Assumptions'!$E$24-IF(AND('1_Assumptions'!$B$134>0,2>='1_Assumptions'!$B$133,2<='1_Assumptions'!$B$133+2),'1_Assumptions'!$B$134/3,0) | I16: =-'2_Income'!I6*'1_Assumptions'!$E$25-IF(AND('1_Assumptions'!$B$134>0,3>='1_Assumptions'!$B$133,3<='1_Assumptions'!$B$133+2),'1_Assumptions'!$B$134/3,0) | J16: =-'2_Income'!J6*'1_Assumptions'!$E$26-IF(AND('1_Assumptions'!$B$134>0,4>='1_Assumptions'!$B$133,4<='1_Assumptions'!$B$133+2),'1_Assumptions'!$B$134/3,0) | K16: =-'2_Income'!K6*'1_Assumptions'!$E$27-IF(AND('1_Assumptions'!$B$134>0,5>='1_Assumptions'!$B$133,5<='1_Assumptions'!$B$133+2),'1_Assumptions'!$B$134/3,0)
A17: Investing cash flow 投资活动现金流 | G17: =G16 | H17: =H16 | I17: =I16 | J17: =J16 | K17: =K16
A18: Free cash flow (OCF − capex) 自由现金流 | G18: =G15+G16 | H18: =H15+H16 | I18: =I15+I16 | J18: =J15+J16 | K18: =K15+K16
A19: FCFF（无杠杆自由现金流） | G19: ='2_Income'!G14*(1-'1_Assumptions'!$B$52)+G7+G8+IF('1_Assumptions'!$B$113=1,G9,0)+G16+SUM(G10:G14) | H19: ='2_Income'!H14*(1-'1_Assumptions'!$B$52)+H7+H8+IF('1_Assumptions'!$B$113=1,H9,0)+H16+SUM(H10:H14) | I19: ='2_Income'!I14*(1-'1_Assumptions'!$B$52)+I7+I8+IF('1_Assumptions'!$B$113=1,I9,0)+I16+SUM(I10:I14) | J19: ='2_Income'!J14*(1-'1_Assumptions'!$B$52)+J7+J8+IF('1_Assumptions'!$B$113=1,J9,0)+J16+SUM(J10:J14) | K19: ='2_Income'!K14*(1-'1_Assumptions'!$B$52)+K7+K8+IF('1_Assumptions'!$B$113=1,K9,0)+K16+SUM(K10:K14)
A20: − Dividends 分红 | B20: -14467 | C20: -14841 | D20: -15025 | E20: -15234 | F20: -15421 | G20: =-'2_Income'!G22*'1_Assumptions'!$B$63 | H20: =-'2_Income'!H22*'1_Assumptions'!$B$63 | I20: =-'2_Income'!I22*'1_Assumptions'!$B$63 | J20: =-'2_Income'!J22*'1_Assumptions'!$B$63 | K20: =-'2_Income'!K22*'1_Assumptions'!$B$63
A21: − Share repurchase 回购 | B21: -85971 | C21: -89402 | D21: -77550 | E21: -94949 | F21: -90711 | G21: =-'2_Income'!G6*'1_Assumptions'!$B$128 | H21: =-'2_Income'!H6*'1_Assumptions'!$B$128 | I21: =-'2_Income'!I6*'1_Assumptions'!$B$128 | J21: =-'2_Income'!J6*'1_Assumptions'!$B$128 | K21: =-'2_Income'!K6*'1_Assumptions'!$B$128
A22: + Equity issuance 增发募资净额 | G22: =IF('1_Assumptions'!$B$133=1,'1_Assumptions'!$B$135,0) | H22: =IF('1_Assumptions'!$B$133=2,'1_Assumptions'!$B$135,0) | I22: =IF('1_Assumptions'!$B$133=3,'1_Assumptions'!$B$135,0) | J22: =IF('1_Assumptions'!$B$133=4,'1_Assumptions'!$B$135,0) | K22: =IF('1_Assumptions'!$B$133=5,'1_Assumptions'!$B$135,0)
A23: + Revolver 循环贷净变动 | G23: =IF(G26<'1_Assumptions'!$B$64,'1_Assumptions'!$B$64-G26,IF(AND(G26>'1_Assumptions'!$B$64+'1_Assumptions'!$B$65,'3_Balance'!F18>0),-MIN('3_Balance'!F18,G26-('1_Assumptions'!$B$64+'1_Assumptions'!$B$65)),0)) | H23: =IF(H26<'1_Assumptions'!$B$64,'1_Assumptions'!$B$64-H26,IF(AND(H26>'1_Assumptions'!$B$64+'1_Assumptions'!$B$65,'3_Balance'!G18>0),-MIN('3_Balance'!G18,H26-('1_Assumptions'!$B$64+'1_Assumptions'!$B$65)),0)) | I23: =IF(I26<'1_Assumptions'!$B$64,'1_Assumptions'!$B$64-I26,IF(AND(I26>'1_Assumptions'!$B$64+'1_Assumptions'!$B$65,'3_Balance'!H18>0),-MIN('3_Balance'!H18,I26-('1_Assumptions'!$B$64+'1_Assumptions'!$B$65)),0)) | J23: =IF(J26<'1_Assumptions'!$B$64,'1_Assumptions'!$B$64-J26,IF(AND(J26>'1_Assumptions'!$B$64+'1_Assumptions'!$B$65,'3_Balance'!I18>0),-MIN('3_Balance'!I18,J26-('1_Assumptions'!$B$64+'1_Assumptions'!$B$65)),0)) | K23: =IF(K26<'1_Assumptions'!$B$64,'1_Assumptions'!$B$64-K26,IF(AND(K26>'1_Assumptions'!$B$64+'1_Assumptions'!$B$65,'3_Balance'!J18>0),-MIN('3_Balance'!J18,K26-('1_Assumptions'!$B$64+'1_Assumptions'!$B$65)),0))
A24: Financing cash flow 筹资活动现金流 | G24: =SUM(G20:G23) | H24: =SUM(H20:H23) | I24: =SUM(I20:I23) | J24: =SUM(J20:J23) | K24: =SUM(K20:K23)
A25: Net change in cash 现金净增加 | G25: =G15+G17+G24 | H25: =H15+H17+H24 | I25: =I15+I17+I24 | J25: =J15+J17+J24 | K25: =K15+K17+K24
A26: （辅助）筹资前现金余额 | G26: =F27+G15+G17+G20+G21+G22 | H26: =G27+H15+H17+H20+H21+H22 | I26: =H27+I15+I17+I20+I21+I22 | J26: =I27+J15+J17+J20+J21+J22 | K26: =J27+K15+K17+K20+K21+K22
A27: Ending cash 期末现金 | B27: 34940 | C27: 23646 | D27: 29965 | E27: 29943 | F27: 35934 | G27: =F27+G25 | H27: =G27+H25 | I27: =H27+I25 | J27: =I27+J25 | K27: =J27+K25
A28: 回购股数（百万股） | G28: =-G21/'1_Assumptions'!$B$129 | H28: =-H21/'1_Assumptions'!$B$129 | I28: =-I21/'1_Assumptions'!$B$129 | J28: =-J21/'1_Assumptions'!$B$129 | K28: =-K21/'1_Assumptions'!$B$129
A29: SBC 增发股数（仅在加回口径下） | G29: =IF('1_Assumptions'!$B$113=1,'2_Income'!G26/'1_Assumptions'!$B$129,0) | H29: =IF('1_Assumptions'!$B$113=1,'2_Income'!H26/'1_Assumptions'!$B$129,0) | I29: =IF('1_Assumptions'!$B$113=1,'2_Income'!I26/'1_Assumptions'!$B$129,0) | J29: =IF('1_Assumptions'!$B$113=1,'2_Income'!J26/'1_Assumptions'!$B$129,0) | K29: =IF('1_Assumptions'!$B$113=1,'2_Income'!K26/'1_Assumptions'!$B$129,0)
A30: Diluted shares 摊薄股数（滚动） | B30: 16864.92 | C30: 16325.82 | D30: 15812.55 | E30: 15408.09 | F30: 15004.7 | G30: ='1_Assumptions'!$B$88-G28+G29+IF('1_Assumptions'!$B$133=1,'1_Assumptions'!$B$130,0) | H30: =G30-H28+H29+IF('1_Assumptions'!$B$133=2,'1_Assumptions'!$B$130,0) | I30: =H30-I28+I29+IF('1_Assumptions'!$B$133=3,'1_Assumptions'!$B$130,0) | J30: =I30-J28+J29+IF('1_Assumptions'!$B$133=4,'1_Assumptions'!$B$130,0) | K30: =J30-K28+K29+IF('1_Assumptions'!$B$133=5,'1_Assumptions'!$B$130,0)

Sheet 5_DCF
A1: Apple Inc. (AAPL) — DCF 估值（全公式，百万美元）
A2: 绿色单元格链接自「1_Assumptions」，改假设本页自动重算
A4: 一、折现率 WACC
A5: 无风险利率 Rf（10Y UST） | B5: ='1_Assumptions'!B94
A6: 股权风险溢价 ERP | B6: ='1_Assumptions'!B95
A7: Beta（5年 + Blume） | B7: ='1_Assumptions'!B96
A8: 股权成本 Ke = Rf + β×ERP | B8: =B5+B7*B6
A9: 信用评级（合成，可覆盖） | B9: ='1_Assumptions'!B98 | H9: Altman Z 推导的默认值；已知实际 S&P 评级时请在假设页直接改
A10: 信用利差 | B10: ='1_Assumptions'!B99 | H10: ICE BofA AAA OAS（FRED BAMLC0A1CAAA，2026-09-09）
A11: 债务成本 Kd = Rf + 信用利差 | B11: =B5+B10 | H11: 课程 Ch.4：kd = 无风险利率 + 国家违约利差 + 公司违约利差（美国视为无国家违约利差）
A12: 有效所得税率 t | B12: ='1_Assumptions'!B52
A13: 债务权重 D/(D+E) | B13: ='1_Assumptions'!B101
A14: WACC | B14: =(1-B13)*B8+B13*B11*(1-B12)
A15: 永续增长率 g | B15: ='1_Assumptions'!B103 | H15: Damodaran 规则：g ≤ Rf。当前 Rf 见上方第 1 行
A16: 期中折现开关 | B16: ='1_Assumptions'!B105
A17: SBC 加回开关（0=费用化 1=加回） | B17: ='1_Assumptions'!B113 | H17: 0 = Damodaran（默认）：SBC 是真实成本，不加回；股数也不因 SBC 摊薄
A19: 二、自由现金流 FCFF 与现值
A20: 科目（百万美元） | B20: FY2026E | C20: FY2027E | D20: FY2028E | E20: FY2029E | F20: FY2030E
A21: EBIT（= Operating income） | B21: ='2_Income'!G14 | C21: ='2_Income'!H14 | D21: ='2_Income'!I14 | E21: ='2_Income'!J14 | F21: ='2_Income'!K14
A22: EBIT × (1 − t) | B22: =B21*(1-$B$12) | C22: =C21*(1-$B$12) | D22: =D21*(1-$B$12) | E22: =E21*(1-$B$12) | F22: =F21*(1-$B$12)
A23: + 折旧 | B23: ='4_CashFlow'!G7 | C23: ='4_CashFlow'!H7 | D23: ='4_CashFlow'!I7 | E23: ='4_CashFlow'!J7 | F23: ='4_CashFlow'!K7
A24: + 无形摊销 | B24: ='4_CashFlow'!G8 | C24: ='4_CashFlow'!H8 | D24: ='4_CashFlow'!I8 | E24: ='4_CashFlow'!J8 | F24: ='4_CashFlow'!K8
A25: + SBC（仅在加回口径下） | B25: =IF($B$17=1,'4_CashFlow'!G9,0) | C25: =IF($B$17=1,'4_CashFlow'!H9,0) | D25: =IF($B$17=1,'4_CashFlow'!I9,0) | E25: =IF($B$17=1,'4_CashFlow'!J9,0) | F25: =IF($B$17=1,'4_CashFlow'!K9,0) | H25: 默认 0。加回会同时打开股数的 SBC 摊薄 —— 两件事绑在一起
A26: − 资本开支 | B26: ='4_CashFlow'!G16 | C26: ='4_CashFlow'!H16 | D26: ='4_CashFlow'!I16 | E26: ='4_CashFlow'!J16 | F26: ='4_CashFlow'!K16
A27: 营运资本变动（现金影响） | B27: =SUM('4_CashFlow'!G10:G14) | C27: =SUM('4_CashFlow'!H10:H14) | D27: =SUM('4_CashFlow'!I10:I14) | E27: =SUM('4_CashFlow'!J10:J14) | F27: =SUM('4_CashFlow'!K10:K14)
A28: FCFF | B28: =B22+B23+B24+B25+B26+B27 | C28: =C22+C23+C24+C25+C26+C27 | D28: =D22+D23+D24+D25+D26+D27 | E28: =E22+E23+E24+E25+E26+E27 | F28: =F22+F23+F24+F25+F26+F27
A29: 折现年数 t | B29: 1 | C29: 2 | D29: 3 | E29: 4 | F29: 5
A30: 折现因子 | B30: =1/(1+$B$14)^(B29-0.5*$B$16) | C30: =1/(1+$B$14)^(C29-0.5*$B$16) | D30: =1/(1+$B$14)^(D29-0.5*$B$16) | E30: =1/(1+$B$14)^(E29-0.5*$B$16) | F30: =1/(1+$B$14)^(F29-0.5*$B$16)
A31: FCFF 现值 | B31: =B28*B30 | C31: =C28*C30 | D31: =D28*D30 | E31: =E28*E30 | F31: =F28*F30
A33: 三、终值（Damodaran 一致性：稳态再投资率 = g / ROIC）
A34: 终值所得税率 t_term | B34: ='1_Assumptions'!B104 | H34: 美国联邦法定 21%；永续期不应假设税收优惠永存
A35: FY2030E EBIT | B35: =F21
A36: FY2030E 营运资本 NWC | B36: ='3_Balance'!K31
A37: FY2030E 固定资产净额 | B37: ='3_Balance'!K12
A38: FY2030E 商誉与无形资产 | B38: ='3_Balance'!K14
A39: FY2030E 其他非流动资产 − 其他非流动负债 | B39: ='3_Balance'!K15-'3_Balance'!K23
A40: 投入资本 IC（申报口径） | B40: =B36+B37+B38+B39 | H40: 口径：营运资本 + 固定资产 + 商誉无形 + 其他非流动资产 − 其他非流动负债。旧版只算「营运资本 + 固定资产」，对美股大盘会崩：AAPL 营运资本 −520 亿、商誉无形与其他非流动资产未计入 → IC = −22 亿 → ROIC −4760%，终值被迫降级。本式等价于融资端「有息债务 + 全部权益 − 现金 − 短投 − 长投」；两侧恒等（同一恒等式的重排），属口径自洽性展示，不是独立检错
A41: FY2030E 研发资本（Damodaran） | B41: ='3_Balance'!K33 | H41: 报表外调整项：不进资产总计，只用于投入资本与 ROIC
A42: 生效投入资本 IC | B42: =B40+IF('1_Assumptions'!$B$109=1,B41,0)
A43: 终值 ROIC（计算值） | B43: =B35*(1-B34)/B42 | H43: 把末年超额回报直接永续化
A44: 终值 ROIC（收敛口径） | B44: =B14+'1_Assumptions'!$B$112 | H44: 竞争终将侵蚀超额回报：终值 ROIC = WACC + 溢价
A45: 终值 ROIC（生效） | B45: =IF('1_Assumptions'!$B$111=2,B44,B43) | H45: 必须可持续，否则终值不成立
A46: 稳态再投资率 RR = g / ROIC | B46: =B15/B45 | H46: Damodaran：g = RR × ROIC，三者不可自由设定
A47: 终值 NOPAT = EBIT × (1 − t_term) | B47: =B35*(1-B34) | H47: 用【申报口径】NOPAT：研发资本化只调 ROIC 与 IC，不调 FCFF。稳态下研发支出≈研发摊销，两种口径的 NOPAT 收敛，故此处一致
A48: ★ 终值是否降级（1=是） | B48: =IF(OR(B42<=0,B45<=B14,B46>=1,B46<0),1,0) | H48: 投入资本为负、或 ROIC ≤ WACC、或再投资率越界时，Gordon 式的 (1−g/ROIC) 会失真甚至变号。此时降级为【无增长永续】TV = NOPAT/WACC —— 经济上正确：ROIC 不高于 WACC 时增长不创造价值。修正 IC 口径后，负投入资本这一触发条件对正常经营的公司已不应出现
A49: 终值 FCFF | B49: =IF(B48=1,B47,B35*(1+B15)*(1-B34)*(1-B46))
A50: 终值 TV | B50: =IF(B48=1,B47/B14,B49/(B14-B15)) | H50: 未降级：FCFF终 /(WACC − g) ｜ 已降级：NOPAT / WACC
A51: 终值现值 PV(TV) | B51: =B50/(1+B14)^(5-0.5*B16)
A52: 〔交叉校验〕可持续增长 g =（1−派息率）× ROE | B52: 1.4542 | H52: ⚠ 本例不可用：ROE 171% > 50%，多半是长期回购把账面权益冲小所致，公式失效
A54: 四、企业价值 → 每股内在价值
A55: 明确期 FCFF 现值合计 | B55: =SUM(B31:F31)
A56: 终值现值 | B56: =B51
A57: 企业价值 EV（2025-09-27 基准） | B57: =B55+B56
A58: 估值基准日滚动年数 | B58: ='1_Assumptions'!B106 | H58: 财年末 → 评估日。非 12-31 财年在此体现
A59: 企业价值 EV（滚动至评估日） | B59: =B57*(1+B14)^B58-B28*B58*(1+B14)^(B58/2) | H59: 滚动后扣除财年末至评估日已实现的自由现金流
A60: 减：净负债（基期） | B60: ='1_Assumptions'!B80+'1_Assumptions'!B79+'1_Assumptions'!B81-'1_Assumptions'!B68-'1_Assumptions'!B69 | H60: 经营租赁负债【不】计入 —— ASC 842 下租金已在 EBIT 内扣除，再计入即重复扣
A61: 加：非经营资产 | B61: ='1_Assumptions'!B107 | H61: 长期有价证券与权益法投资（短期投资已在净负债中扣除）
A62: 加：增发募资净额（现值） | B62: ='1_Assumptions'!B135/(1+B14)^'1_Assumptions'!B136 | H62: 净负债按基期计量，未来募资的现金对 EV 不可见，必须单列
A63: 归属全体股东权益价值 | B63: =B59-B60+B61+B62
A64: 少数股东扣除方式 | B64: ='1_Assumptions'!B108
A65: 少数股东利润占比 | B65: ='1_Assumptions'!B53
A66: 减：少数股东权益 | B66: =IF(B64=1,'1_Assumptions'!B83,B63*B65)
A67: 归母股权价值 | B67: =B63-B66
A68: 当前摊薄股数（百万股，含增发） | B68: ='1_Assumptions'!B88+'1_Assumptions'!B130 | H68: 用【当前】股数而非终值年股数：FCFF 是融资前口径，回购属于融资决策，不改变今天的企业价值；回购对未来 EPS 的影响见「2_Income」
A69: 每股内在价值 | B69: =B67/B68
A70: 现价 | B70: ='1_Assumptions'!B89
A71: 上行 / 下行空间 | B71: =B69/B70-1
A72: 终值占 EV 比重 | B72: =B56/B57 | H72: 超过 75% 说明估值高度依赖终值假设
A74: 五、退出倍数交叉验证（FINC6021 Ch.8：倍数与 DCF 是同一件事）
A75: FY2030E EBITDA | B75: =B35+F23+F24
A76: 模型隐含的退出 EV/EBITDA | B76: =B50/B75 | H76: 由 Gordon 终值反解。若远高于同业成熟公司的 EV/EBITDA，说明终值假设过于乐观
A77: FY2030E 归母净利 | B77: ='2_Income'!K22
A78: 模型隐含的退出 P/E（终值权益 / 终值净利） | B78: =(B50-('1_Assumptions'!B80+'1_Assumptions'!B79+'1_Assumptions'!B81))/B77 | H78: 粗略口径：终值 EV 扣基期有息负债。仅作量级对照
A79: 理论倍数 = (1+g)/(WACC − g) | B79: =(1+B15)/(B14-B15) | H79: 课程：资本化率 = 1/倍数 < 折现率；增长越高，两者差距越大
A81: 六、资本结构漂移诊断（FINC6021 Ch.4：WACC 假定资本结构恒定）
A82: 年度 | B82: FY2026E | C82: FY2027E | D82: FY2028E | E82: FY2029E | F82: FY2030E
A83: 模型内含有息负债 | B83: ='3_Balance'!G18+'3_Balance'!G19+'3_Balance'!G21 | C83: ='3_Balance'!H18+'3_Balance'!H19+'3_Balance'!H21 | D83: ='3_Balance'!I18+'3_Balance'!I19+'3_Balance'!I21 | E83: ='3_Balance'!J18+'3_Balance'!J19+'3_Balance'!J21 | F83: ='3_Balance'!K18+'3_Balance'!K19+'3_Balance'!K21
A84: 股权（按现价 × 滚动股数） | B84: ='1_Assumptions'!$B$89*'4_CashFlow'!G30 | C84: ='1_Assumptions'!$B$89*'4_CashFlow'!H30 | D84: ='1_Assumptions'!$B$89*'4_CashFlow'!I30 | E84: ='1_Assumptions'!$B$89*'4_CashFlow'!J30 | F84: ='1_Assumptions'!$B$89*'4_CashFlow'!K30
A85: 模型内含 D/(D+E) | B85: =B83/(B83+B84) | C85: =C83/(C83+C84) | D85: =D83/(D83+D84) | E85: =E83/(E83+E84) | F85: =F83/(F83+F84)
A86: 与 WACC 假设权重的差 | B86: =B85-$B$13 | C86: =C85-$B$13 | D86: =D85-$B$13 | E86: =E85-$B$13 | F86: =F85-$B$13 | H86: Plug 选的是现金 + 循环贷，资本结构会漂移；WACC 却假定它恒定。差距大到一定程度就该改用目标资本结构，并对 β 做去杠杆/再杠杆
A88: 七、敏感性：每股内在价值（行 = WACC，列 = 永续增长率 g）
A89: WACC \ g | B89: 0.015 | C89: 0.02 | D89: 0.025 | E89: 0.03 | F89: 0.035
A90: =$B$14+-0.02 | B90: =(((($B$28/(1+$A90)^(1-0.5*$B$16)+$C$28/(1+$A90)^(2-0.5*$B$16)+$D$28/(1+$A90)^(3-0.5*$B$16)+$E$28/(1+$A90)^(4-0.5*$B$16)+$F$28/(1+$A90)^(5-0.5*$B$16))+(IF(OR($B$42<=0,($B$35*(1-$B$34)/$B$42)<=$A90,(B$89/($B$35*(1-$B$34)/$B$42))>=1,(B$89/($B$35*(1-$B$34)/$B$42))<0),($B$35*(1-$B$34))/$A90,$B$35*(1+B$89)*(1-$B$34)*(1-(B$89/($B$35*(1-$B$34)/$B$42)))/($A90-B$89)))/(1+$A90)^(5-0.5*$B$16))*(1+$A90)^$B$58-$B$28*$B$58*(1+$A90)^($B$58/2)-$B$60+$B$61+$B$62)*(1-IF($B$64=1,0,$B$65))-IF($B$64=1,'1_Assumptions'!$B$83,0))/$B$68 | C90: =(((($B$28/(1+$A90)^(1-0.5*$B$16)+$C$28/(1+$A90)^(2-0.5*$B$16)+$D$28/(1+$A90)^(3-0.5*$B$16)+$E$28/(1+$A90)^(4-0.5*$B$16)+$F$28/(1+$A90)^(5-0.5*$B$16))+(IF(OR($B$42<=0,($B$35*(1-$B$34)/$B$42)<=$A90,(C$89/($B$35*(1-$B$34)/$B$42))>=1,(C$89/($B$35*(1-$B$34)/$B$42))<0),($B$35*(1-$B$34))/$A90,$B$35*(1+C$89)*(1-$B$34)*(1-(C$89/($B$35*(1-$B$34)/$B$42)))/($A90-C$89)))/(1+$A90)^(5-0.5*$B$16))*(1+$A90)^$B$58-$B$28*$B$58*(1+$A90)^($B$58/2)-$B$60+$B$61+$B$62)*(1-IF($B$64=1,0,$B$65))-IF($B$64=1,'1_Assumptions'!$B$83,0))/$B$68 | D90: =(((($B$28/(1+$A90)^(1-0.5*$B$16)+$C$28/(1+$A90)^(2-0.5*$B$16)+$D$28/(1+$A90)^(3-0.5*$B$16)+$E$28/(1+$A90)^(4-0.5*$B$16)+$F$28/(1+$A90)^(5-0.5*$B$16))+(IF(OR($B$42<=0,($B$35*(1-$B$34)/$B$42)<=$A90,(D$89/($B$35*(1-$B$34)/$B$42))>=1,(D$89/($B$35*(1-$B$34)/$B$42))<0),($B$35*(1-$B$34))/$A90,$B$35*(1+D$89)*(1-$B$34)*(1-(D$89/($B$35*(1-$B$34)/$B$42)))/($A90-D$89)))/(1+$A90)^(5-0.5*$B$16))*(1+$A90)^$B$58-$B$28*$B$58*(1+$A90)^($B$58/2)-$B$60+$B$61+$B$62)*(1-IF($B$64=1,0,$B$65))-IF($B$64=1,'1_Assumptions'!$B$83,0))/$B$68 | E90: =(((($B$28/(1+$A90)^(1-0.5*$B$16)+$C$28/(1+$A90)^(2-0.5*$B$16)+$D$28/(1+$A90)^(3-0.5*$B$16)+$E$28/(1+$A90)^(4-0.5*$B$16)+$F$28/(1+$A90)^(5-0.5*$B$16))+(IF(OR($B$42<=0,($B$35*(1-$B$34)/$B$42)<=$A90,(E$89/($B$35*(1-$B$34)/$B$42))>=1,(E$89/($B$35*(1-$B$34)/$B$42))<0),($B$35*(1-$B$34))/$A90,$B$35*(1+E$89)*(1-$B$34)*(1-(E$89/($B$35*(1-$B$34)/$B$42)))/($A90-E$89)))/(1+$A90)^(5-0.5*$B$16))*(1+$A90)^$B$58-$B$28*$B$58*(1+$A90)^($B$58/2)-$B$60+$B$61+$B$62)*(1-IF($B$64=1,0,$B$65))-IF($B$64=1,'1_Assumptions'!$B$83,0))/$B$68 | F90: =(((($B$28/(1+$A90)^(1-0.5*$B$16)+$C$28/(1+$A90)^(2-0.5*$B$16)+$D$28/(1+$A90)^(3-0.5*$B$16)+$E$28/(1+$A90)^(4-0.5*$B$16)+$F$28/(1+$A90)^(5-0.5*$B$16))+(IF(OR($B$42<=0,($B$35*(1-$B$34)/$B$42)<=$A90,(F$89/($B$35*(1-$B$34)/$B$42))>=1,(F$89/($B$35*(1-$B$34)/$B$42))<0),($B$35*(1-$B$34))/$A90,$B$35*(1+F$89)*(1-$B$34)*(1-(F$89/($B$35*(1-$B$34)/$B$42)))/($A90-F$89)))/(1+$A90)^(5-0.5*$B$16))*(1+$A90)^$B$58-$B$28*$B$58*(1+$A90)^($B$58/2)-$B$60+$B$61+$B$62)*(1-IF($B$64=1,0,$B$65))-IF($B$64=1,'1_Assumptions'!$B$83,0))/$B$68
A91: =$B$14+-0.01 | B91: =(((($B$28/(1+$A91)^(1-0.5*$B$16)+$C$28/(1+$A91)^(2-0.5*$B$16)+$D$28/(1+$A91)^(3-0.5*$B$16)+$E$28/(1+$A91)^(4-0.5*$B$16)+$F$28/(1+$A91)^(5-0.5*$B$16))+(IF(OR($B$42<=0,($B$35*(1-$B$34)/$B$42)<=$A91,(B$89/($B$35*(1-$B$34)/$B$42))>=1,(B$89/($B$35*(1-$B$34)/$B$42))<0),($B$35*(1-$B$34))/$A91,$B$35*(1+B$89)*(1-$B$34)*(1-(B$89/($B$35*(1-$B$34)/$B$42)))/($A91-B$89)))/(1+$A91)^(5-0.5*$B$16))*(1+$A91)^$B$58-$B$28*$B$58*(1+$A91)^($B$58/2)-$B$60+$B$61+$B$62)*(1-IF($B$64=1,0,$B$65))-IF($B$64=1,'1_Assumptions'!$B$83,0))/$B$68 | C91: =(((($B$28/(1+$A91)^(1-0.5*$B$16)+$C$28/(1+$A91)^(2-0.5*$B$16)+$D$28/(1+$A91)^(3-0.5*$B$16)+$E$28/(1+$A91)^(4-0.5*$B$16)+$F$28/(1+$A91)^(5-0.5*$B$16))+(IF(OR($B$42<=0,($B$35*(1-$B$34)/$B$42)<=$A91,(C$89/($B$35*(1-$B$34)/$B$42))>=1,(C$89/($B$35*(1-$B$34)/$B$42))<0),($B$35*(1-$B$34))/$A91,$B$35*(1+C$89)*(1-$B$34)*(1-(C$89/($B$35*(1-$B$34)/$B$42)))/($A91-C$89)))/(1+$A91)^(5-0.5*$B$16))*(1+$A91)^$B$58-$B$28*$B$58*(1+$A91)^($B$58/2)-$B$60+$B$61+$B$62)*(1-IF($B$64=1,0,$B$65))-IF($B$64=1,'1_Assumptions'!$B$83,0))/$B$68 | D91: =(((($B$28/(1+$A91)^(1-0.5*$B$16)+$C$28/(1+$A91)^(2-0.5*$B$16)+$D$28/(1+$A91)^(3-0.5*$B$16)+$E$28/(1+$A91)^(4-0.5*$B$16)+$F$28/(1+$A91)^(5-0.5*$B$16))+(IF(OR($B$42<=0,($B$35*(1-$B$34)/$B$42)<=$A91,(D$89/($B$35*(1-$B$34)/$B$42))>=1,(D$89/($B$35*(1-$B$34)/$B$42))<0),($B$35*(1-$B$34))/$A91,$B$35*(1+D$89)*(1-$B$34)*(1-(D$89/($B$35*(1-$B$34)/$B$42)))/($A91-D$89)))/(1+$A91)^(5-0.5*$B$16))*(1+$A91)^$B$58-$B$28*$B$58*(1+$A91)^($B$58/2)-$B$60+$B$61+$B$62)*(1-IF($B$64=1,0,$B$65))-IF($B$64=1,'1_Assumptions'!$B$83,0))/$B$68 | E91: =(((($B$28/(1+$A91)^(1-0.5*$B$16)+$C$28/(1+$A91)^(2-0.5*$B$16)+$D$28/(1+$A91)^(3-0.5*$B$16)+$E$28/(1+$A91)^(4-0.5*$B$16)+$F$28/(1+$A91)^(5-0.5*$B$16))+(IF(OR($B$42<=0,($B$35*(1-$B$34)/$B$42)<=$A91,(E$89/($B$35*(1-$B$34)/$B$42))>=1,(E$89/($B$35*(1-$B$34)/$B$42))<0),($B$35*(1-$B$34))/$A91,$B$35*(1+E$89)*(1-$B$34)*(1-(E$89/($B$35*(1-$B$34)/$B$42)))/($A91-E$89)))/(1+$A91)^(5-0.5*$B$16))*(1+$A91)^$B$58-$B$28*$B$58*(1+$A91)^($B$58/2)-$B$60+$B$61+$B$62)*(1-IF($B$64=1,0,$B$65))-IF($B$64=1,'1_Assumptions'!$B$83,0))/$B$68 | F91: =(((($B$28/(1+$A91)^(1-0.5*$B$16)+$C$28/(1+$A91)^(2-0.5*$B$16)+$D$28/(1+$A91)^(3-0.5*$B$16)+$E$28/(1+$A91)^(4-0.5*$B$16)+$F$28/(1+$A91)^(5-0.5*$B$16))+(IF(OR($B$42<=0,($B$35*(1-$B$34)/$B$42)<=$A91,(F$89/($B$35*(1-$B$34)/$B$42))>=1,(F$89/($B$35*(1-$B$34)/$B$42))<0),($B$35*(1-$B$34))/$A91,$B$35*(1+F$89)*(1-$B$34)*(1-(F$89/($B$35*(1-$B$34)/$B$42)))/($A91-F$89)))/(1+$A91)^(5-0.5*$B$16))*(1+$A91)^$B$58-$B$28*$B$58*(1+$A91)^($B$58/2)-$B$60+$B$61+$B$62)*(1-IF($B$64=1,0,$B$65))-IF($B$64=1,'1_Assumptions'!$B$83,0))/$B$68
A92: =$B$14+0.0 | B92: =(((($B$28/(1+$A92)^(1-0.5*$B$16)+$C$28/(1+$A92)^(2-0.5*$B$16)+$D$28/(1+$A92)^(3-0.5*$B$16)+$E$28/(1+$A92)^(4-0.5*$B$16)+$F$28/(1+$A92)^(5-0.5*$B$16))+(IF(OR($B$42<=0,($B$35*(1-$B$34)/$B$42)<=$A92,(B$89/($B$35*(1-$B$34)/$B$42))>=1,(B$89/($B$35*(1-$B$34)/$B$42))<0),($B$35*(1-$B$34))/$A92,$B$35*(1+B$89)*(1-$B$34)*(1-(B$89/($B$35*(1-$B$34)/$B$42)))/($A92-B$89)))/(1+$A92)^(5-0.5*$B$16))*(1+$A92)^$B$58-$B$28*$B$58*(1+$A92)^($B$58/2)-$B$60+$B$61+$B$62)*(1-IF($B$64=1,0,$B$65))-IF($B$64=1,'1_Assumptions'!$B$83,0))/$B$68 | C92: =(((($B$28/(1+$A92)^(1-0.5*$B$16)+$C$28/(1+$A92)^(2-0.5*$B$16)+$D$28/(1+$A92)^(3-0.5*$B$16)+$E$28/(1+$A92)^(4-0.5*$B$16)+$F$28/(1+$A92)^(5-0.5*$B$16))+(IF(OR($B$42<=0,($B$35*(1-$B$34)/$B$42)<=$A92,(C$89/($B$35*(1-$B$34)/$B$42))>=1,(C$89/($B$35*(1-$B$34)/$B$42))<0),($B$35*(1-$B$34))/$A92,$B$35*(1+C$89)*(1-$B$34)*(1-(C$89/($B$35*(1-$B$34)/$B$42)))/($A92-C$89)))/(1+$A92)^(5-0.5*$B$16))*(1+$A92)^$B$58-$B$28*$B$58*(1+$A92)^($B$58/2)-$B$60+$B$61+$B$62)*(1-IF($B$64=1,0,$B$65))-IF($B$64=1,'1_Assumptions'!$B$83,0))/$B$68 | D92: =(((($B$28/(1+$A92)^(1-0.5*$B$16)+$C$28/(1+$A92)^(2-0.5*$B$16)+$D$28/(1+$A92)^(3-0.5*$B$16)+$E$28/(1+$A92)^(4-0.5*$B$16)+$F$28/(1+$A92)^(5-0.5*$B$16))+(IF(OR($B$42<=0,($B$35*(1-$B$34)/$B$42)<=$A92,(D$89/($B$35*(1-$B$34)/$B$42))>=1,(D$89/($B$35*(1-$B$34)/$B$42))<0),($B$35*(1-$B$34))/$A92,$B$35*(1+D$89)*(1-$B$34)*(1-(D$89/($B$35*(1-$B$34)/$B$42)))/($A92-D$89)))/(1+$A92)^(5-0.5*$B$16))*(1+$A92)^$B$58-$B$28*$B$58*(1+$A92)^($B$58/2)-$B$60+$B$61+$B$62)*(1-IF($B$64=1,0,$B$65))-IF($B$64=1,'1_Assumptions'!$B$83,0))/$B$68 | E92: =(((($B$28/(1+$A92)^(1-0.5*$B$16)+$C$28/(1+$A92)^(2-0.5*$B$16)+$D$28/(1+$A92)^(3-0.5*$B$16)+$E$28/(1+$A92)^(4-0.5*$B$16)+$F$28/(1+$A92)^(5-0.5*$B$16))+(IF(OR($B$42<=0,($B$35*(1-$B$34)/$B$42)<=$A92,(E$89/($B$35*(1-$B$34)/$B$42))>=1,(E$89/($B$35*(1-$B$34)/$B$42))<0),($B$35*(1-$B$34))/$A92,$B$35*(1+E$89)*(1-$B$34)*(1-(E$89/($B$35*(1-$B$34)/$B$42)))/($A92-E$89)))/(1+$A92)^(5-0.5*$B$16))*(1+$A92)^$B$58-$B$28*$B$58*(1+$A92)^($B$58/2)-$B$60+$B$61+$B$62)*(1-IF($B$64=1,0,$B$65))-IF($B$64=1,'1_Assumptions'!$B$83,0))/$B$68 | F92: =(((($B$28/(1+$A92)^(1-0.5*$B$16)+$C$28/(1+$A92)^(2-0.5*$B$16)+$D$28/(1+$A92)^(3-0.5*$B$16)+$E$28/(1+$A92)^(4-0.5*$B$16)+$F$28/(1+$A92)^(5-0.5*$B$16))+(IF(OR($B$42<=0,($B$35*(1-$B$34)/$B$42)<=$A92,(F$89/($B$35*(1-$B$34)/$B$42))>=1,(F$89/($B$35*(1-$B$34)/$B$42))<0),($B$35*(1-$B$34))/$A92,$B$35*(1+F$89)*(1-$B$34)*(1-(F$89/($B$35*(1-$B$34)/$B$42)))/($A92-F$89)))/(1+$A92)^(5-0.5*$B$16))*(1+$A92)^$B$58-$B$28*$B$58*(1+$A92)^($B$58/2)-$B$60+$B$61+$B$62)*(1-IF($B$64=1,0,$B$65))-IF($B$64=1,'1_Assumptions'!$B$83,0))/$B$68
A93: =$B$14+0.01 | B93: =(((($B$28/(1+$A93)^(1-0.5*$B$16)+$C$28/(1+$A93)^(2-0.5*$B$16)+$D$28/(1+$A93)^(3-0.5*$B$16)+$E$28/(1+$A93)^(4-0.5*$B$16)+$F$28/(1+$A93)^(5-0.5*$B$16))+(IF(OR($B$42<=0,($B$35*(1-$B$34)/$B$42)<=$A93,(B$89/($B$35*(1-$B$34)/$B$42))>=1,(B$89/($B$35*(1-$B$34)/$B$42))<0),($B$35*(1-$B$34))/$A93,$B$35*(1+B$89)*(1-$B$34)*(1-(B$89/($B$35*(1-$B$34)/$B$42)))/($A93-B$89)))/(1+$A93)^(5-0.5*$B$16))*(1+$A93)^$B$58-$B$28*$B$58*(1+$A93)^($B$58/2)-$B$60+$B$61+$B$62)*(1-IF($B$64=1,0,$B$65))-IF($B$64=1,'1_Assumptions'!$B$83,0))/$B$68 | C93: =(((($B$28/(1+$A93)^(1-0.5*$B$16)+$C$28/(1+$A93)^(2-0.5*$B$16)+$D$28/(1+$A93)^(3-0.5*$B$16)+$E$28/(1+$A93)^(4-0.5*$B$16)+$F$28/(1+$A93)^(5-0.5*$B$16))+(IF(OR($B$42<=0,($B$35*(1-$B$34)/$B$42)<=$A93,(C$89/($B$35*(1-$B$34)/$B$42))>=1,(C$89/($B$35*(1-$B$34)/$B$42))<0),($B$35*(1-$B$34))/$A93,$B$35*(1+C$89)*(1-$B$34)*(1-(C$89/($B$35*(1-$B$34)/$B$42)))/($A93-C$89)))/(1+$A93)^(5-0.5*$B$16))*(1+$A93)^$B$58-$B$28*$B$58*(1+$A93)^($B$58/2)-$B$60+$B$61+$B$62)*(1-IF($B$64=1,0,$B$65))-IF($B$64=1,'1_Assumptions'!$B$83,0))/$B$68 | D93: =(((($B$28/(1+$A93)^(1-0.5*$B$16)+$C$28/(1+$A93)^(2-0.5*$B$16)+$D$28/(1+$A93)^(3-0.5*$B$16)+$E$28/(1+$A93)^(4-0.5*$B$16)+$F$28/(1+$A93)^(5-0.5*$B$16))+(IF(OR($B$42<=0,($B$35*(1-$B$34)/$B$42)<=$A93,(D$89/($B$35*(1-$B$34)/$B$42))>=1,(D$89/($B$35*(1-$B$34)/$B$42))<0),($B$35*(1-$B$34))/$A93,$B$35*(1+D$89)*(1-$B$34)*(1-(D$89/($B$35*(1-$B$34)/$B$42)))/($A93-D$89)))/(1+$A93)^(5-0.5*$B$16))*(1+$A93)^$B$58-$B$28*$B$58*(1+$A93)^($B$58/2)-$B$60+$B$61+$B$62)*(1-IF($B$64=1,0,$B$65))-IF($B$64=1,'1_Assumptions'!$B$83,0))/$B$68 | E93: =(((($B$28/(1+$A93)^(1-0.5*$B$16)+$C$28/(1+$A93)^(2-0.5*$B$16)+$D$28/(1+$A93)^(3-0.5*$B$16)+$E$28/(1+$A93)^(4-0.5*$B$16)+$F$28/(1+$A93)^(5-0.5*$B$16))+(IF(OR($B$42<=0,($B$35*(1-$B$34)/$B$42)<=$A93,(E$89/($B$35*(1-$B$34)/$B$42))>=1,(E$89/($B$35*(1-$B$34)/$B$42))<0),($B$35*(1-$B$34))/$A93,$B$35*(1+E$89)*(1-$B$34)*(1-(E$89/($B$35*(1-$B$34)/$B$42)))/($A93-E$89)))/(1+$A93)^(5-0.5*$B$16))*(1+$A93)^$B$58-$B$28*$B$58*(1+$A93)^($B$58/2)-$B$60+$B$61+$B$62)*(1-IF($B$64=1,0,$B$65))-IF($B$64=1,'1_Assumptions'!$B$83,0))/$B$68 | F93: =(((($B$28/(1+$A93)^(1-0.5*$B$16)+$C$28/(1+$A93)^(2-0.5*$B$16)+$D$28/(1+$A93)^(3-0.5*$B$16)+$E$28/(1+$A93)^(4-0.5*$B$16)+$F$28/(1+$A93)^(5-0.5*$B$16))+(IF(OR($B$42<=0,($B$35*(1-$B$34)/$B$42)<=$A93,(F$89/($B$35*(1-$B$34)/$B$42))>=1,(F$89/($B$35*(1-$B$34)/$B$42))<0),($B$35*(1-$B$34))/$A93,$B$35*(1+F$89)*(1-$B$34)*(1-(F$89/($B$35*(1-$B$34)/$B$42)))/($A93-F$89)))/(1+$A93)^(5-0.5*$B$16))*(1+$A93)^$B$58-$B$28*$B$58*(1+$A93)^($B$58/2)-$B$60+$B$61+$B$62)*(1-IF($B$64=1,0,$B$65))-IF($B$64=1,'1_Assumptions'!$B$83,0))/$B$68
A94: =$B$14+0.02 | B94: =(((($B$28/(1+$A94)^(1-0.5*$B$16)+$C$28/(1+$A94)^(2-0.5*$B$16)+$D$28/(1+$A94)^(3-0.5*$B$16)+$E$28/(1+$A94)^(4-0.5*$B$16)+$F$28/(1+$A94)^(5-0.5*$B$16))+(IF(OR($B$42<=0,($B$35*(1-$B$34)/$B$42)<=$A94,(B$89/($B$35*(1-$B$34)/$B$42))>=1,(B$89/($B$35*(1-$B$34)/$B$42))<0),($B$35*(1-$B$34))/$A94,$B$35*(1+B$89)*(1-$B$34)*(1-(B$89/($B$35*(1-$B$34)/$B$42)))/($A94-B$89)))/(1+$A94)^(5-0.5*$B$16))*(1+$A94)^$B$58-$B$28*$B$58*(1+$A94)^($B$58/2)-$B$60+$B$61+$B$62)*(1-IF($B$64=1,0,$B$65))-IF($B$64=1,'1_Assumptions'!$B$83,0))/$B$68 | C94: =(((($B$28/(1+$A94)^(1-0.5*$B$16)+$C$28/(1+$A94)^(2-0.5*$B$16)+$D$28/(1+$A94)^(3-0.5*$B$16)+$E$28/(1+$A94)^(4-0.5*$B$16)+$F$28/(1+$A94)^(5-0.5*$B$16))+(IF(OR($B$42<=0,($B$35*(1-$B$34)/$B$42)<=$A94,(C$89/($B$35*(1-$B$34)/$B$42))>=1,(C$89/($B$35*(1-$B$34)/$B$42))<0),($B$35*(1-$B$34))/$A94,$B$35*(1+C$89)*(1-$B$34)*(1-(C$89/($B$35*(1-$B$34)/$B$42)))/($A94-C$89)))/(1+$A94)^(5-0.5*$B$16))*(1+$A94)^$B$58-$B$28*$B$58*(1+$A94)^($B$58/2)-$B$60+$B$61+$B$62)*(1-IF($B$64=1,0,$B$65))-IF($B$64=1,'1_Assumptions'!$B$83,0))/$B$68 | D94: =(((($B$28/(1+$A94)^(1-0.5*$B$16)+$C$28/(1+$A94)^(2-0.5*$B$16)+$D$28/(1+$A94)^(3-0.5*$B$16)+$E$28/(1+$A94)^(4-0.5*$B$16)+$F$28/(1+$A94)^(5-0.5*$B$16))+(IF(OR($B$42<=0,($B$35*(1-$B$34)/$B$42)<=$A94,(D$89/($B$35*(1-$B$34)/$B$42))>=1,(D$89/($B$35*(1-$B$34)/$B$42))<0),($B$35*(1-$B$34))/$A94,$B$35*(1+D$89)*(1-$B$34)*(1-(D$89/($B$35*(1-$B$34)/$B$42)))/($A94-D$89)))/(1+$A94)^(5-0.5*$B$16))*(1+$A94)^$B$58-$B$28*$B$58*(1+$A94)^($B$58/2)-$B$60+$B$61+$B$62)*(1-IF($B$64=1,0,$B$65))-IF($B$64=1,'1_Assumptions'!$B$83,0))/$B$68 | E94: =(((($B$28/(1+$A94)^(1-0.5*$B$16)+$C$28/(1+$A94)^(2-0.5*$B$16)+$D$28/(1+$A94)^(3-0.5*$B$16)+$E$28/(1+$A94)^(4-0.5*$B$16)+$F$28/(1+$A94)^(5-0.5*$B$16))+(IF(OR($B$42<=0,($B$35*(1-$B$34)/$B$42)<=$A94,(E$89/($B$35*(1-$B$34)/$B$42))>=1,(E$89/($B$35*(1-$B$34)/$B$42))<0),($B$35*(1-$B$34))/$A94,$B$35*(1+E$89)*(1-$B$34)*(1-(E$89/($B$35*(1-$B$34)/$B$42)))/($A94-E$89)))/(1+$A94)^(5-0.5*$B$16))*(1+$A94)^$B$58-$B$28*$B$58*(1+$A94)^($B$58/2)-$B$60+$B$61+$B$62)*(1-IF($B$64=1,0,$B$65))-IF($B$64=1,'1_Assumptions'!$B$83,0))/$B$68 | F94: =(((($B$28/(1+$A94)^(1-0.5*$B$16)+$C$28/(1+$A94)^(2-0.5*$B$16)+$D$28/(1+$A94)^(3-0.5*$B$16)+$E$28/(1+$A94)^(4-0.5*$B$16)+$F$28/(1+$A94)^(5-0.5*$B$16))+(IF(OR($B$42<=0,($B$35*(1-$B$34)/$B$42)<=$A94,(F$89/($B$35*(1-$B$34)/$B$42))>=1,(F$89/($B$35*(1-$B$34)/$B$42))<0),($B$35*(1-$B$34))/$A94,$B$35*(1+F$89)*(1-$B$34)*(1-(F$89/($B$35*(1-$B$34)/$B$42)))/($A94-F$89)))/(1+$A94)^(5-0.5*$B$16))*(1+$A94)^$B$58-$B$28*$B$58*(1+$A94)^($B$58/2)-$B$60+$B$61+$B$62)*(1-IF($B$64=1,0,$B$65))-IF($B$64=1,'1_Assumptions'!$B$83,0))/$B$68
A95: ★ 中心格（生效 WACC，且 g = 生效值）应等于上方「每股内在价值」
A97: 模块 A：营收增速平移 × 永续增长率 g — 每股内在价值
A98: Δ 施加在每一年的生效增速上；中心格 Δ=0 且 g=生效值，必然复现基准每股价值
A99: 营收增速 Δ \ 永续 g | B99: 0.01 | C99: 0.0175 | D99: 0.025 | E99: 0.0325 | F99: 0.04
A100: ='6_Engine'!$B$38 | B100: ='6_Engine'!BU38 | C100: ='6_Engine'!BU39 | D100: ='6_Engine'!BU40 | E100: ='6_Engine'!BU41 | F100: ='6_Engine'!BU42
A101: ='6_Engine'!$B$43 | B101: ='6_Engine'!BU43 | C101: ='6_Engine'!BU44 | D101: ='6_Engine'!BU45 | E101: ='6_Engine'!BU46 | F101: ='6_Engine'!BU47
A102: ='6_Engine'!$B$48 | B102: ='6_Engine'!BU48 | C102: ='6_Engine'!BU49 | D102: ='6_Engine'!BU50 | E102: ='6_Engine'!BU51 | F102: ='6_Engine'!BU52
A103: ='6_Engine'!$B$53 | B103: ='6_Engine'!BU53 | C103: ='6_Engine'!BU54 | D103: ='6_Engine'!BU55 | E103: ='6_Engine'!BU56 | F103: ='6_Engine'!BU57
A104: ='6_Engine'!$B$58 | B104: ='6_Engine'!BU58 | C104: ='6_Engine'!BU59 | D104: ='6_Engine'!BU60 | E104: ='6_Engine'!BU61 | F104: ='6_Engine'!BU62
A105: ★ 中心格自检（应为 0） | B105: ='6_Engine'!BU50-B69
A107: 模块 B：毛利率平移 × 永续增长率 g — 每股内在价值
A108: 毛利率是判断项里最敏感的一个：1pp 的持续偏差会被终值放大
A109: 毛利率 Δ \ 永续 g | B109: 0.01 | C109: 0.0175 | D109: 0.025 | E109: 0.0325 | F109: 0.04
...

Sheet 6_Engine
A1: AAPL — 敏感性引擎（每行 = 一次完整 5 年 FCFF 重算）
A2: 本页是计算中间层，不需手工编辑。「5_DCF」的敏感性表从这里取数；改「1_Assumptions」后本页自动重算。
A4: 基期锚点与生效参数
A5: 基期营业收入 | B5: ='1_Assumptions'!$B$87
A6: 期初固定资产净额 | B6: ='1_Assumptions'!$B$73
A7: 期初商誉与无形 | B7: ='1_Assumptions'!$B$75
A8: 期初研发资本 | B8: ='1_Assumptions'!$B$86
A9: 其他非流动资产净额 | B9: ='1_Assumptions'!$B$76-'1_Assumptions'!$B$82
A10: 期初 NWC | B10: ='1_Assumptions'!$B$70+'1_Assumptions'!$B$71+'1_Assumptions'!$B$72-'1_Assumptions'!$B$77-'1_Assumptions'!$B$78
A11: 经营费用率合计 | B11: ='1_Assumptions'!$B$49+'1_Assumptions'!$B$50
A12: 其他经营损益率 | B12: ='1_Assumptions'!$B$51
A13: 折旧率 | B13: ='1_Assumptions'!$B$59
A14: 无形摊销率 | B14: ='1_Assumptions'!$B$60
A15: 有效税率 | B15: ='1_Assumptions'!$B$52
A16: 研发费用率 | B16: ='1_Assumptions'!$B$49
A17: 研发资本化开关 | B17: ='1_Assumptions'!B109
A18: 研发摊销年限 | B18: ='1_Assumptions'!B110
A19: SBC 加回开关 | B19: ='1_Assumptions'!B113
A20: 终值税率 | B20: ='5_DCF'!B34
A21: WACC（生效） | B21: ='5_DCF'!B14
A22: 永续 g（生效） | B22: ='5_DCF'!B15
A23: 期中折现开关 | B23: ='5_DCF'!B16
A24: 滚动年数 | B24: ='5_DCF'!B58
A25: 净负债 | B25: ='5_DCF'!B60
A26: 非经营资产 | B26: ='5_DCF'!B61
A27: 募资净额现值 | B27: ='5_DCF'!B62
A28: 少数股东方式 | B28: ='5_DCF'!B64
A29: 少数股东占比 | B29: ='5_DCF'!B65
A30: 账面少数股东权益 | B30: ='1_Assumptions'!$B$83
A31: 总股本 | B31: ='5_DCF'!B68
A32: 终值ROIC模式 | B32: ='1_Assumptions'!B111
A33: 终值ROIC溢价 | B33: ='1_Assumptions'!B112
A35: 模块 A：营收增速平移 × 永续增长率 g
A36: Δ 施加在每一年的生效增速上；中心格 Δ=0 且 g=生效值，必然复现基准每股价值
A37: 场景 | B37: 营收增速 Δ | C37: 永续 g | D37: 营收1 | E37: 成本1 | F37: EBIT1 | G37: 折旧1 | H37: 资本开支1 | I37: 期末固资1 | J37: 摊销1 | K37: 商誉无形1 | L37: 研发资本1 | M37: NWC1 | N37: FCFF1 | O37: 营收2 | P37: 成本2 | Q37: EBIT2 | R37: 折旧2 | S37: 资本开支2 | T37: 期末固资2 | U37: 摊销2 | V37: 商誉无形2 | W37: 研发资本2 | X37: NWC2 | Y37: FCFF2 | Z37: 营收3 | AA37: 成本3 | AB37: EBIT3 | AC37: 折旧3 | AD37: 资本开支3 | AE37: 期末固资3 | AF37: 摊销3 | AG37: 商誉无形3 | AH37: 研发资本3 | AI37: NWC3 | AJ37: FCFF3 | AK37: 营收4 | AL37: 成本4 | AM37: EBIT4 | AN37: 折旧4 | AO37: 资本开支4 | AP37: 期末固资4 | AQ37: 摊销4 | AR37: 商誉无形4 | AS37: 研发资本4 | AT37: NWC4 | AU37: FCFF4 | AV37: 营收5 | AW37: 成本5 | AX37: EBIT5 | AY37: 折旧5 | AZ37: 资本开支5 | BA37: 期末固资5 | BB37: 摊销5 | BC37: 商誉无形5 | BD37: 研发资本5 | BE37: NWC5 | BF37: FCFF5 | BG37: PV明确期 | BH37: 终值IC | BI37: 终值ROIC | BJ37: 再投资率 | BK37: 降级 | BL37: 终值NOPAT | BM37: 终值FCFF | BN37: TV | BO37: PV(TV) | BP37: EV0 | BQ37: EV | BR37: 全体权益 | BS37: 少数股东 | BT37: 归母权益 | BU37: 每股
A38: 1-1 | B38: -0.06 | C38: 0.01 | D38: =$B$5*(1+('1_Assumptions'!$E$11+IF('1_Assumptions'!$B$39=1,0,$B38))) | E38: =D38*(1-'1_Assumptions'!$E$17) | F38: =D38-E38-D38*$B$11+D38*$B$12 | G38: =$B$6*$B$13 | H38: =D38*'1_Assumptions'!$E$23 | I38: =$B$6+H38-G38 | J38: =D38*$B$14 | K38: =$B$7-J38 | L38: =$B$8+D38*$B$16-$B$8/$B$18 | M38: =D38*'1_Assumptions'!$B$56/365+E38*'1_Assumptions'!$B$57/365+D38*'1_Assumptions'!$B$54-E38*'1_Assumptions'!$B$58/365-D38*'1_Assumptions'!$B$55 | N38: =F38*(1-$B$15)+G38+J38+IF($B$19=1,D38*'1_Assumptions'!$E$29,0)-H38-(M38-$B$10) | O38: =D38*(1+('1_Assumptions'!$E$12+$B38)) | P38: =O38*(1-'1_Assumptions'!$E$18) | Q38: =O38-P38-O38*$B$11+O38*$B$12 | R38: =I38*$B$13 | S38: =O38*'1_Assumptions'!$E$24 | T38: =I38+S38-R38 | U38: =O38*$B$14 | V38: =K38-U38 | W38: =L38+O38*$B$16-L38/$B$18 | X38: =O38*'1_Assumptions'!$B$56/365+P38*'1_Assumptions'!$B$57/365+O38*'1_Assumptions'!$B$54-P38*'1_Assumptions'!$B$58/365-O38*'1_Assumptions'!$B$55 | Y38: =Q38*(1-$B$15)+R38+U38+IF($B$19=1,O38*'1_Assumptions'!$E$30,0)-S38-(X38-M38) | Z38: =O38*(1+('1_Assumptions'!$E$13+$B38)) | AA38: =Z38*(1-'1_Assumptions'!$E$19) | AB38: =Z38-AA38-Z38*$B$11+Z38*$B$12 | AC38: =T38*$B$13 | AD38: =Z38*'1_Assumptions'!$E$25 | AE38: =T38+AD38-AC38 | AF38: =Z38*$B$14 | AG38: =V38-AF38 | AH38: =W38+Z38*$B$16-W38/$B$18 | AI38: =Z38*'1_Assumptions'!$B$56/365+AA38*'1_Assumptions'!$B$57/365+Z38*'1_Assumptions'!$B$54-AA38*'1_Assumptions'!$B$58/365-Z38*'1_Assumptions'!$B$55 | AJ38: =AB38*(1-$B$15)+AC38+AF38+IF($B$19=1,Z38*'1_Assumptions'!$E$31,0)-AD38-(AI38-X38) | AK38: =Z38*(1+('1_Assumptions'!$E$14+$B38)) | AL38: =AK38*(1-'1_Assumptions'!$E$20) | AM38: =AK38-AL38-AK38*$B$11+AK38*$B$12 | AN38: =AE38*$B$13 | AO38: =AK38*'1_Assumptions'!$E$26 | AP38: =AE38+AO38-AN38 | AQ38: =AK38*$B$14 | AR38: =AG38-AQ38 | AS38: =AH38+AK38*$B$16-AH38/$B$18 | AT38: =AK38*'1_Assumptions'!$B$56/365+AL38*'1_Assumptions'!$B$57/365+AK38*'1_Assumptions'!$B$54-AL38*'1_Assumptions'!$B$58/365-AK38*'1_Assumptions'!$B$55 | AU38: =AM38*(1-$B$15)+AN38+AQ38+IF($B$19=1,AK38*'1_Assumptions'!$E$32,0)-AO38-(AT38-AI38) | AV38: =AK38*(1+('1_Assumptions'!$E$15+$B38)) | AW38: =AV38*(1-'1_Assumptions'!$E$21) | AX38: =AV38-AW38-AV38*$B$11+AV38*$B$12 | AY38: =AP38*$B$13 | AZ38: =AV38*'1_Assumptions'!$E$27 | BA38: =AP38+AZ38-AY38 | BB38: =AV38*$B$14 | BC38: =AR38-BB38 | BD38: =AS38+AV38*$B$16-AS38/$B$18 | BE38: =AV38*'1_Assumptions'!$B$56/365+AW38*'1_Assumptions'!$B$57/365+AV38*'1_Assumptions'!$B$54-AW38*'1_Assumptions'!$B$58/365-AV38*'1_Assumptions'!$B$55 | BF38: =AX38*(1-$B$15)+AY38+BB38+IF($B$19=1,AV38*'1_Assumptions'!$E$33,0)-AZ38-(BE38-AT38) | BG38: =N38/(1+$B$21)^(1-0.5*$B$23)+Y38/(1+$B$21)^(2-0.5*$B$23)+AJ38/(1+$B$21)^(3-0.5*$B$23)+AU38/(1+$B$21)^(4-0.5*$B$23)+BF38/(1+$B$21)^(5-0.5*$B$23) | BH38: =BE38+BA38+BC38+$B$9+IF($B$17=1,BD38,0) | BI38: =IF($B$32=2,$B$21+$B$33,IF(BH38=0,0,BL38/BH38)) | BJ38: =IF(BI38=0,9,$C38/BI38) | BK38: =IF(OR(BH38<=0,BI38<=$B$21,BJ38>=1,BJ38<0),1,0) | BL38: =AX38*(1-$B$20) | BM38: =IF(BK38=1,BL38,AX38*(1+$C38)*(1-$B$20)*(1-BJ38)) | BN38: =IF(BK38=1,BL38/$B$21,BM38/($B$21-$C38)) | BO38: =BN38/(1+$B$21)^(5-0.5*$B$23) | BP38: =BG38+BO38 | BQ38: =BP38*(1+$B$21)^$B$24-N38*$B$24*(1+$B$21)^($B$24/2) | BR38: =BQ38-$B$25+$B$26+$B$27 | BS38: =IF($B$28=1,$B$30,BR38*$B$29) | BT38: =BR38-BS38 | BU38: =BT38/$B$31
A39: 1-2 | B39: -0.06 | C39: 0.0175 | D39: =$B$5*(1+('1_Assumptions'!$E$11+IF('1_Assumptions'!$B$39=1,0,$B39))) | E39: =D39*(1-'1_Assumptions'!$E$17) | F39: =D39-E39-D39*$B$11+D39*$B$12 | G39: =$B$6*$B$13 | H39: =D39*'1_Assumptions'!$E$23 | I39: =$B$6+H39-G39 | J39: =D39*$B$14 | K39: =$B$7-J39 | L39: =$B$8+D39*$B$16-$B$8/$B$18 | M39: =D39*'1_Assumptions'!$B$56/365+E39*'1_Assumptions'!$B$57/365+D39*'1_Assumptions'!$B$54-E39*'1_Assumptions'!$B$58/365-D39*'1_Assumptions'!$B$55 | N39: =F39*(1-$B$15)+G39+J39+IF($B$19=1,D39*'1_Assumptions'!$E$29,0)-H39-(M39-$B$10) | O39: =D39*(1+('1_Assumptions'!$E$12+$B39)) | P39: =O39*(1-'1_Assumptions'!$E$18) | Q39: =O39-P39-O39*$B$11+O39*$B$12 | R39: =I39*$B$13 | S39: =O39*'1_Assumptions'!$E$24 | T39: =I39+S39-R39 | U39: =O39*$B$14 | V39: =K39-U39 | W39: =L39+O39*$B$16-L39/$B$18 | X39: =O39*'1_Assumptions'!$B$56/365+P39*'1_Assumptions'!$B$57/365+O39*'1_Assumptions'!$B$54-P39*'1_Assumptions'!$B$58/365-O39*'1_Assumptions'!$B$55 | Y39: =Q39*(1-$B$15)+R39+U39+IF($B$19=1,O39*'1_Assumptions'!$E$30,0)-S39-(X39-M39) | Z39: =O39*(1+('1_Assumptions'!$E$13+$B39)) | AA39: =Z39*(1-'1_Assumptions'!$E$19) | AB39: =Z39-AA39-Z39*$B$11+Z39*$B$12 | AC39: =T39*$B$13 | AD39: =Z39*'1_Assumptions'!$E$25 | AE39: =T39+AD39-AC39 | AF39: =Z39*$B$14 | AG39: =V39-AF39 | AH39: =W39+Z39*$B$16-W39/$B$18 | AI39: =Z39*'1_Assumptions'!$B$56/365+AA39*'1_Assumptions'!$B$57/365+Z39*'1_Assumptions'!$B$54-AA39*'1_Assumptions'!$B$58/365-Z39*'1_Assumptions'!$B$55 | AJ39: =AB39*(1-$B$15)+AC39+AF39+IF($B$19=1,Z39*'1_Assumptions'!$E$31,0)-AD39-(AI39-X39) | AK39: =Z39*(1+('1_Assumptions'!$E$14+$B39)) | AL39: =AK39*(1-'1_Assumptions'!$E$20) | AM39: =AK39-AL39-AK39*$B$11+AK39*$B$12 | AN39: =AE39*$B$13 | AO39: =AK39*'1_Assumptions'!$E$26 | AP39: =AE39+AO39-AN39 | AQ39: =AK39*$B$14 | AR39: =AG39-AQ39 | AS39: =AH39+AK39*$B$16-AH39/$B$18 | AT39: =AK39*'1_Assumptions'!$B$56/365+AL39*'1_Assumptions'!$B$57/365+AK39*'1_Assumptions'!$B$54-AL39*'1_Assumptions'!$B$58/365-AK39*'1_Assumptions'!$B$55 | AU39: =AM39*(1-$B$15)+AN39+AQ39+IF($B$19=1,AK39*'1_Assumptions'!$E$32,0)-AO39-(AT39-AI39) | AV39: =AK39*(1+('1_Assumptions'!$E$15+$B39)) | AW39: =AV39*(1-'1_Assumptions'!$E$21) | AX39: =AV39-AW39-AV39*$B$11+AV39*$B$12 | AY39: =AP39*$B$13 | AZ39: =AV39*'1_Assumptions'!$E$27 | BA39: =AP39+AZ39-AY39 | BB39: =AV39*$B$14 | BC39: =AR39-BB39 | BD39: =AS39+AV39*$B$16-AS39/$B$18 | BE39: =AV39*'1_Assumptions'!$B$56/365+AW39*'1_Assumptions'!$B$57/365+AV39*'1_Assumptions'!$B$54-AW39*'1_Assumptions'!$B$58/365-AV39*'1_Assumptions'!$B$55 | BF39: =AX39*(1-$B$15)+AY39+BB39+IF($B$19=1,AV39*'1_Assumptions'!$E$33,0)-AZ39-(BE39-AT39) | BG39: =N39/(1+$B$21)^(1-0.5*$B$23)+Y39/(1+$B$21)^(2-0.5*$B$23)+AJ39/(1+$B$21)^(3-0.5*$B$23)+AU39/(1+$B$21)^(4-0.5*$B$23)+BF39/(1+$B$21)^(5-0.5*$B$23) | BH39: =BE39+BA39+BC39+$B$9+IF($B$17=1,BD39,0) | BI39: =IF($B$32=2,$B$21+$B$33,IF(BH39=0,0,BL39/BH39)) | BJ39: =IF(BI39=0,9,$C39/BI39) | BK39: =IF(OR(BH39<=0,BI39<=$B$21,BJ39>=1,BJ39<0),1,0) | BL39: =AX39*(1-$B$20) | BM39: =IF(BK39=1,BL39,AX39*(1+$C39)*(1-$B$20)*(1-BJ39)) | BN39: =IF(BK39=1,BL39/$B$21,BM39/($B$21-$C39)) | BO39: =BN39/(1+$B$21)^(5-0.5*$B$23) | BP39: =BG39+BO39 | BQ39: =BP39*(1+$B$21)^$B$24-N39*$B$24*(1+$B$21)^($B$24/2) | BR39: =BQ39-$B$25+$B$26+$B$27 | BS39: =IF($B$28=1,$B$30,BR39*$B$29) | BT39: =BR39-BS39 | BU39: =BT39/$B$31
A40: 1-3 | B40: -0.06 | C40: 0.025 | D40: =$B$5*(1+('1_Assumptions'!$E$11+IF('1_Assumptions'!$B$39=1,0,$B40))) | E40: =D40*(1-'1_Assumptions'!$E$17) | F40: =D40-E40-D40*$B$11+D40*$B$12 | G40: =$B$6*$B$13 | H40: =D40*'1_Assumptions'!$E$23 | I40: =$B$6+H40-G40 | J40: =D40*$B$14 | K40: =$B$7-J40 | L40: =$B$8+D40*$B$16-$B$8/$B$18 | M40: =D40*'1_Assumptions'!$B$56/365+E40*'1_Assumptions'!$B$57/365+D40*'1_Assumptions'!$B$54-E40*'1_Assumptions'!$B$58/365-D40*'1_Assumptions'!$B$55 | N40: =F40*(1-$B$15)+G40+J40+IF($B$19=1,D40*'1_Assumptions'!$E$29,0)-H40-(M40-$B$10) | O40: =D40*(1+('1_Assumptions'!$E$12+$B40)) | P40: =O40*(1-'1_Assumptions'!$E$18) | Q40: =O40-P40-O40*$B$11+O40*$B$12 | R40: =I40*$B$13 | S40: =O40*'1_Assumptions'!$E$24 | T40: =I40+S40-R40 | U40: =O40*$B$14 | V40: =K40-U40 | W40: =L40+O40*$B$16-L40/$B$18 | X40: =O40*'1_Assumptions'!$B$56/365+P40*'1_Assumptions'!$B$57/365+O40*'1_Assumptions'!$B$54-P40*'1_Assumptions'!$B$58/365-O40*'1_Assumptions'!$B$55 | Y40: =Q40*(1-$B$15)+R40+U40+IF($B$19=1,O40*'1_Assumptions'!$E$30,0)-S40-(X40-M40) | Z40: =O40*(1+('1_Assumptions'!$E$13+$B40)) | AA40: =Z40*(1-'1_Assumptions'!$E$19) | AB40: =Z40-AA40-Z40*$B$11+Z40*$B$12 | AC40: =T40*$B$13 | AD40: =Z40*'1_Assumptions'!$E$25 | AE40: =T40+AD40-AC40 | AF40: =Z40*$B$14 | AG40: =V40-AF40 | AH40: =W40+Z40*$B$16-W40/$B$18 | AI40: =Z40*'1_Assumptions'!$B$56/365+AA40*'1_Assumptions'!$B$57/365+Z40*'1_Assumptions'!$B$54-AA40*'1_Assumptions'!$B$58/365-Z40*'1_Assumptions'!$B$55 | AJ40: =AB40*(1-$B$15)+AC40+AF40+IF($B$19=1,Z40*'1_Assumptions'!$E$31,0)-AD40-(AI40-X40) | AK40: =Z40*(1+('1_Assumptions'!$E$14+$B40)) | AL40: =AK40*(1-'1_Assumptions'!$E$20) | AM40: =AK40-AL40-AK40*$B$11+AK40*$B$12 | AN40: =AE40*$B$13 | AO40: =AK40*'1_Assumptions'!$E$26 | AP40: =AE40+AO40-AN40 | AQ40: =AK40*$B$14 | AR40: =AG40-AQ40 | AS40: =AH40+AK40*$B$16-AH40/$B$18 | AT40: =AK40*'1_Assumptions'!$B$56/365+AL40*'1_Assumptions'!$B$57/365+AK40*'1_Assumptions'!$B$54-AL40*'1_Assumptions'!$B$58/365-AK40*'1_Assumptions'!$B$55 | AU40: =AM40*(1-$B$15)+AN40+AQ40+IF($B$19=1,AK40*'1_Assumptions'!$E$32,0)-AO40-(AT40-AI40) | AV40: =AK40*(1+('1_Assumptions'!$E$15+$B40)) | AW40: =AV40*(1-'1_Assumptions'!$E$21) | AX40: =AV40-AW40-AV40*$B$11+AV40*$B$12 | AY40: =AP40*$B$13 | AZ40: =AV40*'1_Assumptions'!$E$27 | BA40: =AP40+AZ40-AY40 | BB40: =AV40*$B$14 | BC40: =AR40-BB40 | BD40: =AS40+AV40*$B$16-AS40/$B$18 | BE40: =AV40*'1_Assumptions'!$B$56/365+AW40*'1_Assumptions'!$B$57/365+AV40*'1_Assumptions'!$B$54-AW40*'1_Assumptions'!$B$58/365-AV40*'1_Assumptions'!$B$55 | BF40: =AX40*(1-$B$15)+AY40+BB40+IF($B$19=1,AV40*'1_Assumptions'!$E$33,0)-AZ40-(BE40-AT40) | BG40: =N40/(1+$B$21)^(1-0.5*$B$23)+Y40/(1+$B$21)^(2-0.5*$B$23)+AJ40/(1+$B$21)^(3-0.5*$B$23)+AU40/(1+$B$21)^(4-0.5*$B$23)+BF40/(1+$B$21)^(5-0.5*$B$23) | BH40: =BE40+BA40+BC40+$B$9+IF($B$17=1,BD40,0) | BI40: =IF($B$32=2,$B$21+$B$33,IF(BH40=0,0,BL40/BH40)) | BJ40: =IF(BI40=0,9,$C40/BI40) | BK40: =IF(OR(BH40<=0,BI40<=$B$21,BJ40>=1,BJ40<0),1,0) | BL40: =AX40*(1-$B$20) | BM40: =IF(BK40=1,BL40,AX40*(1+$C40)*(1-$B$20)*(1-BJ40)) | BN40: =IF(BK40=1,BL40/$B$21,BM40/($B$21-$C40)) | BO40: =BN40/(1+$B$21)^(5-0.5*$B$23) | BP40: =BG40+BO40 | BQ40: =BP40*(1+$B$21)^$B$24-N40*$B$24*(1+$B$21)^($B$24/2) | BR40: =BQ40-$B$25+$B$26+$B$27 | BS40: =IF($B$28=1,$B$30,BR40*$B$29) | BT40: =BR40-BS40 | BU40: =BT40/$B$31
A41: 1-4 | B41: -0.06 | C41: 0.0325 | D41: =$B$5*(1+('1_Assumptions'!$E$11+IF('1_Assumptions'!$B$39=1,0,$B41))) | E41: =D41*(1-'1_Assumptions'!$E$17) | F41: =D41-E41-D41*$B$11+D41*$B$12 | G41: =$B$6*$B$13 | H41: =D41*'1_Assumptions'!$E$23 | I41: =$B$6+H41-G41 | J41: =D41*$B$14 | K41: =$B$7-J41 | L41: =$B$8+D41*$B$16-$B$8/$B$18 | M41: =D41*'1_Assumptions'!$B$56/365+E41*'1_Assumptions'!$B$57/365+D41*'1_Assumptions'!$B$54-E41*'1_Assumptions'!$B$58/365-D41*'1_Assumptions'!$B$55 | N41: =F41*(1-$B$15)+G41+J41+IF($B$19=1,D41*'1_Assumptions'!$E$29,0)-H41-(M41-$B$10) | O41: =D41*(1+('1_Assumptions'!$E$12+$B41)) | P41: =O41*(1-'1_Assumptions'!$E$18) | Q41: =O41-P41-O41*$B$11+O41*$B$12 | R41: =I41*$B$13 | S41: =O41*'1_Assumptions'!$E$24 | T41: =I41+S41-R41 | U41: =O41*$B$14 | V41: =K41-U41 | W41: =L41+O41*$B$16-L41/$B$18 | X41: =O41*'1_Assumptions'!$B$56/365+P41*'1_Assumptions'!$B$57/365+O41*'1_Assumptions'!$B$54-P41*'1_Assumptions'!$B$58/365-O41*'1_Assumptions'!$B$55 | Y41: =Q41*(1-$B$15)+R41+U41+IF($B$19=1,O41*'1_Assumptions'!$E$30,0)-S41-(X41-M41) | Z41: =O41*(1+('1_Assumptions'!$E$13+$B41)) | AA41: =Z41*(1-'1_Assumptions'!$E$19) | AB41: =Z41-AA41-Z41*$B$11+Z41*$B$12 | AC41: =T41*$B$13 | AD41: =Z41*'1_Assumptions'!$E$25 | AE41: =T41+AD41-AC41 | AF41: =Z41*$B$14 | AG41: =V41-AF41 | AH41: =W41+Z41*$B$16-W41/$B$18 | AI41: =Z41*'1_Assumptions'!$B$56/365+AA41*'1_Assumptions'!$B$57/365+Z41*'1_Assumptions'!$B$54-AA41*'1_Assumptions'!$B$58/365-Z41*'1_Assumptions'!$B$55 | AJ41: =AB41*(1-$B$15)+AC41+AF41+IF($B$19=1,Z41*'1_Assumptions'!$E$31,0)-AD41-(AI41-X41) | AK41: =Z41*(1+('1_Assumptions'!$E$14+$B41)) | AL41: =AK41*(1-'1_Assumptions'!$E$20) | AM41: =AK41-AL41-AK41*$B$11+AK41*$B$12 | AN41: =AE41*$B$13 | AO41: =AK41*'1_Assumptions'!$E$26 | AP41: =AE41+AO41-AN41 | AQ41: =AK41*$B$14 | AR41: =AG41-AQ41 | AS41: =AH41+AK41*$B$16-AH41/$B$18 | AT41: =AK41*'1_Assumptions'!$B$56/365+AL41*'1_Assumptions'!$B$57/365+AK41*'1_Assumptions'!$B$54-AL41*'1_Assumptions'!$B$58/365-AK41*'1_Assumptions'!$B$55 | AU41: =AM41*(1-$B$15)+AN41+AQ41+IF($B$19=1,AK41*'1_Assumptions'!$E$32,0)-AO41-(AT41-AI41) | AV41: =AK41*(1+('1_Assumptions'!$E$15+$B41)) | AW41: =AV41*(1-'1_Assumptions'!$E$21) | AX41: =AV41-AW41-AV41*$B$11+AV41*$B$12 | AY41: =AP41*$B$13 | AZ41: =AV41*'1_Assumptions'!$E$27 | BA41: =AP41+AZ41-AY41 | BB41: =AV41*$B$14 | BC41: =AR41-BB41 | BD41: =AS41+AV41*$B$16-AS41/$B$18 | BE41: =AV41*'1_Assumptions'!$B$56/365+AW41*'1_Assumptions'!$B$57/365+AV41*'1_Assumptions'!$B$54-AW41*'1_Assumptions'!$B$58/365-AV41*'1_Assumptions'!$B$55 | BF41: =AX41*(1-$B$15)+AY41+BB41+IF($B$19=1,AV41*'1_Assumptions'!$E$33,0)-AZ41-(BE41-AT41) | BG41: =N41/(1+$B$21)^(1-0.5*$B$23)+Y41/(1+$B$21)^(2-0.5*$B$23)+AJ41/(1+$B$21)^(3-0.5*$B$23)+AU41/(1+$B$21)^(4-0.5*$B$23)+BF41/(1+$B$21)^(5-0.5*$B$23) | BH41: =BE41+BA41+BC41+$B$9+IF($B$17=1,BD41,0) | BI41: =IF($B$32=2,$B$21+$B$33,IF(BH41=0,0,BL41/BH41)) | BJ41: =IF(BI41=0,9,$C41/BI41) | BK41: =IF(OR(BH41<=0,BI41<=$B$21,BJ41>=1,BJ41<0),1,0) | BL41: =AX41*(1-$B$20) | BM41: =IF(BK41=1,BL41,AX41*(1+$C41)*(1-$B$20)*(1-BJ41)) | BN41: =IF(BK41=1,BL41/$B$21,BM41/($B$21-$C41)) | BO41: =BN41/(1+$B$21)^(5-0.5*$B$23) | BP41: =BG41+BO41 | BQ41: =BP41*(1+$B$21)^$B$24-N41*$B$24*(1+$B$21)^($B$24/2) | BR41: =BQ41-$B$25+$B$26+$B$27 | BS41: =IF($B$28=1,$B$30,BR41*$B$29) | BT41: =BR41-BS41 | BU41: =BT41/$B$31
A42: 1-5 | B42: -0.06 | C42: 0.04 | D42: =$B$5*(1+('1_Assumptions'!$E$11+IF('1_Assumptions'!$B$39=1,0,$B42))) | E42: =D42*(1-'1_Assumptions'!$E$17) | F42: =D42-E42-D42*$B$11+D42*$B$12 | G42: =$B$6*$B$13 | H42: =D42*'1_Assumptions'!$E$23 | I42: =$B$6+H42-G42 | J42: =D42*$B$14 | K42: =$B$7-J42 | L42: =$B$8+D42*$B$16-$B$8/$B$18 | M42: =D42*'1_Assumptions'!$B$56/365+E42*'1_Assumptions'!$B$57/365+D42*'1_Assumptions'!$B$54-E42*'1_Assumptions'!$B$58/365-D42*'1_Assumptions'!$B$55 | N42: =F42*(1-$B$15)+G42+J42+IF($B$19=1,D42*'1_Assumptions'!$E$29,0)-H42-(M42-$B$10) | O42: =D42*(1+('1_Assumptions'!$E$12+$B42)) | P42: =O42*(1-'1_Assumptions'!$E$18) | Q42: =O42-P42-O42*$B$11+O42*$B$12 | R42: =I42*$B$13 | S42: =O42*'1_Assumptions'!$E$24 | T42: =I42+S42-R42 | U42: =O42*$B$14 | V42: =K42-U42 | W42: =L42+O42*$B$16-L42/$B$18 | X42: =O42*'1_Assumptions'!$B$56/365+P42*'1_Assumptions'!$B$57/365+O42*'1_Assumptions'!$B$54-P42*'1_Assumptions'!$B$58/365-O42*'1_Assumptions'!$B$55 | Y42: =Q42*(1-$B$15)+R42+U42+IF($B$19=1,O42*'1_Assumptions'!$E$30,0)-S42-(X42-M42) | Z42: =O42*(1+('1_Assumptions'!$E$13+$B42)) | AA42: =Z42*(1-'1_Assumptions'!$E$19) | AB42: =Z42-AA42-Z42*$B$11+Z42*$B$12 | AC42: =T42*$B$13 | AD42: =Z42*'1_Assumptions'!$E$25 | AE42: =T42+AD42-AC42 | AF42: =Z42*$B$14 | AG42: =V42-AF42 | AH42: =W42+Z42*$B$16-W42/$B$18 | AI42: =Z42*'1_Assumptions'!$B$56/365+AA42*'1_Assumptions'!$B$57/365+Z42*'1_Assumptions'!$B$54-AA42*'1_Assumptions'!$B$58/365-Z42*'1_Assumptions'!$B$55 | AJ42: =AB42*(1-$B$15)+AC42+AF42+IF($B$19=1,Z42*'1_Assumptions'!$E$31,0)-AD42-(AI42-X42) | AK42: =Z42*(1+('1_Assumptions'!$E$14+$B42)) | AL42: =AK42*(1-'1_Assumptions'!$E$20) | AM42: =AK42-AL42-AK42*$B$11+AK42*$B$12 | AN42: =AE42*$B$13 | AO42: =AK42*'1_Assumptions'!$E$26 | AP42: =AE42+AO42-AN42 | AQ42: =AK42*$B$14 | AR42: =AG42-AQ42 | AS42: =AH42+AK42*$B$16-AH42/$B$18 | AT42: =AK42*'1_Assumptions'!$B$56/365+AL42*'1_Assumptions'!$B$57/365+AK42*'1_Assumptions'!$B$54-AL42*'1_Assumptions'!$B$58/365-AK42*'1_Assumptions'!$B$55 | AU42: =AM42*(1-$B$15)+AN42+AQ42+IF($B$19=1,AK42*'1_Assumptions'!$E$32,0)-AO42-(AT42-AI42) | AV42: =AK42*(1+('1_Assumptions'!$E$15+$B42)) | AW42: =AV42*(1-'1_Assumptions'!$E$21) | AX42: =AV42-AW42-AV42*$B$11+AV42*$B$12 | AY42: =AP42*$B$13 | AZ42: =AV42*'1_Assumptions'!$E$27 | BA42: =AP42+AZ42-AY42 | BB42: =AV42*$B$14 | BC42: =AR42-BB42 | BD42: =AS42+AV42*$B$16-AS42/$B$18 | BE42: =AV42*'1_Assumptions'!$B$56/365+AW42*'1_Assumptions'!$B$57/365+AV42*'1_Assumptions'!$B$54-AW42*'1_Assumptions'!$B$58/365-AV42*'1_Assumptions'!$B$55 | BF42: =AX42*(1-$B$15)+AY42+BB42+IF($B$19=1,AV42*'1_Assumptions'!$E$33,0)-AZ42-(BE42-AT42) | BG42: =N42/(1+$B$21)^(1-0.5*$B$23)+Y42/(1+$B$21)^(2-0.5*$B$23)+AJ42/(1+$B$21)^(3-0.5*$B$23)+AU42/(1+$B$21)^(4-0.5*$B$23)+BF42/(1+$B$21)^(5-0.5*$B$23) | BH42: =BE42+BA42+BC42+$B$9+IF($B$17=1,BD42,0) | BI42: =IF($B$32=2,$B$21+$B$33,IF(BH42=0,0,BL42/BH42)) | BJ42: =IF(BI42=0,9,$C42/BI42) | BK42: =IF(OR(BH42<=0,BI42<=$B$21,BJ42>=1,BJ42<0),1,0) | BL42: =AX42*(1-$B$20) | BM42: =IF(BK42=1,BL42,AX42*(1+$C42)*(1-$B$20)*(1-BJ42)) | BN42: =IF(BK42=1,BL42/$B$21,BM42/($B$21-$C42)) | BO42: =BN42/(1+$B$21)^(5-0.5*$B$23) | BP42: =BG42+BO42 | BQ42: =BP42*(1+$B$21)^$B$24-N42*$B$24*(1+$B$21)^($B$24/2) | BR42: =BQ42-$B$25+$B$26+$B$27 | BS42: =IF($B$28=1,$B$30,BR42*$B$29) | BT42: =BR42-BS42 | BU42: =BT42/$B$31
A43: 2-1 | B43: -0.03 | C43: 0.01 | D43: =$B$5*(1+('1_Assumptions'!$E$11+IF('1_Assumptions'!$B$39=1,0,$B43))) | E43: =D43*(1-'1_Assumptions'!$E$17) | F43: =D43-E43-D43*$B$11+D43*$B$12 | G43: =$B$6*$B$13 | H43: =D43*'1_Assumptions'!$E$23 | I43: =$B$6+H43-G43 | J43: =D43*$B$14 | K43: =$B$7-J43 | L43: =$B$8+D43*$B$16-$B$8/$B$18 | M43: =D43*'1_Assumptions'!$B$56/365+E43*'1_Assumptions'!$B$57/365+D43*'1_Assumptions'!$B$54-E43*'1_Assumptions'!$B$58/365-D43*'1_Assumptions'!$B$55 | N43: =F43*(1-$B$15)+G43+J43+IF($B$19=1,D43*'1_Assumptions'!$E$29,0)-H43-(M43-$B$10) | O43: =D43*(1+('1_Assumptions'!$E$12+$B43)) | P43: =O43*(1-'1_Assumptions'!$E$18) | Q43: =O43-P43-O43*$B$11+O43*$B$12 | R43: =I43*$B$13 | S43: =O43*'1_Assumptions'!$E$24 | T43: =I43+S43-R43 | U43: =O43*$B$14 | V43: =K43-U43 | W43: =L43+O43*$B$16-L43/$B$18 | X43: =O43*'1_Assumptions'!$B$56/365+P43*'1_Assumptions'!$B$57/365+O43*'1_Assumptions'!$B$54-P43*'1_Assumptions'!$B$58/365-O43*'1_Assumptions'!$B$55 | Y43: =Q43*(1-$B$15)+R43+U43+IF($B$19=1,O43*'1_Assumptions'!$E$30,0)-S43-(X43-M43) | Z43: =O43*(1+('1_Assumptions'!$E$13+$B43)) | AA43: =Z43*(1-'1_Assumptions'!$E$19) | AB43: =Z43-AA43-Z43*$B$11+Z43*$B$12 | AC43: =T43*$B$13 | AD43: =Z43*'1_Assumptions'!$E$25 | AE43: =T43+AD43-AC43 | AF43: =Z43*$B$14 | AG43: =V43-AF43 | AH43: =W43+Z43*$B$16-W43/$B$18 | AI43: =Z43*'1_Assumptions'!$B$56/365+AA43*'1_Assumptions'!$B$57/365+Z43*'1_Assumptions'!$B$54-AA43*'1_Assumptions'!$B$58/365-Z43*'1_Assumptions'!$B$55 | AJ43: =AB43*(1-$B$15)+AC43+AF43+IF($B$19=1,Z43*'1_Assumptions'!$E$31,0)-AD43-(AI43-X43) | AK43: =Z43*(1+('1_Assumptions'!$E$14+$B43)) | AL43: =AK43*(1-'1_Assumptions'!$E$20) | AM43: =AK43-AL43-AK43*$B$11+AK43*$B$12 | AN43: =AE43*$B$13 | AO43: =AK43*'1_Assumptions'!$E$26 | AP43: =AE43+AO43-AN43 | AQ43: =AK43*$B$14 | AR43: =AG43-AQ43 | AS43: =AH43+AK43*$B$16-AH43/$B$18 | AT43: =AK43*'1_Assumptions'!$B$56/365+AL43*'1_Assumptions'!$B$57/365+AK43*'1_Assumptions'!$B$54-AL43*'1_Assumptions'!$B$58/365-AK43*'1_Assumptions'!$B$55 | AU43: =AM43*(1-$B$15)+AN43+AQ43+IF($B$19=1,AK43*'1_Assumptions'!$E$32,0)-AO43-(AT43-AI43) | AV43: =AK43*(1+('1_Assumptions'!$E$15+$B43)) | AW43: =AV43*(1-'1_Assumptions'!$E$21) | AX43: =AV43-AW43-AV43*$B$11+AV43*$B$12 | AY43: =AP43*$B$13 | AZ43: =AV43*'1_Assumptions'!$E$27 | BA43: =AP43+AZ43-AY43 | BB43: =AV43*$B$14 | BC43: =AR43-BB43 | BD43: =AS43+AV43*$B$16-AS43/$B$18 | BE43: =AV43*'1_Assumptions'!$B$56/365+AW43*'1_Assumptions'!$B$57/365+AV43*'1_Assumptions'!$B$54-AW43*'1_Assumptions'!$B$58/365-AV43*'1_Assumptions'!$B$55 | BF43: =AX43*(1-$B$15)+AY43+BB43+IF($B$19=1,AV43*'1_Assumptions'!$E$33,0)-AZ43-(BE43-AT43) | BG43: =N43/(1+$B$21)^(1-0.5*$B$23)+Y43/(1+$B$21)^(2-0.5*$B$23)+AJ43/(1+$B$21)^(3-0.5*$B$23)+AU43/(1+$B$21)^(4-0.5*$B$23)+BF43/(1+$B$21)^(5-0.5*$B$23) | BH43: =BE43+BA43+BC43+$B$9+IF($B$17=1,BD43,0) | BI43: =IF($B$32=2,$B$21+$B$33,IF(BH43=0,0,BL43/BH43)) | BJ43: =IF(BI43=0,9,$C43/BI43) | BK43: =IF(OR(BH43<=0,BI43<=$B$21,BJ43>=1,BJ43<0),1,0) | BL43: =AX43*(1-$B$20) | BM43: =IF(BK43=1,BL43,AX43*(1+$C43)*(1-$B$20)*(1-BJ43)) | BN43: =IF(BK43=1,BL43/$B$21,BM43/($B$21-$C43)) | BO43: =BN43/(1+$B$21)^(5-0.5*$B$23) | BP43: =BG43+BO43 | BQ43: =BP43*(1+$B$21)^$B$24-N43*$B$24*(1+$B$21)^($B$24/2) | BR43: =BQ43-$B$25+$B$26+$B$27 | BS43: =IF($B$28=1,$B$30,BR43*$B$29) | BT43: =BR43-BS43 | BU43: =BT43/$B$31
A44: 2-2 | B44: -0.03 | C44: 0.0175 | D44: =$B$5*(1+('1_Assumptions'!$E$11+IF('1_Assumptions'!$B$39=1,0,$B44))) | E44: =D44*(1-'1_Assumptions'!$E$17) | F44: =D44-E44-D44*$B$11+D44*$B$12 | G44: =$B$6*$B$13 | H44: =D44*'1_Assumptions'!$E$23 | I44: =$B$6+H44-G44 | J44: =D44*$B$14 | K44: =$B$7-J44 | L44: =$B$8+D44*$B$16-$B$8/$B$18 | M44: =D44*'1_Assumptions'!$B$56/365+E44*'1_Assumptions'!$B$57/365+D44*'1_Assumptions'!$B$54-E44*'1_Assumptions'!$B$58/365-D44*'1_Assumptions'!$B$55 | N44: =F44*(1-$B$15)+G44+J44+IF($B$19=1,D44*'1_Assumptions'!$E$29,0)-H44-(M44-$B$10) | O44: =D44*(1+('1_Assumptions'!$E$12+$B44)) | P44: =O44*(1-'1_Assumptions'!$E$18) | Q44: =O44-P44-O44*$B$11+O44*$B$12 | R44: =I44*$B$13 | S44: =O44*'1_Assumptions'!$E$24 | T44: =I44+S44-R44 | U44: =O44*$B$14 | V44: =K44-U44 | W44: =L44+O44*$B$16-L44/$B$18 | X44: =O44*'1_Assumptions'!$B$56/365+P44*'1_Assumptions'!$B$57/365+O44*'1_Assumptions'!$B$54-P44*'1_Assumptions'!$B$58/365-O44*'1_Assumptions'!$B$55 | Y44: =Q44*(1-$B$15)+R44+U44+IF($B$19=1,O44*'1_Assumptions'!$E$30,0)-S44-(X44-M44) | Z44: =O44*(1+('1_Assumptions'!$E$13+$B44)) | AA44: =Z44*(1-'1_Assumptions'!$E$19) | AB44: =Z44-AA44-Z44*$B$11+Z44*$B$12 | AC44: =T44*$B$13 | AD44: =Z44*'1_Assumptions'!$E$25 | AE44: =T44+AD44-AC44 | AF44: =Z44*$B$14 | AG44: =V44-AF44 | AH44: =W44+Z44*$B$16-W44/$B$18 | AI44: =Z44*'1_Assumptions'!$B$56/365+AA44*'1_Assumptions'!$B$57/365+Z44*'1_Assumptions'!$B$54-AA44*'1_Assumptions'!$B$58/365-Z44*'1_Assumptions'!$B$55 | AJ44: =AB44*(1-$B$15)+AC44+AF44+IF($B$19=1,Z44*'1_Assumptions'!$E$31,0)-AD44-(AI44-X44) | AK44: =Z44*(1+('1_Assumptions'!$E$14+$B44)) | AL44: =AK44*(1-'1_Assumptions'!$E$20) | AM44: =AK44-AL44-AK44*$B$11+AK44*$B$12 | AN44: =AE44*$B$13 | AO44: =AK44*'1_Assumptions'!$E$26 | AP44: =AE44+AO44-AN44 | AQ44: =AK44*$B$14 | AR44: =AG44-AQ44 | AS44: =AH44+AK44*$B$16-AH44/$B$18 | AT44: =AK44*'1_Assumptions'!$B$56/365+AL44*'1_Assumptions'!$B$57/365+AK44*'1_Assumptions'!$B$54-AL44*'1_Assumptions'!$B$58/365-AK44*'1_Assumptions'!$B$55 | AU44: =AM44*(1-$B$15)+AN44+AQ44+IF($B$19=1,AK44*'1_Assumptions'!$E$32,0)-AO44-(AT44-AI44) | AV44: =AK44*(1+('1_Assumptions'!$E$15+$B44)) | AW44: =AV44*(1-'1_Assumptions'!$E$21) | AX44: =AV44-AW44-AV44*$B$11+AV44*$B$12 | AY44: =AP44*$B$13 | AZ44: =AV44*'1_Assumptions'!$E$27 | BA44: =AP44+AZ44-AY44 | BB44: =AV44*$B$14 | BC44: =AR44-BB44 | BD44: =AS44+AV44*$B$16-AS44/$B$18 | BE44: =AV44*'1_Assumptions'!$B$56/365+AW44*'1_Assumptions'!$B$57/365+AV44*'1_Assumptions'!$B$54-AW44*'1_Assumptions'!$B$58/365-AV44*'1_Assumptions'!$B$55 | BF44: =AX44*(1-$B$15)+AY44+BB44+IF($B$19=1,AV44*'1_Assumptions'!$E$33,0)-AZ44-(BE44-AT44) | BG44: =N44/(1+$B$21)^(1-0.5*$B$23)+Y44/(1+$B$21)^(2-0.5*$B$23)+AJ44/(1+$B$21)^(3-0.5*$B$23)+AU44/(1+$B$21)^(4-0.5*$B$23)+BF44/(1+$B$21)^(5-0.5*$B$23) | BH44: =BE44+BA44+BC44+$B$9+IF($B$17=1,BD44,0) | BI44: =IF($B$32=2,$B$21+$B$33,IF(BH44=0,0,BL44/BH44)) | BJ44: =IF(BI44=0,9,$C44/BI44) | BK44: =IF(OR(BH44<=0,BI44<=$B$21,BJ44>=1,BJ44<0),1,0) | BL44: =AX44*(1-$B$20) | BM44: =IF(BK44=1,BL44,AX44*(1+$C44)*(1-$B$20)*(1-BJ44)) | BN44: =IF(BK44=1,BL44/$B$21,BM44/($B$21-$C44)) | BO44: =BN44/(1+$B$21)^(5-0.5*$B$23) | BP44: =BG44+BO44 | BQ44: =BP44*(1+$B$21)^$B$24-N44*$B$24*(1+$B$21)^($B$24/2) | BR44: =BQ44-$B$25+$B$26+$B$27 | BS44: =IF($B$28=1,$B$30,BR44*$B$29) | BT44: =BR44-BS44 | BU44: =BT44/$B$31
A45: 2-3 | B45: -0.03 | C45: 0.025 | D45: =$B$5*(1+('1_Assumptions'!$E$11+IF('1_Assumptions'!$B$39=1,0,$B45))) | E45: =D45*(1-'1_Assumptions'!$E$17) | F45: =D45-E45-D45*$B$11+D45*$B$12 | G45: =$B$6*$B$13 | H45: =D45*'1_Assumptions'!$E$23 | I45: =$B$6+H45-G45 | J45: =D45*$B$14 | K45: =$B$7-J45 | L45: =$B$8+D45*$B$16-$B$8/$B$18 | M45: =D45*'1_Assumptions'!$B$56/365+E45*'1_Assumptions'!$B$57/365+D45*'1_Assumptions'!$B$54-E45*'1_Assumptions'!$B$58/365-D45*'1_Assumptions'!$B$55 | N45: =F45*(1-$B$15)+G45+J45+IF($B$19=1,D45*'1_Assumptions'!$E$29,0)-H45-(M45-$B$10) | O45: =D45*(1+('1_Assumptions'!$E$12+$B45)) | P45: =O45*(1-'1_Assumptions'!$E$18) | Q45: =O45-P45-O45*$B$11+O45*$B$12 | R45: =I45*$B$13 | S45: =O45*'1_Assumptions'!$E$24 | T45: =I45+S45-R45 | U45: =O45*$B$14 | V45: =K45-U45 | W45: =L45+O45*$B$16-L45/$B$18 | X45: =O45*'1_Assumptions'!$B$56/365+P45*'1_Assumptions'!$B$57/365+O45*'1_Assumptions'!$B$54-P45*'1_Assumptions'!$B$58/365-O45*'1_Assumptions'!$B$55 | Y45: =Q45*(1-$B$15)+R45+U45+IF($B$19=1,O45*'1_Assumptions'!$E$30,0)-S45-(X45-M45) | Z45: =O45*(1+('1_Assumptions'!$E$13+$B45)) | AA45: =Z45*(1-'1_Assumptions'!$E$19) | AB45: =Z45-AA45-Z45*$B$11+Z45*$B$12 | AC45: =T45*$B$13 | AD45: =Z45*'1_Assumptions'!$E$25 | AE45: =T45+AD45-AC45 | AF45: =Z45*$B$14 | AG45: =V45-AF45 | AH45: =W45+Z45*$B$16-W45/$B$18 | AI45: =Z45*'1_Assumptions'!$B$56/365+AA45*'1_Assumptions'!$B$57/365+Z45*'1_Assumptions'!$B$54-AA45*'1_Assumptions'!$B$58/365-Z45*'1_Assumptions'!$B$55 | AJ45: =AB45*(1-$B$15)+AC45+AF45+IF($B$19=1,Z45*'1_Assumptions'!$E$31,0)-AD45-(AI45-X45) | AK45: =Z45*(1+('1_Assumptions'!$E$14+$B45)) | AL45: =AK45*(1-'1_Assumptions'!$E$20) | AM45: =AK45-AL45-AK45*$B$11+AK45*$B$12 | AN45: =AE45*$B$13 | AO45: =AK45*'1_Assumptions'!$E$26 | AP45: =AE45+AO45-AN45 | AQ45: =AK45*$B$14 | AR45: =AG45-AQ45 | AS45: =AH45+AK45*$B$16-AH45/$B$18 | AT45: =AK45*'1_Assumptions'!$B$56/365+AL45*'1_Assumptions'!$B$57/365+AK45*'1_Assumptions'!$B$54-AL45*'1_Assumptions'!$B$58/365-AK45*'1_Assumptions'!$B$55 | AU45: =AM45*(1-$B$15)+AN45+AQ45+IF($B$19=1,AK45*'1_Assumptions'!$E$32,0)-AO45-(AT45-AI45) | AV45: =AK45*(1+('1_Assumptions'!$E$15+$B45)) | AW45: =AV45*(1-'1_Assumptions'!$E$21) | AX45: =AV45-AW45-AV45*$B$11+AV45*$B$12 | AY45: =AP45*$B$13 | AZ45: =AV45*'1_Assumptions'!$E$27 | BA45: =AP45+AZ45-AY45 | BB45: =AV45*$B$14 | BC45: =AR45-BB45 | BD45: =AS45+AV45*$B$16-AS45/$B$18 | BE45: =AV45*'1_Assumptions'!$B$56/365+AW45*'1_Assumptions'!$B$57/365+AV45*'1_Assumptions'!$B$54-AW45*'1_Assumptions'!$B$58/365-AV45*'1_Assumptions'!$B$55 | BF45: =AX45*(1-$B$15)+AY45+BB45+IF($B$19=1,AV45*'1_Assumptions'!$E$33,0)-AZ45-(BE45-AT45) | BG45: =N45/(1+$B$21)^(1-0.5*$B$23)+Y45/(1+$B$21)^(2-0.5*$B$23)+AJ45/(1+$B$21)^(3-0.5*$B$23)+AU45/(1+$B$21)^(4-0.5*$B$23)+BF45/(1+$B$21)^(5-0.5*$B$23) | BH45: =BE45+BA45+BC45+$B$9+IF($B$17=1,BD45,0) | BI45: =IF($B$32=2,$B$21+$B$33,IF(BH45=0,0,BL45/BH45)) | BJ45: =IF(BI45=0,9,$C45/BI45) | BK45: =IF(OR(BH45<=0,BI45<=$B$21,BJ45>=1,BJ45<0),1,0) | BL45: =AX45*(1-$B$20) | BM45: =IF(BK45=1,BL45,AX45*(1+$C45)*(1-$B$20)*(1-BJ45)) | BN45: =IF(BK45=1,BL45/$B$21,BM45/($B$21-$C45)) | BO45: =BN45/(1+$B$21)^(5-0.5*$B$23) | BP45: =BG45+BO45 | BQ45: =BP45*(1+$B$21)^$B$24-N45*$B$24*(1+$B$21)^($B$24/2) | BR45: =BQ45-$B$25+$B$26+$B$27 | BS45: =IF($B$28=1,$B$30,BR45*$B$29) | BT45: =BR45-BS45 | BU45: =BT45/$B$31
A46: 2-4 | B46: -0.03 | C46: 0.0325 | D46: =$B$5*(1+('1_Assumptions'!$E$11+IF('1_Assumptions'!$B$39=1,0,$B46))) | E46: =D46*(1-'1_Assumptions'!$E$17) | F46: =D46-E46-D46*$B$11+D46*$B$12 | G46: =$B$6*$B$13 | H46: =D46*'1_Assumptions'!$E$23 | I46: =$B$6+H46-G46 | J46: =D46*$B$14 | K46: =$B$7-J46 | L46: =$B$8+D46*$B$16-$B$8/$B$18 | M46: =D46*'1_Assumptions'!$B$56/365+E46*'1_Assumptions'!$B$57/365+D46*'1_Assumptions'!$B$54-E46*'1_Assumptions'!$B$58/365-D46*'1_Assumptions'!$B$55 | N46: =F46*(1-$B$15)+G46+J46+IF($B$19=1,D46*'1_Assumptions'!$E$29,0)-H46-(M46-$B$10) | O46: =D46*(1+('1_Assumptions'!$E$12+$B46)) | P46: =O46*(1-'1_Assumptions'!$E$18) | Q46: =O46-P46-O46*$B$11+O46*$B$12 | R46: =I46*$B$13 | S46: =O46*'1_Assumptions'!$E$24 | T46: =I46+S46-R46 | U46: =O46*$B$14 | V46: =K46-U46 | W46: =L46+O46*$B$16-L46/$B$18 | X46: =O46*'1_Assumptions'!$B$56/365+P46*'1_Assumptions'!$B$57/365+O46*'1_Assumptions'!$B$54-P46*'1_Assumptions'!$B$58/365-O46*'1_Assumptions'!$B$55 | Y46: =Q46*(1-$B$15)+R46+U46+IF($B$19=1,O46*'1_Assumptions'!$E$30,0)-S46-(X46-M46) | Z46: =O46*(1+('1_Assumptions'!$E$13+$B46)) | AA46: =Z46*(1-'1_Assumptions'!$E$19) | AB46: =Z46-AA46-Z46*$B$11+Z46*$B$12 | AC46: =T46*$B$13 | AD46: =Z46*'1_Assumptions'!$E$25 | AE46: =T46+AD46-AC46 | AF46: =Z46*$B$14 | AG46: =V46-AF46 | AH46: =W46+Z46*$B$16-W46/$B$18 | AI46: =Z46*'1_Assumptions'!$B$56/365+AA46*'1_Assumptions'!$B$57/365+Z46*'1_Assumptions'!$B$54-AA46*'1_Assumptions'!$B$58/365-Z46*'1_Assumptions'!$B$55 | AJ46: =AB46*(1-$B$15)+AC46+AF46+IF($B$19=1,Z46*'1_Assumptions'!$E$31,0)-AD46-(AI46-X46) | AK46: =Z46*(1+('1_Assumptions'!$E$14+$B46)) | AL46: =AK46*(1-'1_Assumptions'!$E$20) | AM46: =AK46-AL46-AK46*$B$11+AK46*$B$12 | AN46: =AE46*$B$13 | AO46: =AK46*'1_Assumptions'!$E$26 | AP46: =AE46+AO46-AN46 | AQ46: =AK46*$B$14 | AR46: =AG46-AQ46 | AS46: =AH46+AK46*$B$16-AH46/$B$18 | AT46: =AK46*'1_Assumptions'!$B$56/365+AL46*'1_Assumptions'!$B$57/365+AK46*'1_Assumptions'!$B$54-AL46*'1_Assumptions'!$B$58/365-AK46*'1_Assumptions'!$B$55 | AU46: =AM46*(1-$B$15)+AN46+AQ46+IF($B$19=1,AK46*'1_Assumptions'!$E$32,0)-AO46-(AT46-AI46) | AV46: =AK46*(1+('1_Assumptions'!$E$15+$B46)) | AW46: =AV46*(1-'1_Assumptions'!$E$21) | AX46: =AV46-AW46-AV46*$B$11+AV46*$B$12 | AY46: =AP46*$B$13 | AZ46: =AV46*'1_Assumptions'!$E$27 | BA46: =AP46+AZ46-AY46 | BB46: =AV46*$B$14 | BC46: =AR46-BB46 | BD46: =AS46+AV46*$B$16-AS46/$B$18 | BE46: =AV46*'1_Assumptions'!$B$56/365+AW46*'1_Assumptions'!$B$57/365+AV46*'1_Assumptions'!$B$54-AW46*'1_Assumptions'!$B$58/365-AV46*'1_Assumptions'!$B$55 | BF46: =AX46*(1-$B$15)+AY46+BB46+IF($B$19=1,AV46*'1_Assumptions'!$E$33,0)-AZ46-(BE46-AT46) | BG46: =N46/(1+$B$21)^(1-0.5*$B$23)+Y46/(1+$B$21)^(2-0.5*$B$23)+AJ46/(1+$B$21)^(3-0.5*$B$23)+AU46/(1+$B$21)^(4-0.5*$B$23)+BF46/(1+$B$21)^(5-0.5*$B$23) | BH46: =BE46+BA46+BC46+$B$9+IF($B$17=1,BD46,0) | BI46: =IF($B$32=2,$B$21+$B$33,IF(BH46=0,0,BL46/BH46)) | BJ46: =IF(BI46=0,9,$C46/BI46) | BK46: =IF(OR(BH46<=0,BI46<=$B$21,BJ46>=1,BJ46<0),1,0) | BL46: =AX46*(1-$B$20) | BM46: =IF(BK46=1,BL46,AX46*(1+$C46)*(1-$B$20)*(1-BJ46)) | BN46: =IF(BK46=1,BL46/$B$21,BM46/($B$21-$C46)) | BO46: =BN46/(1+$B$21)^(5-0.5*$B$23) | BP46: =BG46+BO46 | BQ46: =BP46*(1+$B$21)^$B$24-N46*$B$24*(1+$B$21)^($B$24/2) | BR46: =BQ46-$B$25+$B$26+$B$27 | BS46: =IF($B$28=1,$B$30,BR46*$B$29) | BT46: =BR46-BS46 | BU46: =BT46/$B$31
A47: 2-5 | B47: -0.03 | C47: 0.04 | D47: =$B$5*(1+('1_Assumptions'!$E$11+IF('1_Assumptions'!$B$39=1,0,$B47))) | E47: =D47*(1-'1_Assumptions'!$E$17) | F47: =D47-E47-D47*$B$11+D47*$B$12 | G47: =$B$6*$B$13 | H47: =D47*'1_Assumptions'!$E$23 | I47: =$B$6+H47-G47 | J47: =D47*$B$14 | K47: =$B$7-J47 | L47: =$B$8+D47*$B$16-$B$8/$B$18 | M47: =D47*'1_Assumptions'!$B$56/365+E47*'1_Assumptions'!$B$57/365+D47*'1_Assumptions'!$B$54-E47*'1_Assumptions'!$B$58/365-D47*'1_Assumptions'!$B$55 | N47: =F47*(1-$B$15)+G47+J47+IF($B$19=1,D47*'1_Assumptions'!$E$29,0)-H47-(M47-$B$10) | O47: =D47*(1+('1_Assumptions'!$E$12+$B47)) | P47: =O47*(1-'1_Assumptions'!$E$18) | Q47: =O47-P47-O47*$B$11+O47*$B$12 | R47: =I47*$B$13 | S47: =O47*'1_Assumptions'!$E$24 | T47: =I47+S47-R47 | U47: =O47*$B$14 | V47: =K47-U47 | W47: =L47+O47*$B$16-L47/$B$18 | X47: =O47*'1_Assumptions'!$B$56/365+P47*'1_Assumptions'!$B$57/365+O47*'1_Assumptions'!$B$54-P47*'1_Assumptions'!$B$58/365-O47*'1_Assumptions'!$B$55 | Y47: =Q47*(1-$B$15)+R47+U47+IF($B$19=1,O47*'1_Assumptions'!$E$30,0)-S47-(X47-M47) | Z47: =O47*(1+('1_Assumptions'!$E$13+$B47)) | AA47: =Z47*(1-'1_Assumptions'!$E$19) | AB47: =Z47-AA47-Z47*$B$11+Z47*$B$12 | AC47: =T47*$B$13 | AD47: =Z47*'1_Assumptions'!$E$25 | AE47: =T47+AD47-AC47 | AF47: =Z47*$B$14 | AG47: =V47-AF47 | AH47: =W47+Z47*$B$16-W47/$B$18 | AI47: =Z47*'1_Assumptions'!$B$56/365+AA47*'1_Assumptions'!$B$57/365+Z47*'1_Assumptions'!$B$54-AA47*'1_Assumptions'!$B$58/365-Z47*'1_Assumptions'!$B$55 | AJ47: =AB47*(1-$B$15)+AC47+AF47+IF($B$19=1,Z47*'1_Assumptions'!$E$31,0)-AD47-(AI47-X47) | AK47: =Z47*(1+('1_Assumptions'!$E$14+$B47)) | AL47: =AK47*(1-'1_Assumptions'!$E$20) | AM47: =AK47-AL47-AK47*$B$11+AK47*$B$12 | AN47: =AE47*$B$13 | AO47: =AK47*'1_Assumptions'!$E$26 | AP47: =AE47+AO47-AN47 | AQ47: =AK47*$B$14 | AR47: =AG47-AQ47 | AS47: =AH47+AK47*$B$16-AH47/$B$18 | AT47: =AK47*'1_Assumptions'!$B$56/365+AL47*'1_Assumptions'!$B$57/365+AK47*'1_Assumptions'!$B$54-AL47*'1_Assumptions'!$B$58/365-AK47*'1_Assumptions'!$B$55 | AU47: =AM47*(1-$B$15)+AN47+AQ47+IF($B$19=1,AK47*'1_Assumptions'!$E$32,0)-AO47-(AT47-AI47) | AV47: =AK47*(1+('1_Assumptions'!$E$15+$B47)) | AW47: =AV47*(1-'1_Assumptions'!$E$21) | AX47: =AV47-AW47-AV47*$B$11+AV47*$B$12 | AY47: =AP47*$B$13 | AZ47: =AV47*'1_Assumptions'!$E$27 | BA47: =AP47+AZ47-AY47 | BB47: =AV47*$B$14 | BC47: =AR47-BB47 | BD47: =AS47+AV47*$B$16-AS47/$B$18 | BE47: =AV47*'1_Assumptions'!$B$56/365+AW47*'1_Assumptions'!$B$57/365+AV47*'1_Assumptions'!$B$54-AW47*'1_Assumptions'!$B$58/365-AV47*'1_Assumptions'!$B$55 | BF47: =AX47*(1-$B$15)+AY47+BB47+IF($B$19=1,AV47*'1_Assumptions'!$E$33,0)-AZ47-(BE47-AT47) | BG47: =N47/(1+$B$21)^(1-0.5*$B$23)+Y47/(1+$B$21)^(2-0.5*$B$23)+AJ47/(1+$B$21)^(3-0.5*$B$23)+AU47/(1+$B$21)^(4-0.5*$B$23)+BF47/(1+$B$21)^(5-0.5*$B$23) | BH47: =BE47+BA47+BC47+$B$9+IF($B$17=1,BD47,0) | BI47: =IF($B$32=2,$B$21+$B$33,IF(BH47=0,0,BL47/BH47)) | BJ47: =IF(BI47=0,9,$C47/BI47) | BK47: =IF(OR(BH47<=0,BI47<=$B$21,BJ47>=1,BJ47<0),1,0) | BL47: =AX47*(1-$B$20) | BM47: =IF(BK47=1,BL47,AX47*(1+$C47)*(1-$B$20)*(1-BJ47)) | BN47: =IF(BK47=1,BL47/$B$21,BM47/($B$21-$C47)) | BO47: =BN47/(1+$B$21)^(5-0.5*$B$23) | BP47: =BG47+BO47 | BQ47: =BP47*(1+$B$21)^$B$24-N47*$B$24*(1+$B$21)^($B$24/2) | BR47: =BQ47-$B$25+$B$26+$B$27 | BS47: =IF($B$28=1,$B$30,BR47*$B$29) | BT47: =BR47-BS47 | BU47: =BT47/$B$31
A48: 3-1 | B48: 0 | C48: 0.01 | D48: =$B$5*(1+('1_Assumptions'!$E$11+IF('1_Assumptions'!$B$39=1,0,$B48))) | E48: =D48*(1-'1_Assumptions'!$E$17) | F48: =D48-E48-D48*$B$11+D48*$B$12 | G48: =$B$6*$B$13 | H48: =D48*'1_Assumptions'!$E$23 | I48: =$B$6+H48-G48 | J48: =D48*$B$14 | K48: =$B$7-J48 | L48: =$B$8+D48*$B$16-$B$8/$B$18 | M48: =D48*'1_Assumptions'!$B$56/365+E48*'1_Assumptions'!$B$57/365+D48*'1_Assumptions'!$B$54-E48*'1_Assumptions'!$B$58/365-D48*'1_Assumptions'!$B$55 | N48: =F48*(1-$B$15)+G48+J48+IF($B$19=1,D48*'1_Assumptions'!$E$29,0)-H48-(M48-$B$10) | O48: =D48*(1+('1_Assumptions'!$E$12+$B48)) | P48: =O48*(1-'1_Assumptions'!$E$18) | Q48: =O48-P48-O48*$B$11+O48*$B$12 | R48: =I48*$B$13 | S48: =O48*'1_Assumptions'!$E$24 | T48: =I48+S48-R48 | U48: =O48*$B$14 | V48: =K48-U48 | W48: =L48+O48*$B$16-L48/$B$18 | X48: =O48*'1_Assumptions'!$B$56/365+P48*'1_Assumptions'!$B$57/365+O48*'1_Assumptions'!$B$54-P48*'1_Assumptions'!$B$58/365-O48*'1_Assumptions'!$B$55 | Y48: =Q48*(1-$B$15)+R48+U48+IF($B$19=1,O48*'1_Assumptions'!$E$30,0)-S48-(X48-M48) | Z48: =O48*(1+('1_Assumptions'!$E$13+$B48)) | AA48: =Z48*(1-'1_Assumptions'!$E$19) | AB48: =Z48-AA48-Z48*$B$11+Z48*$B$12 | AC48: =T48*$B$13 | AD48: =Z48*'1_Assumptions'!$E$25 | AE48: =T48+AD48-AC48 | AF48: =Z48*$B$14 | AG48: =V48-AF48 | AH48: =W48+Z48*$B$16-W48/$B$18 | AI48: =Z48*'1_Assumptions'!$B$56/365+AA48*'1_Assumptions'!$B$57/365+Z48*'1_Assumptions'!$B$54-AA48*'1_Assumptions'!$B$58/365-Z48*'1_Assumptions'!$B$55 | AJ48: =AB48*(1-$B$15)+AC48+AF48+IF($B$19=1,Z48*'1_Assumptions'!$E$31,0)-AD48-(AI48-X48) | AK48: =Z48*(1+('1_Assumptions'!$E$14+$B48)) | AL48: =AK48*(1-'1_Assumptions'!$E$20) | AM48: =AK48-AL48-AK48*$B$11+AK48*$B$12 | AN48: =AE48*$B$13 | AO48: =AK48*'1_Assumptions'!$E$26 | AP48: =AE48+AO48-AN48 | AQ48: =AK48*$B$14 | AR48: =AG48-AQ48 | AS48: =AH48+AK48*$B$16-AH48/$B$18 | AT48: =AK48*'1_Assumptions'!$B$56/365+AL48*'1_Assumptions'!$B$57/365+AK48*'1_Assumptions'!$B$54-AL48*'1_Assumptions'!$B$58/365-AK48*'1_Assumptions'!$B$55 | AU48: =AM48*(1-$B$15)+AN48+AQ48+IF($B$19=1,AK48*'1_Assumptions'!$E$32,0)-AO48-(AT48-AI48) | AV48: =AK48*(1+('1_Assumptions'!$E$15+$B48)) | AW48: =AV48*(1-'1_Assumptions'!$E$21) | AX48: =AV48-AW48-AV48*$B$11+AV48*$B$12 | AY48: =AP48*$B$13 | AZ48: =AV48*'1_Assumptions'!$E$27 | BA48: =AP48+AZ48-AY48 | BB48: =AV48*$B$14 | BC48: =AR48-BB48 | BD48: =AS48+AV48*$B$16-AS48/$B$18 | BE48: =AV48*'1_Assumptions'!$B$56/365+AW48*'1_Assumptions'!$B$57/365+AV48*'1_Assumptions'!$B$54-AW48*'1_Assumptions'!$B$58/365-AV48*'1_Assumptions'!$B$55 | BF48: =AX48*(1-$B$15)+AY48+BB48+IF($B$19=1,AV48*'1_Assumptions'!$E$33,0)-AZ48-(BE48-AT48) | BG48: =N48/(1+$B$21)^(1-0.5*$B$23)+Y48/(1+$B$21)^(2-0.5*$B$23)+AJ48/(1+$B$21)^(3-0.5*$B$23)+AU48/(1+$B$21)^(4-0.5*$B$23)+BF48/(1+$B$21)^(5-0.5*$B$23) | BH48: =BE48+BA48+BC48+$B$9+IF($B$17=1,BD48,0) | BI48: =IF($B$32=2,$B$21+$B$33,IF(BH48=0,0,BL48/BH48)) | BJ48: =IF(BI48=0,9,$C48/BI48) | BK48: =IF(OR(BH48<=0,BI48<=$B$21,BJ48>=1,BJ48<0),1,0) | BL48: =AX48*(1-$B$20) | BM48: =IF(BK48=1,BL48,AX48*(1+$C48)*(1-$B$20)*(1-BJ48)) | BN48: =IF(BK48=1,BL48/$B$21,BM48/($B$21-$C48)) | BO48: =BN48/(1+$B$21)^(5-0.5*$B$23) | BP48: =BG48+BO48 | BQ48: =BP48*(1+$B$21)^$B$24-N48*$B$24*(1+$B$21)^($B$24/2) | BR48: =BQ48-$B$25+$B$26+$B$27 | BS48: =IF($B$28=1,$B$30,BR48*$B$29) | BT48: =BR48-BS48 | BU48: =BT48/$B$31
A49: 3-2 | B49: 0 | C49: 0.0175 | D49: =$B$5*(1+('1_Assumptions'!$E$11+IF('1_Assumptions'!$B$39=1,0,$B49))) | E49: =D49*(1-'1_Assumptions'!$E$17) | F49: =D49-E49-D49*$B$11+D49*$B$12 | G49: =$B$6*$B$13 | H49: =D49*'1_Assumptions'!$E$23 | I49: =$B$6+H49-G49 | J49: =D49*$B$14 | K49: =$B$7-J49 | L49: =$B$8+D49*$B$16-$B$8/$B$18 | M49: =D49*'1_Assumptions'!$B$56/365+E49*'1_Assumptions'!$B$57/365+D49*'1_Assumptions'!$B$54-E49*'1_Assumptions'!$B$58/365-D49*'1_Assumptions'!$B$55 | N49: =F49*(1-$B$15)+G49+J49+IF($B$19=1,D49*'1_Assumptions'!$E$29,0)-H49-(M49-$B$10) | O49: =D49*(1+('1_Assumptions'!$E$12+$B49)) | P49: =O49*(1-'1_Assumptions'!$E$18) | Q49: =O49-P49-O49*$B$11+O49*$B$12 | R49: =I49*$B$13 | S49: =O49*'1_Assumptions'!$E$24 | T49: =I49+S49-R49 | U49: =O49*$B$14 | V49: =K49-U49 | W49: =L49+O49*$B$16-L49/$B$18 | X49: =O49*'1_Assumptions'!$B$56/365+P49*'1_Assumptions'!$B$57/365+O49*'1_Assumptions'!$B$54-P49*'1_Assumptions'!$B$58/365-O49*'1_Assumptions'!$B$55 | Y49: =Q49*(1-$B$15)+R49+U49+IF($B$19=1,O49*'1_Assumptions'!$E$30,0)-S49-(X49-M49) | Z49: =O49*(1+('1_Assumptions'!$E$13+$B49)) | AA49: =Z49*(1-'1_Assumptions'!$E$19) | AB49: =Z49-AA49-Z49*$B$11+Z49*$B$12 | AC49: =T49*$B$13 | AD49: =Z49*'1_Assumptions'!$E$25 | AE49: =T49+AD49-AC49 | AF49: =Z49*$B$14 | AG49: =V49-AF49 | AH49: =W49+Z49*$B$16-W49/$B$18 | AI49: =Z49*'1_Assumptions'!$B$56/365+AA49*'1_Assumptions'!$B$57/365+Z49*'1_Assumptions'!$B$54-AA49*'1_Assumptions'!$B$58/365-Z49*'1_Assumptions'!$B$55 | AJ49: =AB49*(1-$B$15)+AC49+AF49+IF($B$19=1,Z49*'1_Assumptions'!$E$31,0)-AD49-(AI49-X49) | AK49: =Z49*(1+('1_Assumptions'!$E$14+$B49)) | AL49: =AK49*(1-'1_Assumptions'!$E$20) | AM49: =AK49-AL49-AK49*$B$11+AK49*$B$12 | AN49: =AE49*$B$13 | AO49: =AK49*'1_Assumptions'!$E$26 | AP49: =AE49+AO49-AN49 | AQ49: =AK49*$B$14 | AR49: =AG49-AQ49 | AS49: =AH49+AK49*$B$16-AH49/$B$18 | AT49: =AK49*'1_Assumptions'!$B$56/365+AL49*'1_Assumptions'!$B$57/365+AK49*'1_Assumptions'!$B$54-AL49*'1_Assumptions'!$B$58/365-AK49*'1_Assumptions'!$B$55 | AU49: =AM49*(1-$B$15)+AN49+AQ49+IF($B$19=1,AK49*'1_Assumptions'!$E$32,0)-AO49-(AT49-AI49) | AV49: =AK49*(1+('1_Assumptions'!$E$15+$B49)) | AW49: =AV49*(1-'1_Assumptions'!$E$21) | AX49: =AV49-AW49-AV49*$B$11+AV49*$B$12 | AY49: =AP49*$B$13 | AZ49: =AV49*'1_Assumptions'!$E$27 | BA49: =AP49+AZ49-AY49 | BB49: =AV49*$B$14 | BC49: =AR49-BB49 | BD49: =AS49+AV49*$B$16-AS49/$B$18 | BE49: =AV49*'1_Assumptions'!$B$56/365+AW49*'1_Assumptions'!$B$57/365+AV49*'1_Assumptions'!$B$54-AW49*'1_Assumptions'!$B$58/365-AV49*'1_Assumptions'!$B$55 | BF49: =AX49*(1-$B$15)+AY49+BB49+IF($B$19=1,AV49*'1_Assumptions'!$E$33,0)-AZ49-(BE49-AT49) | BG49: =N49/(1+$B$21)^(1-0.5*$B$23)+Y49/(1+$B$21)^(2-0.5*$B$23)+AJ49/(1+$B$21)^(3-0.5*$B$23)+AU49/(1+$B$21)^(4-0.5*$B$23)+BF49/(1+$B$21)^(5-0.5*$B$23) | BH49: =BE49+BA49+BC49+$B$9+IF($B$17=1,BD49,0) | BI49: =IF($B$32=2,$B$21+$B$33,IF(BH49=0,0,BL49/BH49)) | BJ49: =IF(BI49=0,9,$C49/BI49) | BK49: =IF(OR(BH49<=0,BI49<=$B$21,BJ49>=1,BJ49<0),1,0) | BL49: =AX49*(1-$B$20) | BM49: =IF(BK49=1,BL49,AX49*(1+$C49)*(1-$B$20)*(1-BJ49)) | BN49: =IF(BK49=1,BL49/$B$21,BM49/($B$21-$C49)) | BO49: =BN49/(1+$B$21)^(5-0.5*$B$23) | BP49: =BG49+BO49 | BQ49: =BP49*(1+$B$21)^$B$24-N49*$B$24*(1+$B$21)^($B$24/2) | BR49: =BQ49-$B$25+$B$26+$B$27 | BS49: =IF($B$28=1,$B$30,BR49*$B$29) | BT49: =BR49-BS49 | BU49: =BT49/$B$31
... A62: 5-5 | B62: 0.06 | C62: 0.04 | D62: =$B$5*(1+('1_Assumptions'!$E$11+IF('1_Assumptions'!$B$39=1,0,$B62))) | E62: =D62*(1-'1_Assumptions'!$E$17) | F62: =D62-E62-D62*$B$11+D62*$B$12 | G62: =$B$6*$B$13 | H62: =D62*'1_Assumptions'!$E$23 | I62: =$B$6+H62-G62 | J62: =D62*$B$14 | K62: =$B$7-J62 | L62: =$B$8+D62*$B$16-$B$8/$B$18 | M62: =D62*'1_Assumptions'!$B$56/365+E62*'1_Assumptions'!$B$57/365+D62*'1_Assumptions'!$B$54-E62*'1_Assumptions'!$B$58/365-D62*'1_Assumptions'!$B$55 | N62: =F62*(1-$B$15)+G62+J62+IF($B$19=1,D62*'1_Assumptions'!$E$29,0)-H62-(M62-$B$10) | O62: =D62*(1+('1_Assumptions'!$E$12+$B62)) | P62: =O62*(1-'1_Assumptions'!$E$18) | Q62: =O62-P62-O62*$B$11+O62*$B$12 | R62: =I62*$B$13 | S62: =O62*'1_Assumptions'!$E$24 | T62: =I62+S62-R62 | U62: =O62*$B$14 | V62: =K62-U62 | W62: =L62+O62*$B$16-L62/$B$18 | X62: =O62*'1_Assumptions'!$B$56/365+P62*'1_Assumptions'!$B$57/365+O62*'1_Assumptions'!$B$54-P62*'1_Assumptions'!$B$58/365-O62*'1_Assumptions'!$B$55 | Y62: =Q62*(1-$B$15)+R62+U62+IF($B$19=1,O62*'1_Assumptions'!$E$30,0)-S62-(X62-M62) | Z62: =O62*(1+('1_Assumptions'!$E$13+$B62)) | AA62: =Z62*(1-'1_Assumptions'!$E$19) | AB62: =Z62-AA62-Z62*$B$11+Z62*$B$12 | AC62: =T62*$B$13 | AD62: =Z62*'1_Assumptions'!$E$25 | AE62: =T62+AD62-AC62 | AF62: =Z62*$B$14 | AG62: =V62-AF62 | AH62: =W62+Z62*$B$16-W62/$B$18 | AI62: =Z62*'1_Assumptions'!$B$56/365+AA62*'1_Assumptions'!$B$57/365+Z62*'1_Assumptions'!$B$54-AA62*'1_Assumptions'!$B$58/365-Z62*'1_Assumptions'!$B$55 | AJ62: =AB62*(1-$B$15)+AC62+AF62+IF($B$19=1,Z62*'1_Assumptions'!$E$31,0)-AD62-(AI62-X62) | AK62: =Z62*(1+('1_Assumptions'!$E$14+$B62)) | AL62: =AK62*(1-'1_Assumptions'!$E$20) | AM62: =AK62-AL62-AK62*$B$11+AK62*$B$12 | AN62: =AE62*$B$13 | AO62: =AK62*'1_Assumptions'!$E$26 | AP62: =AE62+AO62-AN62 | AQ62: =AK62*$B$14 | AR62: =AG62-AQ62 | AS62: =AH62+AK62*$B$16-AH62/$B$18 | AT62: =AK62*'1_Assumptions'!$B$56/365+AL62*'1_Assumptions'!$B$57/365+AK62*'1_Assumptions'!$B$54-AL62*'1_Assumptions'!$B$58/365-AK62*'1_Assumptions'!$B$55 | AU62: =AM62*(1-$B$15)+AN62+AQ62+IF($B$19=1,AK62*'1_Assumptions'!$E$32,0)-AO62-(AT62-AI62) | AV62: =AK62*(1+('1_Assumptions'!$E$15+$B62)) | AW62: =AV62*(1-'1_Assumptions'!$E$21) | AX62: =AV62-AW62-AV62*$B$11+AV62*$B$12 | AY62: =AP62*$B$13 | AZ62: =AV62*'1_Assumptions'!$E$27 | BA62: =AP62+AZ62-AY62 | BB62: =AV62*$B$14 | BC62: =AR62-BB62 | BD62: =AS62+AV62*$B$16-AS62/$B$18 | BE62: =AV62*'1_Assumptions'!$B$56/365+AW62*'1_Assumptions'!$B$57/365+AV62*'1_Assumptions'!$B$54-AW62*'1_Assumptions'!$B$58/365-AV62*'1_Assumptions'!$B$55 | BF62: =AX62*(1-$B$15)+AY62+BB62+IF($B$19=1,AV62*'1_Assumptions'!$E$33,0)-AZ62-(BE62-AT62) | BG62: =N62/(1+$B$21)^(1-0.5*$B$23)+Y62/(1+$B$21)^(2-0.5*$B$23)+AJ62/(1+$B$21)^(3-0.5*$B$23)+AU62/(1+$B$21)^(4-0.5*$B$23)+BF62/(1+$B$21)^(5-0.5*$B$23) | BH62: =BE62+BA62+BC62+$B$9+IF($B$17=1,BD62,0) | BI62: =IF($B$32=2,$B$21+$B$33,IF(BH62=0,0,BL62/BH62)) | BJ62: =IF(BI62=0,9,$C62/BI62) | BK62: =IF(OR(BH62<=0,BI62<=$B$21,BJ62>=1,BJ62<0),1,0) | BL62: =AX62*(1-$B$20) | BM62: =IF(BK62=1,BL62,AX62*(1+$C62)*(1-$B$20)*(1-BJ62)) | BN62: =IF(BK62=1,BL62/$B$21,BM62/($B$21-$C62)) | BO62: =BN62/(1+$B$21)^(5-0.5*$B$23) | BP62: =BG62+BO62 | BQ62: =BP62*(1+$B$21)^$B$24-N62*$B$24*(1+$B$21)^($B$24/2) | BR62: =BQ62-$B$25+$B$26+$B$27 | BS62: =IF($B$28=1,$B$30,BR62*$B$29) | BT62: =BR62-BS62 | BU62: =BT62/$B$31
A64: 模块 B：毛利率平移 × 永续增长率 g
A65: 毛利率是判断项里最敏感的一个：1pp 的持续偏差会被终值放大
A66: 场景 | B66: 毛利率 Δ | C66: 永续 g | D66: 营收1 | E66: 成本1 | F66: EBIT1 | G66: 折旧1 | H66: 资本开支1 | I66: 期末固资1 | J66: 摊销1 | K66: 商誉无形1 | L66: 研发资本1 | M66: NWC1 | N66: FCFF1 | O66: 营收2 | P66: 成本2 | Q66: EBIT2 | R66: 折旧2 | S66: 资本开支2 | T66: 期末固资2 | U66: 摊销2 | V66: 商誉无形2 | W66: 研发资本2 | X66: NWC2 | Y66: FCFF2 | Z66: 营收3 | AA66: 成本3 | AB66: EBIT3 | AC66: 折旧3 | AD66: 资本开支3 | AE66: 期末固资3 | AF66: 摊销3 | AG66: 商誉无形3 | AH66: 研发资本3 | AI66: NWC3 | AJ66: FCFF3 | AK66: 营收4 | AL66: 成本4 | AM66: EBIT4 | AN66: 折旧4 | AO66: 资本开支4 | AP66: 期末固资4 | AQ66: 摊销4 | AR66: 商誉无形4 | AS66: 研发资本4 | AT66: NWC4 | AU66: FCFF4 | AV66: 营收5 | AW66: 成本5 | AX66: EBIT5 | AY66: 折旧5 | AZ66: 资本开支5 | BA66: 期末固资5 | BB66: 摊销5 | BC66: 商誉无形5 | BD66: 研发资本5 | BE66: NWC5 | BF66: FCFF5 | BG66: PV明确期 | BH66: 终值IC | BI66: 终值ROIC | BJ66: 再投资率 | BK66: 降级 | BL66: 终值NOPAT | BM66: 终值FCFF | BN66: TV | BO66: PV(TV) | BP66: EV0 | BQ66: EV | BR66: 全体权益 | BS66: 少数股东 | BT66: 归母权益 | BU66: 每股
A67: 1-1 | B67: -0.04 | C67: 0.01 | D67: =$B$5*(1+'1_Assumptions'!$E$11) | E67: =D67*(1-('1_Assumptions'!$E$17+IF('1_Assumptions'!$B$39=1,0,$B67))) | F67: =D67-E67-D67*$B$11+D67*$B$12 | G67: =$B$6*$B$13 | H67: =D67*'1_Assumptions'!$E$23 | I67: =$B$6+H67-G67 | J67: =D67*$B$14 | K67: =$B$7-J67 | L67: =$B$8+D67*$B$16-$B$8/$B$18 | M67: =D67*'1_Assumptions'!$B$56/365+E67*'1_Assumptions'!$B$57/365+D67*'1_Assumptions'!$B$54-E67*'1_Assumptions'!$B$58/365-D67*'1_Assumptions'!$B$55 | N67: =F67*(1-$B$15)+G67+J67+IF($B$19=1,D67*'1_Assumptions'!$E$29,0)-H67-(M67-$B$10) | O67: =D67*(1+'1_Assumptions'!$E$12) | P67: =O67*(1-('1_Assumptions'!$E$18+$B67)) | Q67: =O67-P67-O67*$B$11+O67*$B$12 | R67: =I67*$B$13 | S67: =O67*'1_Assumptions'!$E$24 | T67: =I67+S67-R67 | U67: =O67*$B$14 | V67: =K67-U67 | W67: =L67+O67*$B$16-L67/$B$18 | X67: =O67*'1_Assumptions'!$B$56/365+P67*'1_Assumptions'!$B$57/365+O67*'1_Assumptions'!$B$54-P67*'1_Assumptions'!$B$58/365-O67*'1_Assumptions'!$B$55 | Y67: =Q67*(1-$B$15)+R67+U67+IF($B$19=1,O67*'1_Assumptions'!$E$30,0)-S67-(X67-M67) | Z67: =O67*(1+'1_Assumptions'!$E$13) | AA67: =Z67*(1-('1_Assumptions'!$E$19+$B67)) | AB67: =Z67-AA67-Z67*$B$11+Z67*$B$12 | AC67: =T67*$B$13 | AD67: =Z67*'1_Assumptions'!$E$25 | AE67: =T67+AD67-AC67 | AF67: =Z67*$B$14 | AG67: =V67-AF67 | AH67: =W67+Z67*$B$16-W67/$B$18 | AI67: =Z67*'1_Assumptions'!$B$56/365+AA67*'1_Assumptions'!$B$57/365+Z67*'1_Assumptions'!$B$54-AA67*'1_Assumptions'!$B$58/365-Z67*'1_Assumptions'!$B$55 | AJ67: =AB67*(1-$B$15)+AC67+AF67+IF($B$19=1,Z67*'1_Assumptions'!$E$31,0)-AD67-(AI67-X67) | AK67: =Z67*(1+'1_Assumptions'!$E$14) | AL67: =AK67*(1-('1_Assumptions'!$E$20+$B67)) | AM67: =AK67-AL67-AK67*$B$11+AK67*$B$12 | AN67: =AE67*$B$13 | AO67: =AK67*'1_Assumptions'!$E$26 | AP67: =AE67+AO67-AN67 | AQ67: =AK67*$B$14 | AR67: =AG67-AQ67 | AS67: =AH67+AK67*$B$16-AH67/$B$18 | AT67: =AK67*'1_Assumptions'!$B$56/365+AL67*'1_Assumptions'!$B$57/365+AK67*'1_Assumptions'!$B$54-AL67*'1_Assumptions'!$B$58/365-AK67*'1_Assumptions'!$B$55 | AU67: =AM67*(1-$B$15)+AN67+AQ67+IF($B$19=1,AK67*'1_Assumptions'!$E$32,0)-AO67-(AT67-AI67) | AV67: =AK67*(1+'1_Assumptions'!$E$15) | AW67: =AV67*(1-('1_Assumptions'!$E$21+$B67)) | AX67: =AV67-AW67-AV67*$B$11+AV67*$B$12 | AY67: =AP67*$B$13 | AZ67: =AV67*'1_Assumptions'!$E$27 | BA67: =AP67+AZ67-AY67 | BB67: =AV67*$B$14 | BC67: =AR67-BB67 | BD67: =AS67+AV67*$B$16-AS67/$B$18 | BE67: =AV67*'1_Assumptions'!$B$56/365+AW67*'1_Assumptions'!$B$57/365+AV67*'1_Assumptions'!$B$54-AW67*'1_Assumptions'!$B$58/365-AV67*'1_Assumptions'!$B$55 | BF67: =AX67*(1-$B$15)+AY67+BB67+IF($B$19=1,AV67*'1_Assumptions'!$E$33,0)-AZ67-(BE67-AT67) | BG67: =N67/(1+$B$21)^(1-0.5*$B$23)+Y67/(1+$B$21)^(2-0.5*$B$23)+AJ67/(1+$B$21)^(3-0.5*$B$23)+AU67/(1+$B$21)^(4-0.5*$B$23)+BF67/(1+$B$21)^(5-0.5*$B$23) | BH67: =BE67+BA67+BC67+$B$9+IF($B$17=1,BD67,0) | BI67: =IF($B$32=2,$B$21+$B$33,IF(BH67=0,0,BL67/BH67)) | BJ67: =IF(BI67=0,9,$C67/BI67) | BK67: =IF(OR(BH67<=0,BI67<=$B$21,BJ67>=1,BJ67<0),1,0) | BL67: =AX67*(1-$B$20) | BM67: =IF(BK67=1,BL67,AX67*(1+$C67)*(1-$B$20)*(1-BJ67)) | BN67: =IF(BK67=1,BL67/$B$21,BM67/($B$21-$C67)) | BO67: =BN67/(1+$B$21)^(5-0.5*$B$23) | BP67: =BG67+BO67 | BQ67: =BP67*(1+$B$21)^$B$24-N67*$B$24*(1+$B$21)^($B$24/2) | BR67: =BQ67-$B$25+$B$26+$B$27 | BS67: =IF($B$28=1,$B$30,BR67*$B$29) | BT67: =BR67-BS67 | BU67: =BT67/$B$31
A68: 1-2 | B68: -0.04 | C68: 0.0175 | D68: =$B$5*(1+'1_Assumptions'!$E$11) | E68: =D68*(1-('1_Assumptions'!$E$17+IF('1_Assumptions'!$B$39=1,0,$B68))) | F68: =D68-E68-D68*$B$11+D68*$B$12 | G68: =$B$6*$B$13 | H68: =D68*'1_Assumptions'!$E$23 | I68: =$B$6+H68-G68 | J68: =D68*$B$14 | K68: =$B$7-J68 | L68: =$B$8+D68*$B$16-$B$8/$B$18 | M68: =D68*'1_Assumptions'!$B$56/365+E68*'1_Assumptions'!$B$57/365+D68*'1_Assumptions'!$B$54-E68*'1_Assumptions'!$B$58/365-D68*'1_Assumptions'!$B$55 | N68: =F68*(1-$B$15)+G68+J68+IF($B$19=1,D68*'1_Assumptions'!$E$29,0)-H68-(M68-$B$10) | O68: =D68*(1+'1_Assumptions'!$E$12) | P68: =O68*(1-('1_Assumptions'!$E$18+$B68)) | Q68: =O68-P68-O68*$B$11+O68*$B$12 | R68: =I68*$B$13 | S68: =O68*'1_Assumptions'!$E$24 | T68: =I68+S68-R68 | U68: =O68*$B$14 | V68: =K68-U68 | W68: =L68+O68*$B$16-L68/$B$18 | X68: =O68*'1_Assumptions'!$B$56/365+P68*'1_Assumptions'!$B$57/365+O68*'1_Assumptions'!$B$54-P68*'1_Assumptions'!$B$58/365-O68*'1_Assumptions'!$B$55 | Y68: =Q68*(1-$B$15)+R68+U68+IF($B$19=1,O68*'1_Assumptions'!$E$30,0)-S68-(X68-M68) | Z68: =O68*(1+'1_Assumptions'!$E$13) | AA68: =Z68*(1-('1_Assumptions'!$E$19+$B68)) | AB68: =Z68-AA68-Z68*$B$11+Z68*$B$12 | AC68: =T68*$B$13 | AD68: =Z68*'1_Assumptions'!$E$25 | AE68: =T68+AD68-AC68 | AF68: =Z68*$B$14 | AG68: =V68-AF68 | AH68: =W68+Z68*$B$16-W68/$B$18 | AI68: =Z68*'1_Assumptions'!$B$56/365+AA68*'1_Assumptions'!$B$57/365+Z68*'1_Assumptions'!$B$54-AA68*'1_Assumptions'!$B$58/365-Z68*'1_Assumptions'!$B$55 | AJ68: =AB68*(1-$B$15)+AC68+AF68+IF($B$19=1,Z68*'1_Assumptions'!$E$31,0)-AD68-(AI68-X68) | AK68: =Z68*(1+'1_Assumptions'!$E$14) | AL68: =AK68*(1-('1_Assumptions'!$E$20+$B68)) | AM68: =AK68-AL68-AK68*$B$11+AK68*$B$12 | AN68: =AE68*$B$13 | AO68: =AK68*'1_Assumptions'!$E$26 | AP68: =AE68+AO68-AN68 | AQ68: =AK68*$B$14 | AR68: =AG68-AQ68 | AS68: =AH68+AK68*$B$16-AH68/$B$18 | AT68: =AK68*'1_Assumptions'!$B$56/365+AL68*'1_Assumptions'!$B$57/365+AK68*'1_Assumptions'!$B$54-AL68*'1_Assumptions'!$B$58/365-AK68*'1_Assumptions'!$B$55 | AU68: =AM68*(1-$B$15)+AN68+AQ68+IF($B$19=1,AK68*'1_Assumptions'!$E$32,0)-AO68-(AT68-AI68) | AV68: =AK68*(1+'1_Assumptions'!$E$15) | AW68: =AV68*(1-('1_Assumptions'!$E$21+$B68)) | AX68: =AV68-AW68-AV68*$B$11+AV68*$B$12 | AY68: =AP68*$B$13 | AZ68: =AV68*'1_Assumptions'!$E$27 | BA68: =AP68+AZ68-AY68 | BB68: =AV68*$B$14 | BC68: =AR68-BB68 | BD68: =AS68+AV68*$B$16-AS68/$B$18 | BE68: =AV68*'1_Assumptions'!$B$56/365+AW68*'1_Assumptions'!$B$57/365+AV68*'1_Assumptions'!$B$54-AW68*'1_Assumptions'!$B$58/365-AV68*'1_Assumptions'!$B$55 | BF68: =AX68*(1-$B$15)+AY68+BB68+IF($B$19=1,AV68*'1_Assumptions'!$E$33,0)-AZ68-(BE68-AT68) | BG68: =N68/(1+$B$21)^(1-0.5*$B$23)+Y68/(1+$B$21)^(2-0.5*$B$23)+AJ68/(1+$B$21)^(3-0.5*$B$23)+AU68/(1+$B$21)^(4-0.5*$B$23)+BF68/(1+$B$21)^(5-0.5*$B$23) | BH68: =BE68+BA68+BC68+$B$9+IF($B$17=1,BD68,0) | BI68: =IF($B$32=2,$B$21+$B$33,IF(BH68=0,0,BL68/BH68)) | BJ68: =IF(BI68=0,9,$C68/BI68) | BK68: =IF(OR(BH68<=0,BI68<=$B$21,BJ68>=1,BJ68<0),1,0) | BL68: =AX68*(1-$B$20) | BM68: =IF(BK68=1,BL68,AX68*(1+$C68)*(1-$B$20)*(1-BJ68)) | BN68: =IF(BK68=1,BL68/$B$21,BM68/($B$21-$C68)) | BO68: =BN68/(1+$B$21)^(5-0.5*$B$23) | BP68: =BG68+BO68 | BQ68: =BP68*(1+$B$21)^$B$24-N68*$B$24*(1+$B$21)^($B$24/2) | BR68: =BQ68-$B$25+$B$26+$B$27 | BS68: =IF($B$28=1,$B$30,BR68*$B$29) | BT68: =BR68-BS68 | BU68: =BT68/$B$31
A69: 1-3 | B69: -0.04 | C69: 0.025 | D69: =$B$5*(1+'1_Assumptions'!$E$11) | E69: =D69*(1-('1_Assumptions'!$E$17+IF('1_Assumptions'!$B$39=1,0,$B69))) | F69: =D69-E69-D69*$B$11+D69*$B$12 | G69: =$B$6*$B$13 | H69: =D69*'1_Assumptions'!$E$23 | I69: =$B$6+H69-G69 | J69: =D69*$B$14 | K69: =$B$7-J69 | L69: =$B$8+D69*$B$16-$B$8/$B$18 | M69: =D69*'1_Assumptions'!$B$56/365+E69*'1_Assumptions'!$B$57/365+D69*'1_Assumptions'!$B$54-E69*'1_Assumptions'!$B$58/365-D69*'1_Assumptions'!$B$55 | N69: =F69*(1-$B$15)+G69+J69+IF($B$19=1,D69*'1_Assumptions'!$E$29,0)-H69-(M69-$B$10) | O69: =D69*(1+'1_Assumptions'!$E$12) | P69: =O69*(1-('1_Assumptions'!$E$18+$B69)) | Q69: =O69-P69-O69*$B$11+O69*$B$12 | R69: =I69*$B$13 | S69: =O69*'1_Assumptions'!$E$24 | T69: =I69+S69-R69 | U69: =O69*$B$14 | V69: =K69-U69 | W69: =L69+O69*$B$16-L69/$B$18 | X69: =O69*'1_Assumptions'!$B$56/365+P69*'1_Assumptions'!$B$57/365+O69*'1_Assumptions'!$B$54-P69*'1_Assumptions'!$B$58/365-O69*'1_Assumptions'!$B$55 | Y69: =Q69*(1-$B$15)+R69+U69+IF($B$19=1,O69*'1_Assumptions'!$E$30,0)-S69-(X69-M69) | Z69: =O69*(1+'1_Assumptions'!$E$13) | AA69: =Z69*(1-('1_Assumptions'!$E$19+$B69)) | AB69: =Z69-AA69-Z69*$B$11+Z69*$B$12 | AC69: =T69*$B$13 | AD69: =Z69*'1_Assumptions'!$E$25 | AE69: =T69+AD69-AC69 | AF69: =Z69*$B$14 | AG69: =V69-AF69 | AH69: =W69+Z69*$B$16-W69/$B$18 | AI69: =Z69*'1_Assumptions'!$B$56/365+AA69*'1_Assumptions'!$B$57/365+Z69*'1_Assumptions'!$B$54-AA69*'1_Assumptions'!$B$58/365-Z69*'1_Assumptions'!$B$55 | AJ69: =AB69*(1-$B$15)+AC69+AF69+IF($B$19=1,Z69*'1_Assumptions'!$E$31,0)-AD69-(AI69-X69) | AK69: =Z69*(1+'1_Assumptions'!$E$14) | AL69: =AK69*(1-('1_Assumptions'!$E$20+$B69)) | AM69: =AK69-AL69-AK69*$B$11+AK69*$B$12 | AN69: =AE69*$B$13 | AO69: =AK69*'1_Assumptions'!$E$26 | AP69: =AE69+AO69-AN69 | AQ69: =AK69*$B$14 | AR69: =AG69-AQ69 | AS69: =AH69+AK69*$B$16-AH69/$B$18 | AT69: =AK69*'1_Assumptions'!$B$56/365+AL69*'1_Assumptions'!$B$57/365+AK69*'1_Assumptions'!$B$54-AL69*'1_Assumptions'!$B$58/365-AK69*'1_Assumptions'!$B$55 | AU69: =AM69*(1-$B$15)+AN69+AQ69+IF($B$19=1,AK69*'1_Assumptions'!$E$32,0)-AO69-(AT69-AI69) | AV69: =AK69*(1+'1_Assumptions'!$E$15) | AW69: =AV69*(1-('1_Assumptions'!$E$21+$B69)) | AX69: =AV69-AW69-AV69*$B$11+AV69*$B$12 | AY69: =AP69*$B$13 | AZ69: =AV69*'1_Assumptions'!$E$27 | BA69: =AP69+AZ69-AY69 | BB69: =AV69*$B$14 | BC69: =AR69-BB69 | BD69: =AS69+AV69*$B$16-AS69/$B$18 | BE69: =AV69*'1_Assumptions'!$B$56/365+AW69*'1_Assumptions'!$B$57/365+AV69*'1_Assumptions'!$B$54-AW69*'1_Assumptions'!$B$58/365-AV69*'1_Assumptions'!$B$55 | BF69: =AX69*(1-$B$15)+AY69+BB69+IF($B$19=1,AV69*'1_Assumptions'!$E$33,0)-AZ69-(BE69-AT69) | BG69: =N69/(1+$B$21)^(1-0.5*$B$23)+Y69/(1+$B$21)^(2-0.5*$B$23)+AJ69/(1+$B$21)^(3-0.5*$B$23)+AU69/(1+$B$21)^(4-0.5*$B$23)+BF69/(1+$B$21)^(5-0.5*$B$23) | BH69: =BE69+BA69+BC69+$B$9+IF($B$17=1,BD69,0) | BI69: =IF($B$32=2,$B$21+$B$33,IF(BH69=0,0,BL69/BH69)) | BJ69: =IF(BI69=0,9,$C69/BI69) | BK69: =IF(OR(BH69<=0,BI69<=$B$21,BJ69>=1,BJ69<0),1,0) | BL69: =AX69*(1-$B$20) | BM69: =IF(BK69=1,BL69,AX69*(1+$C69)*(1-$B$20)*(1-BJ69)) | BN69: =IF(BK69=1,BL69/$B$21,BM69/($B$21-$C69)) | BO69: =BN69/(1+$B$21)^(5-0.5*$B$23) | BP69: =BG69+BO69 | BQ69: =BP69*(1+$B$21)^$B$24-N69*$B$24*(1+$B$21)^($B$24/2) | BR69: =BQ69-$B$25+$B$26+$B$27 | BS69: =IF($B$28=1,$B$30,BR69*$B$29) | BT69: =BR69-BS69 | BU69: =BT69/$B$31
A70: 1-4 | B70: -0.04 | C70: 0.0325 | D70: =$B$5*(1+'1_Assumptions'!$E$11) | E70: =D70*(1-('1_Assumptions'!$E$17+IF('1_Assumptions'!$B$39=1,0,$B70))) | F70: =D70-E70-D70*$B$11+D70*$B$12 | G70: =$B$6*$B$13 | H70: =D70*'1_Assumptions'!$E$23 | I70: =$B$6+H70-G70 | J70: =D70*$B$14 | K70: =$B$7-J70 | L70: =$B$8+D70*$B$16-$B$8/$B$18 | M70: =D70*'1_Assumptions'!$B$56/365+E70*'1_Assumptions'!$B$57/365+D70*'1_Assumptions'!$B$54-E70*'1_Assumptions'!$B$58/365-D70*'1_Assumptions'!$B$55 | N70: =F70*(1-$B$15)+G70+J70+IF($B$19=1,D70*'1_Assumptions'!$E$29,0)-H70-(M70-$B$10) | O70: =D70*(1+'1_Assumptions'!$E$12) | P70: =O70*(1-('1_Assumptions'!$E$18+$B70)) | Q70: =O70-P70-O70*$B$11+O70*$B$12 | R70: =I70*$B$13 | S70: =O70*'1_Assumptions'!$E$24 | T70: =I70+S70-R70 | U70: =O70*$B$14 | V70: =K70-U70 | W70: =L70+O70*$B$16-L70/$B$18 | X70: =O70*'1_Assumptions'!$B$56/365+P70*'1_Assumptions'!$B$57/365+O70*'1_Assumptions'!$B$54-P70*'1_Assumptions'!$B$58/365-O70*'1_Assumptions'!$B$55 | Y70: =Q70*(1-$B$15)+R70+U70+IF($B$19=1,O70*'1_Assumptions'!$E$30,0)-S70-(X70-M70) | Z70: =O70*(1+'1_Assumptions'!$E$13) | AA70: =Z70*(1-('1_Assumptions'!$E$19+$B70)) | AB70: =Z70-AA70-Z70*$B$11+Z70*$B$12 | AC70: =T70*$B$13 | AD70: =Z70*'1_Assumptions'!$E$25 | AE70: =T70+AD70-AC70 | AF70: =Z70*$B$14 | AG70: =V70-AF70 | AH70: =W70+Z70*$B$16-W70/$B$18 | AI70: =Z70*'1_Assumptions'!$B$56/365+AA70*'1_Assumptions'!$B$57/365+Z70*'1_Assumptions'!$B$54-AA70*'1_Assumptions'!$B$58/365-Z70*'1_Assumptions'!$B$55 | AJ70: =AB70*(1-$B$15)+AC70+AF70+IF($B$19=1,Z70*'1_Assumptions'!$E$31,0)-AD70-(AI70-X70) | AK70: =Z70*(1+'1_Assumptions'!$E$14) | AL70: =AK70*(1-('1_Assumptions'!$E$20+$B70)) | AM70: =AK70-AL70-AK70*$B$11+AK70*$B$12 | AN70: =AE70*$B$13 | AO70: =AK70*'1_Assumptions'!$E$26 | AP70: =AE70+AO70-AN70 | AQ70: =AK70*$B$14 | AR70: =AG70-AQ70 | AS70: =AH70+AK70*$B$16-AH70/$B$18 | AT70: =AK70*'1_Assumptions'!$B$56/365+AL70*'1_Assumptions'!$B$57/365+AK70*'1_Assumptions'!$B$54-AL70*'1_Assumptions'!$B$58/365-AK70*'1_Assumptions'!$B$55 | AU70: =AM70*(1-$B$15)+AN70+AQ70+IF($B$19=1,AK70*'1_Assumptions'!$E$32,0)-AO70-(AT70-AI70) | AV70: =AK70*(1+'1_Assumptions'!$E$15) | AW70: =AV70*(1-('1_Assumptions'!$E$21+$B70)) | AX70: =AV70-AW70-AV70*$B$11+AV70*$B$12 | AY70: =AP70*$B$13 | AZ70: =AV70*'1_Assumptions'!$E$27 | BA70: =AP70+AZ70-AY70 | BB70: =AV70*$B$14 | BC70: =AR70-BB70 | BD70: =AS70+AV70*$B$16-AS70/$B$18 | BE70: =AV70*'1_Assumptions'!$B$56/365+AW70*'1_Assumptions'!$B$57/365+AV70*'1_Assumptions'!$B$54-AW70*'1_Assumptions'!$B$58/365-AV70*'1_Assumptions'!$B$55 | BF70: =AX70*(1-$B$15)+AY70+BB70+IF($B$19=1,AV70*'1_Assumptions'!$E$33,0)-AZ70-(BE70-AT70) | BG70: =N70/(1+$B$21)^(1-0.5*$B$23)+Y70/(1+$B$21)^(2-0.5*$B$23)+AJ70/(1+$B$21)^(3-0.5*$B$23)+AU70/(1+$B$21)^(4-0.5*$B$23)+BF70/(1+$B$21)^(5-0.5*$B$23) | BH70: =BE70+BA70+BC70+$B$9+IF($B$17=1,BD70,0) | BI70: =IF($B$32=2,$B$21+$B$33,IF(BH70=0,0,BL70/BH70)) | BJ70: =IF(BI70=0,9,$C70/BI70) | BK70: =IF(OR(BH70<=0,BI70<=$B$21,BJ70>=1,BJ70<0),1,0) | BL70: =AX70*(1-$B$20) | BM70: =IF(BK70=1,BL70,AX70*(1+$C70)*(1-$B$20)*(1-BJ70)) | BN70: =IF(BK70=1,BL70/$B$21,BM70/($B$21-$C70)) | BO70: =BN70/(1+$B$21)^(5-0.5*$B$23) | BP70: =BG70+BO70 | BQ70: =BP70*(1+$B$21)^$B$24-N70*$B$24*(1+$B$21)^($B$24/2) | BR70: =BQ70-$B$25+$B$26+$B$27 | BS70: =IF($B$28=1,$B$30,BR70*$B$29) | BT70: =BR70-BS70 | BU70: =BT70/$B$31
A71: 1-5 | B71: -0.04 | C71: 0.04 | D71: =$B$5*(1+'1_Assumptions'!$E$11) | E71: =D71*(1-('1_Assumptions'!$E$17+IF('1_Assumptions'!$B$39=1,0,$B71))) | F71: =D71-E71-D71*$B$11+D71*$B$12 | G71: =$B$6*$B$13 | H71: =D71*'1_Assumptions'!$E$23 | I71: =$B$6+H71-G71 | J71: =D71*$B$14 | K71: =$B$7-J71 | L71: =$B$8+D71*$B$16-$B$8/$B$18 | M71: =D71*'1_Assumptions'!$B$56/365+E71*'1_Assumptions'!$B$57/365+D71*'1_Assumptions'!$B$54-E71*'1_Assumptions'!$B$58/365-D71*'1_Assumptions'!$B$55 | N71: =F71*(1-$B$15)+G71+J71+IF($B$19=1,D71*'1_Assumptions'!$E$29,0)-H71-(M71-$B$10) | O71: =D71*(1+'1_Assumptions'!$E$12) | P71: =O71*(1-('1_Assumptions'!$E$18+$B71)) | Q71: =O71-P71-O71*$B$11+O71*$B$12 | R71: =I71*$B$13 | S71: =O71*'1_Assumptions'!$E$24 | T71: =I71+S71-R71 | U71: =O71*$B$14 | V71: =K71-U71 | W71: =L71+O71*$B$16-L71/$B$18 | X71: =O71*'1_Assumptions'!$B$56/365+P71*'1_Assumptions'!$B$57/365+O71*'1_Assumptions'!$B$54-P71*'1_Assumptions'!$B$58/365-O71*'1_Assumptions'!$B$55 | Y71: =Q71*(1-$B$15)+R71+U71+IF($B$19=1,O71*'1_Assumptions'!$E$30,0)-S71-(X71-M71) | Z71: =O71*(1+'1_Assumptions'!$E$13) | AA71: =Z71*(1-('1_Assumptions'!$E$19+$B71)) | AB71: =Z71-AA71-Z71*$B$11+Z71*$B$12 | AC71: =T71*$B$13 | AD71: =Z71*'1_Assumptions'!$E$25 | AE71: =T71+AD71-AC71 | AF71: =Z71*$B$14 | AG71: =V71-AF71 | AH71: =W71+Z71*$B$16-W71/$B$18 | AI71: =Z71*'1_Assumptions'!$B$56/365+AA71*'1_Assumptions'!$B$57/365+Z71*'1_Assumptions'!$B$54-AA71*'1_Assumptions'!$B$58/365-Z71*'1_Assumptions'!$B$55 | AJ71: =AB71*(1-$B$15)+AC71+AF71+IF($B$19=1,Z71*'1_Assumptions'!$E$31,0)-AD71-(AI71-X71) | AK71: =Z71*(1+'1_Assumptions'!$E$14) | AL71: =AK71*(1-('1_Assumptions'!$E$20+$B71)) | AM71: =AK71-AL71-AK71*$B$11+AK71*$B$12 | AN71: =AE71*$B$13 | AO71: =AK71*'1_Assumptions'!$E$26 | AP71: =AE71+AO71-AN71 | AQ71: =AK71*$B$14 | AR71: =AG71-AQ71 | AS71: =AH71+AK71*$B$16-AH71/$B$18 | AT71: =AK71*'1_Assumptions'!$B$56/365+AL71*'1_Assumptions'!$B$57/365+AK71*'1_Assumptions'!$B$54-AL71*'1_Assumptions'!$B$58/365-AK71*'1_Assumptions'!$B$55 | AU71: =AM71*(1-$B$15)+AN71+AQ71+IF($B$19=1,AK71*'1_Assumptions'!$E$32,0)-AO71-(AT71-AI71) | AV71: =AK71*(1+'1_Assumptions'!$E$15) | AW71: =AV71*(1-('1_Assumptions'!$E$21+$B71)) | AX71: =AV71-AW71-AV71*$B$11+AV71*$B$12 | AY71: =AP71*$B$13 | AZ71: =AV71*'1_Assumptions'!$E$27 | BA71: =AP71+AZ71-AY71 | BB71: =AV71*$B$14 | BC71: =AR71-BB71 | BD71: =AS71+AV71*$B$16-AS71/$B$18 | BE71: =AV71*'1_Assumptions'!$B$56/365+AW71*'1_Assumptions'!$B$57/365+AV71*'1_Assumptions'!$B$54-AW71*'1_Assumptions'!$B$58/365-AV71*'1_Assumptions'!$B$55 | BF71: =AX71*(1-$B$15)+AY71+BB71+IF($B$19=1,AV71*'1_Assumptions'!$E$33,0)-AZ71-(BE71-AT71) | BG71: =N71/(1+$B$21)^(1-0.5*$B$23)+Y71/(1+$B$21)^(2-0.5*$B$23)+AJ71/(1+$B$21)^(3-0.5*$B$23)+AU71/(1+$B$21)^(4-0.5*$B$23)+BF71/(1+$B$21)^(5-0.5*$B$23) | BH71: =BE71+BA71+BC71+$B$9+IF($B$17=1,BD71,0) | BI71: =IF($B$32=2,$B$21+$B$33,IF(BH71=0,0,BL71/BH71)) | BJ71: =IF(BI71=0,9,$C71/BI71) | BK71: =IF(OR(BH71<=0,BI71<=$B$21,BJ71>=1,BJ71<0),1,0) | BL71: =AX71*(1-$B$20) | BM71: =IF(BK71=1,BL71,AX71*(1+$C71)*(1-$B$20)*(1-BJ71)) | BN71: =IF(BK71=1,BL71/$B$21,BM71/($B$21-$C71)) | BO71: =BN71/(1+$B$21)^(5-0.5*$B$23) | BP71: =BG71+BO71 | BQ71: =BP71*(1+$B$21)^$B$24-N71*$B$24*(1+$B$21)^($B$24/2) | BR71: =BQ71-$B$25+$B$26+$B$27 | BS71: =IF($B$28=1,$B$30,BR71*$B$29) | BT71: =BR71-BS71 | BU71: =BT71/$B$31
A72: 2-1 | B72: -0.02 | C72: 0.01 | D72: =$B$5*(1+'1_Assumptions'!$E$11) | E72: =D72*(1-('1_Assumptions'!$E$17+IF('1_Assumptions'!$B$39=1,0,$B72))) | F72: =D72-E72-D72*$B$11+D72*$B$12 | G72: =$B$6*$B$13 | H72: =D72*'1_Assumptions'!$E$23 | I72: =$B$6+H72-G72 | J72: =D72*$B$14 | K72: =$B$7-J72 | L72: =$B$8+D72*$B$16-$B$8/$B$18 | M72: =D72*'1_Assumptions'!$B$56/365+E72*'1_Assumptions'!$B$57/365+D72*'1_Assumptions'!$B$54-E72*'1_Assumptions'!$B$58/365-D72*'1_Assumptions'!$B$55 | N72: =F72*(1-$B$15)+G72+J72+IF($B$19=1,D72*'1_Assumptions'!$E$29,0)-H72-(M72-$B$10) | O72: =D72*(1+'1_Assumptions'!$E$12) | P72: =O72*(1-('1_Assumptions'!$E$18+$B72)) | Q72: =O72-P72-O72*$B$11+O72*$B$12 | R72: =I72*$B$13 | S72: =O72*'1_Assumptions'!$E$24 | T72: =I72+S72-R72 | U72: =O72*$B$14 | V72: =K72-U72 | W72: =L72+O72*$B$16-L72/$B$18 | X72: =O72*'1_Assumptions'!$B$56/365+P72*'1_Assumptions'!$B$57/365+O72*'1_Assumptions'!$B$54-P72*'1_Assumptions'!$B$58/365-O72*'1_Assumptions'!$B$55 | Y72: =Q72*(1-$B$15)+R72+U72+IF($B$19=1,O72*'1_Assumptions'!$E$30,0)-S72-(X72-M72) | Z72: =O72*(1+'1_Assumptions'!$E$13) | AA72: =Z72*(1-('1_Assumptions'!$E$19+$B72)) | AB72: =Z72-AA72-Z72*$B$11+Z72*$B$12 | AC72: =T72*$B$13 | AD72: =Z72*'1_Assumptions'!$E$25 | AE72: =T72+AD72-AC72 | AF72: =Z72*$B$14 | AG72: =V72-AF72 | AH72: =W72+Z72*$B$16-W72/$B$18 | AI72: =Z72*'1_Assumptions'!$B$56/365+AA72*'1_Assumptions'!$B$57/365+Z72*'1_Assumptions'!$B$54-AA72*'1_Assumptions'!$B$58/365-Z72*'1_Assumptions'!$B$55 | AJ72: =AB72*(1-$B$15)+AC72+AF72+IF($B$19=1,Z72*'1_Assumptions'!$E$31,0)-AD72-(AI72-X72) | AK72: =Z72*(1+'1_Assumptions'!$E$14) | AL72: =AK72*(1-('1_Assumptions'!$E$20+$B72)) | AM72: =AK72-AL72-AK72*$B$11+AK72*$B$12 | AN72: =AE72*$B$13 | AO72: =AK72*'1_Assumptions'!$E$26 | AP72: =AE72+AO72-AN72 | AQ72: =AK72*$B$14 | AR72: =AG72-AQ72 | AS72: =AH72+AK72*$B$16-AH72/$B$18 | AT72: =AK72*'1_Assumptions'!$B$56/365+AL72*'1_Assumptions'!$B$57/365+AK72*'1_Assumptions'!$B$54-AL72*'1_Assumptions'!$B$58/365-AK72*'1_Assumptions'!$B$55 | AU72: =AM72*(1-$B$15)+AN72+AQ72+IF($B$19=1,AK72*'1_Assumptions'!$E$32,0)-AO72-(AT72-AI72) | AV72: =AK72*(1+'1_Assumptions'!$E$15) | AW72: =AV72*(1-('1_Assumptions'!$E$21+$B72)) | AX72: =AV72-AW72-AV72*$B$11+AV72*$B$12 | AY72: =AP72*$B$13 | AZ72: =AV72*'1_Assumptions'!$E$27 | BA72: =AP72+AZ72-AY72 | BB72: =AV72*$B$14 | BC72: =AR72-BB72 | BD72: =AS72+AV72*$B$16-AS72/$B$18 | BE72: =AV72*'1_Assumptions'!$B$56/365+AW72*'1_Assumptions'!$B$57/365+AV72*'1_Assumptions'!$B$54-AW72*'1_Assumptions'!$B$58/365-AV72*'1_Assumptions'!$B$55 | BF72: =AX72*(1-$B$15)+AY72+BB72+IF($B$19=1,AV72*'1_Assumptions'!$E$33,0)-AZ72-(BE72-AT72) | BG72: =N72/(1+$B$21)^(1-0.5*$B$23)+Y72/(1+$B$21)^(2-0.5*$B$23)+AJ72/(1+$B$21)^(3-0.5*$B$23)+AU72/(1+$B$21)^(4-0.5*$B$23)+BF72/(1+$B$21)^(5-0.5*$B$23) | BH72: =BE72+BA72+BC72+$B$9+IF($B$17=1,BD72,0) | BI72: =IF($B$32=2,$B$21+$B$33,IF(BH72=0,0,BL72/BH72)) | BJ72: =IF(BI72=0,9,$C72/BI72) | BK72: =IF(OR(BH72<=0,BI72<=$B$21,BJ72>=1,BJ72<0),1,0) | BL72: =AX72*(1-$B$20) | BM72: =IF(BK72=1,BL72,AX72*(1+$C72)*(1-$B$20)*(1-BJ72)) | BN72: =IF(BK72=1,BL72/$B$21,BM72/($B$21-$C72)) | BO72: =BN72/(1+$B$21)^(5-0.5*$B$23) | BP72: =BG72+BO72 | BQ72: =BP72*(1+$B$21)^$B$24-N72*$B$24*(1+$B$21)^($B$24/2) | BR72: =BQ72-$B$25+$B$26+$B$27 | BS72: =IF($B$28=1,$B$30,BR72*$B$29) | BT72: =BR72-BS72 | BU72: =BT72/$B$31
A73: 2-2 | B73: -0.02 | C73: 0.0175 | D73: =$B$5*(1+'1_Assumptions'!$E$11) | E73: =D73*(1-('1_Assumptions'!$E$17+IF('1_Assumptions'!$B$39=1,0,$B73))) | F73: =D73-E73-D73*$B$11+D73*$B$12 | G73: =$B$6*$B$13 | H73: =D73*'1_Assumptions'!$E$23 | I73: =$B$6+H73-G73 | J73: =D73*$B$14 | K73: =$B$7-J73 | L73: =$B$8+D73*$B$16-$B$8/$B$18 | M73: =D73*'1_Assumptions'!$B$56/365+E73*'1_Assumptions'!$B$57/365+D73*'1_Assumptions'!$B$54-E73*'1_Assumptions'!$B$58/365-D73*'1_Assumptions'!$B$55 | N73: =F73*(1-$B$15)+G73+J73+IF($B$19=1,D73*'1_Assumptions'!$E$29,0)-H73-(M73-$B$10) | O73: =D73*(1+'1_Assumptions'!$E$12) | P73: =O73*(1-('1_Assumptions'!$E$18+$B73)) | Q73: =O73-P73-O73*$B$11+O73*$B$12 | R73: =I73*$B$13 | S73: =O73*'1_Assumptions'!$E$24 | T73: =I73+S73-R73 | U73: =O73*$B$14 | V73: =K73-U73 | W73: =L73+O73*$B$16-L73/$B$18 | X73: =O73*'1_Assumptions'!$B$56/365+P73*'1_Assumptions'!$B$57/365+O73*'1_Assumptions'!$B$54-P73*'1_Assumptions'!$B$58/365-O73*'1_Assumptions'!$B$55 | Y73: =Q73*(1-$B$15)+R73+U73+IF($B$19=1,O73*'1_Assumptions'!$E$30,0)-S73-(X73-M73) | Z73: =O73*(1+'1_Assumptions'!$E$13) | AA73: =Z73*(1-('1_Assumptions'!$E$19+$B73)) | AB73: =Z73-AA73-Z73*$B$11+Z73*$B$12 | AC73: =T73*$B$13 | AD73: =Z73*'1_Assumptions'!$E$25 | AE73: =T73+AD73-AC73 | AF73: =Z73*$B$14 | AG73: =V73-AF73 | AH73: =W73+Z73*$B$16-W73/$B$18 | AI73: =Z73*'1_Assumptions'!$B$56/365+AA73*'1_Assumptions'!$B$57/365+Z73*'1_Assumptions'!$B$54-AA73*'1_Assumptions'!$B$58/365-Z73*'1_Assumptions'!$B$55 | AJ73: =AB73*(1-$B$15)+AC73+AF73+IF($B$19=1,Z73*'1_Assumptions'!$E$31,0)-AD73-(AI73-X73) | AK73: =Z73*(1+'1_Assumptions'!$E$14) | AL73: =AK73*(1-('1_Assumptions'!$E$20+$B73)) | AM73: =AK73-AL73-AK73*$B$11+AK73*$B$12 | AN73: =AE73*$B$13 | AO73: =AK73*'1_Assumptions'!$E$26 | AP73: =AE73+AO73-AN73 | AQ73: =AK73*$B$14 | AR73: =AG73-AQ73 | AS73: =AH73+AK73*$B$16-AH73/$B$18 | AT73: =AK73*'1_Assumptions'!$B$56/365+AL73*'1_Assumptions'!$B$57/365+AK73*'1_Assumptions'!$B$54-AL73*'1_Assumptions'!$B$58/365-AK73*'1_Assumptions'!$B$55 | AU73: =AM73*(1-$B$15)+AN73+AQ73+IF($B$19=1,AK73*'1_Assumptions'!$E$32,0)-AO73-(AT73-AI73) | AV73: =AK73*(1+'1_Assumptions'!$E$15) | AW73: =AV73*(1-('1_Assumptions'!$E$21+$B73)) | AX73: =AV73-AW73-AV73*$B$11+AV73*$B$12 | AY73: =AP73*$B$13 | AZ73: =AV73*'1_Assumptions'!$E$27 | BA73: =AP73+AZ73-AY73 | BB73: =AV73*$B$14 | BC73: =AR73-BB73 | BD73: =AS73+AV73*$B$16-AS73/$B$18 | BE73: =AV73*'1_Assumptions'!$B$56/365+AW73*'1_Assumptions'!$B$57/365+AV73*'1_Assumptions'!$B$54-AW73*'1_Assumptions'!$B$58/365-AV73*'1_Assumptions'!$B$55 | BF73: =AX73*(1-$B$15)+AY73+BB73+IF($B$19=1,AV73*'1_Assumptions'!$E$33,0)-AZ73-(BE73-AT73) | BG73: =N73/(1+$B$21)^(1-0.5*$B$23)+Y73/(1+$B$21)^(2-0.5*$B$23)+AJ73/(1+$B$21)^(3-0.5*$B$23)+AU73/(1+$B$21)^(4-0.5*$B$23)+BF73/(1+$B$21)^(5-0.5*$B$23) | BH73: =BE73+BA73+BC73+$B$9+IF($B$17=1,BD73,0) | BI73: =IF($B$32=2,$B$21+$B$33,IF(BH73=0,0,BL73/BH73)) | BJ73: =IF(BI73=0,9,$C73/BI73) | BK73: =IF(OR(BH73<=0,BI73<=$B$21,BJ73>=1,BJ73<0),1,0) | BL73: =AX73*(1-$B$20) | BM73: =IF(BK73=1,BL73,AX73*(1+$C73)*(1-$B$20)*(1-BJ73)) | BN73: =IF(BK73=1,BL73/$B$21,BM73/($B$21-$C73)) | BO73: =BN73/(1+$B$21)^(5-0.5*$B$23) | BP73: =BG73+BO73 | BQ73: =BP73*(1+$B$21)^$B$24-N73*$B$24*(1+$B$21)^($B$24/2) | BR73: =BQ73-$B$25+$B$26+$B$27 | BS73: =IF($B$28=1,$B$30,BR73*$B$29) | BT73: =BR73-BS73 | BU73: =BT73/$B$31
A74: 2-3 | B74: -0.02 | C74: 0.025 | D74: =$B$5*(1+'1_Assumptions'!$E$11) | E74: =D74*(1-('1_Assumptions'!$E$17+IF('1_Assumptions'!$B$39=1,0,$B74))) | F74: =D74-E74-D74*$B$11+D74*$B$12 | G74: =$B$6*$B$13 | H74: =D74*'1_Assumptions'!$E$23 | I74: =$B$6+H74-G74 | J74: =D74*$B$14 | K74: =$B$7-J74 | L74: =$B$8+D74*$B$16-$B$8/$B$18 | M74: =D74*'1_Assumptions'!$B$56/365+E74*'1_Assumptions'!$B$57/365+D74*'1_Assumptions'!$B$54-E74*'1_Assumptions'!$B$58/365-D74*'1_Assumptions'!$B$55 | N74: =F74*(1-$B$15)+G74+J74+IF($B$19=1,D74*'1_Assumptions'!$E$29,0)-H74-(M74-$B$10) | O74: =D74*(1+'1_Assumptions'!$E$12) | P74: =O74*(1-('1_Assumptions'!$E$18+$B74)) | Q74: =O74-P74-O74*$B$11+O74*$B$12 | R74: =I74*$B$13 | S74: =O74*'1_Assumptions'!$E$24 | T74: =I74+S74-R74 | U74: =O74*$B$14 | V74: =K74-U74 | W74: =L74+O74*$B$16-L74/$B$18 | X74: =O74*'1_Assumptions'!$B$56/365+P74*'1_Assumptions'!$B$57/365+O74*'1_Assumptions'!$B$54-P74*'1_Assumptions'!$B$58/365-O74*'1_Assumptions'!$B$55 | Y74: =Q74*(1-$B$15)+R74+U74+IF($B$19=1,O74*'1_Assumptions'!$E$30,0)-S74-(X74-M74) | Z74: =O74*(1+'1_Assumptions'!$E$13) | AA74: =Z74*(1-('1_Assumptions'!$E$19+$B74)) | AB74: =Z74-AA74-Z74*$B$11+Z74*$B$12 | AC74: =T74*$B$13 | AD74: =Z74*'1_Assumptions'!$E$25 | AE74: =T74+AD74-AC74 | AF74: =Z74*$B$14 | AG74: =V74-AF74 | AH74: =W74+Z74*$B$16-W74/$B$18 | AI74: =Z74*'1_Assumptions'!$B$56/365+AA74*'1_Assumptions'!$B$57/365+Z74*'1_Assumptions'!$B$54-AA74*'1_Assumptions'!$B$58/365-Z74*'1_Assumptions'!$B$55 | AJ74: =AB74*(1-$B$15)+AC74+AF74+IF($B$19=1,Z74*'1_Assumptions'!$E$31,0)-AD74-(AI74-X74) | AK74: =Z74*(1+'1_Assumptions'!$E$14) | AL74: =AK74*(1-('1_Assumptions'!$E$20+$B74)) | AM74: =AK74-AL74-AK74*$B$11+AK74*$B$12 | AN74: =AE74*$B$13 | AO74: =AK74*'1_Assumptions'!$E$26 | AP74: =AE74+AO74-AN74 | AQ74: =AK74*$B$14 | AR74: =AG74-AQ74 | AS74: =AH74+AK74*$B$16-AH74/$B$18 | AT74: =AK74*'1_Assumptions'!$B$56/365+AL74*'1_Assumptions'!$B$57/365+AK74*'1_Assumptions'!$B$54-AL74*'1_Assumptions'!$B$58/365-AK74*'1_Assumptions'!$B$55 | AU74: =AM74*(1-$B$15)+AN74+AQ74+IF($B$19=1,AK74*'1_Assumptions'!$E$32,0)-AO74-(AT74-AI74) | AV74: =AK74*(1+'1_Assumptions'!$E$15) | AW74: =AV74*(1-('1_Assumptions'!$E$21+$B74)) | AX74: =AV74-AW74-AV74*$B$11+AV74*$B$12 | AY74: =AP74*$B$13 | AZ74: =AV74*'1_Assumptions'!$E$27 | BA74: =AP74+AZ74-AY74 | BB74: =AV74*$B$14 | BC74: =AR74-BB74 | BD74: =AS74+AV74*$B$16-AS74/$B$18 | BE74: =AV74*'1_Assumptions'!$B$56/365+AW74*'1_Assumptions'!$B$57/365+AV74*'1_Assumptions'!$B$54-AW74*'1_Assumptions'!$B$58/365-AV74*'1_Assumptions'!$B$55 | BF74: =AX74*(1-$B$15)+AY74+BB74+IF($B$19=1,AV74*'1_Assumptions'!$E$33,0)-AZ74-(BE74-AT74) | BG74: =N74/(1+$B$21)^(1-0.5*$B$23)+Y74/(1+$B$21)^(2-0.5*$B$23)+AJ74/(1+$B$21)^(3-0.5*$B$23)+AU74/(1+$B$21)^(4-0.5*$B$23)+BF74/(1+$B$21)^(5-0.5*$B$23) | BH74: =BE74+BA74+BC74+$B$9+IF($B$17=1,BD74,0) | BI74: =IF($B$32=2,$B$21+$B$33,IF(BH74=0,0,BL74/BH74)) | BJ74: =IF(BI74=0,9,$C74/BI74) | BK74: =IF(OR(BH74<=0,BI74<=$B$21,BJ74>=1,BJ74<0),1,0) | BL74: =AX74*(1-$B$20) | BM74: =IF(BK74=1,BL74,AX74*(1+$C74)*(1-$B$20)*(1-BJ74)) | BN74: =IF(BK74=1,BL74/$B$21,BM74/($B$21-$C74)) | BO74: =BN74/(1+$B$21)^(5-0.5*$B$23) | BP74: =BG74+BO74 | BQ74: =BP74*(1+$B$21)^$B$24-N74*$B$24*(1+$B$21)^($B$24/2) | BR74: =BQ74-$B$25+$B$26+$B$27 | BS74: =IF($B$28=1,$B$30,BR74*$B$29) | BT74: =BR74-BS74 | BU74: =BT74/$B$31
A75: 2-4 | B75: -0.02 | C75: 0.0325 | D75: =$B$5*(1+'1_Assumptions'!$E$11) | E75: =D75*(1-('1_Assumptions'!$E$17+IF('1_Assumptions'!$B$39=1,0,$B75))) | F75: =D75-E75-D75*$B$11+D75*$B$12 | G75: =$B$6*$B$13 | H75: =D75*'1_Assumptions'!$E$23 | I75: =$B$6+H75-G75 | J75: =D75*$B$14 | K75: =$B$7-J75 | L75: =$B$8+D75*$B$16-$B$8/$B$18 | M75: =D75*'1_Assumptions'!$B$56/365+E75*'1_Assumptions'!$B$57/365+D75*'1_Assumptions'!$B$54-E75*'1_Assumptions'!$B$58/365-D75*'1_Assumptions'!$B$55 | N75: =F75*(1-$B$15)+G75+J75+IF($B$19=1,D75*'1_Assumptions'!$E$29,0)-H75-(M75-$B$10) | O75: =D75*(1+'1_Assumptions'!$E$12) | P75: =O75*(1-('1_Assumptions'!$E$18+$B75)) | Q75: =O75-P75-O75*$B$11+O75*$B$12 | R75: =I75*$B$13 | S75: =O75*'1_Assumptions'!$E$24 | T75: =I75+S75-R75 | U75: =O75*$B$14 | V75: =K75-U75 | W75: =L75+O75*$B$16-L75/$B$18 | X75: =O75*'1_Assumptions'!$B$56/365+P75*'1_Assumptions'!$B$57/365+O75*'1_Assumptions'!$B$54-P75*'1_Assumptions'!$B$58/365-O75*'1_Assumptions'!$B$55 | Y75: =Q75*(1-$B$15)+R75+U75+IF($B$19=1,O75*'1_Assumptions'!$E$30,0)-S75-(X75-M75) | Z75: =O75*(1+'1_Assumptions'!$E$13) | AA75: =Z75*(1-('1_Assumptions'!$E$19+$B75)) | AB75: =Z75-AA75-Z75*$B$11+Z75*$B$12 | AC75: =T75*$B$13 | AD75: =Z75*'1_Assumptions'!$E$25 | AE75: =T75+AD75-AC75 | AF75: =Z75*$B$14 | AG75: =V75-AF75 | AH75: =W75+Z75*$B$16-W75/$B$18 | AI75: =Z75*'1_Assumptions'!$B$56/365+AA75*'1_Assumptions'!$B$57/365+Z75*'1_Assumptions'!$B$54-AA75*'1_Assumptions'!$B$58/365-Z75*'1_Assumptions'!$B$55 | AJ75: =AB75*(1-$B$15)+AC75+AF75+IF($B$19=1,Z75*'1_Assumptions'!$E$31,0)-AD75-(AI75-X75) | AK75: =Z75*(1+'1_Assumptions'!$E$14) | AL75: =AK75*(1-('1_Assumptions'!$E$20+$B75)) | AM75: =AK75-AL75-AK75*$B$11+AK75*$B$12 | AN75: =AE75*$B$13 | AO75: =AK75*'1_Assumptions'!$E$26 | AP75: =AE75+AO75-AN75 | AQ75: =AK75*$B$14 | AR75: =AG75-AQ75 | AS75: =AH75+AK75*$B$16-AH75/$B$18 | AT75: =AK75*'1_Assumptions'!$B$56/365+AL75*'1_Assumptions'!$B$57/365+AK75*'1_Assumptions'!$B$54-AL75*'1_Assumptions'!$B$58/365-AK75*'1_Assumptions'!$B$55 | AU75: =AM75*(1-$B$15)+AN75+AQ75+IF($B$19=1,AK75*'1_Assumptions'!$E$32,0)-AO75-(AT75-AI75) | AV75: =AK75*(1+'1_Assumptions'!$E$15) | AW75: =AV75*(1-('1_Assumptions'!$E$21+$B75)) | AX75: =AV75-AW75-AV75*$B$11+AV75*$B$12 | AY75: =AP75*$B$13 | AZ75: =AV75*'1_Assumptions'!$E$27 | BA75: =AP75+AZ75-AY75 | BB75: =AV75*$B$14 | BC75: =AR75-BB75 | BD75: =AS75+AV75*$B$16-AS75/$B$18 | BE75: =AV75*'1_Assumptions'!$B$56/365+AW75*'1_Assumptions'!$B$57/365+AV75*'1_Assumptions'!$B$54-AW75*'1_Assumptions'!$B$58/365-AV75*'1_Assumptions'!$B$55 | BF75: =AX75*(1-$B$15)+AY75+BB75+IF($B$19=1,AV75*'1_Assumptions'!$E$33,0)-AZ75-(BE75-AT75) | BG75: =N75/(1+$B$21)^(1-0.5*$B$23)+Y75/(1+$B$21)^(2-0.5*$B$23)+AJ75/(1+$B$21)^(3-0.5*$B$23)+AU75/(1+$B$21)^(4-0.5*$B$23)+BF75/(1+$B$21)^(5-0.5*$B$23) | BH75: =BE75+BA75+BC75+$B$9+IF($B$17=1,BD75,0) | BI75: =IF($B$32=2,$B$21+$B$33,IF(BH75=0,0,BL75/BH75)) | BJ75: =IF(BI75=0,9,$C75/BI75) | BK75: =IF(OR(BH75<=0,BI75<=$B$21,BJ75>=1,BJ75<0),1,0) | BL75: =AX75*(1-$B$20) | BM75: =IF(BK75=1,BL75,AX75*(1+$C75)*(1-$B$20)*(1-BJ75)) | BN75: =IF(BK75=1,BL75/$B$21,BM75/($B$21-$C75)) | BO75: =BN75/(1+$B$21)^(5-0.5*$B$23) | BP75: =BG75+BO75 | BQ75: =BP75*(1+$B$21)^$B$24-N75*$B$24*(1+$B$21)^($B$24/2) | BR75: =BQ75-$B$25+$B$26+$B$27 | BS75: =IF($B$28=1,$B$30,BR75*$B$29) | BT75: =BR75-BS75 | BU75: =BT75/$B$31
A76: 2-5 | B76: -0.02 | C76: 0.04 | D76: =$B$5*(1+'1_Assumptions'!$E$11) | E76: =D76*(1-('1_Assumptions'!$E$17+IF('1_Assumptions'!$B$39=1,0,$B76))) | F76: =D76-E76-D76*$B$11+D76*$B$12 | G76: =$B$6*$B$13 | H76: =D76*'1_Assumptions'!$E$23 | I76: =$B$6+H76-G76 | J76: =D76*$B$14 | K76: =$B$7-J76 | L76: =$B$8+D76*$B$16-$B$8/$B$18 | M76: =D76*'1_Assumptions'!$B$56/365+E76*'1_Assumptions'!$B$57/365+D76*'1_Assumptions'!$B$54-E76*'1_Assumptions'!$B$58/365-D76*'1_Assumptions'!$B$55 | N76: =F76*(1-$B$15)+G76+J76+IF($B$19=1,D76*'1_Assumptions'!$E$29,0)-H76-(M76-$B$10) | O76: =D76*(1+'1_Assumptions'!$E$12) | P76: =O76*(1-('1_Assumptions'!$E$18+$B76)) | Q76: =O76-P76-O76*$B$11+O76*$B$12 | R76: =I76*$B$13 | S76: =O76*'1_Assumptions'!$E$24 | T76: =I76+S76-R76 | U76: =O76*$B$14 | V76: =K76-U76 | W76: =L76+O76*$B$16-L76/$B$18 | X76: =O76*'1_Assumptions'!$B$56/365+P76*'1_Assumptions'!$B$57/365+O76*'1_Assumptions'!$B$54-P76*'1_Assumptions'!$B$58/365-O76*'1_Assumptions'!$B$55 | Y76: =Q76*(1-$B$15)+R76+U76+IF($B$19=1,O76*'1_Assumptions'!$E$30,0)-S76-(X76-M76) | Z76: =O76*(1+'1_Assumptions'!$E$13) | AA76: =Z76*(1-('1_Assumptions'!$E$19+$B76)) | AB76: =Z76-AA76-Z76*$B$11+Z76*$B$12 | AC76: =T76*$B$13 | AD76: =Z76*'1_Assumptions'!$E$25 | AE76: =T76+AD76-AC76 | AF76: =Z76*$B$14 | AG76: =V76-AF76 | AH76: =W76+Z76*$B$16-W76/$B$18 | AI76: =Z76*'1_Assumptions'!$B$56/365+AA76*'1_Assumptions'!$B$57/365+Z76*'1_Assumptions'!$B$54-AA76*'1_Assumptions'!$B$58/365-Z76*'1_Assumptions'!$B$55 | AJ76: =AB76*(1-$B$15)+AC76+AF76+IF($B$19=1,Z76*'1_Assumptions'!$E$31,0)-AD76-(AI76-X76) | AK76: =Z76*(1+'1_Assumptions'!$E$14) | AL76: =AK76*(1-('1_Assumptions'!$E$20+$B76)) | AM76: =AK76-AL76-AK76*$B$11+AK76*$B$12 | AN76: =AE76*$B$13 | AO76: =AK76*'1_Assumptions'!$E$26 | AP76: =AE76+AO76-AN76 | AQ76: =AK76*$B$14 | AR76: =AG76-AQ76 | AS76: =AH76+AK76*$B$16-AH76/$B$18 | AT76: =AK76*'1_Assumptions'!$B$56/365+AL76*'1_Assumptions'!$B$57/365+AK76*'1_Assumptions'!$B$54-AL76*'1_Assumptions'!$B$58/365-AK76*'1_Assumptions'!$B$55 | AU76: =AM76*(1-$B$15)+AN76+AQ76+IF($B$19=1,AK76*'1_Assumptions'!$E$32,0)-AO76-(AT76-AI76) | AV76: =AK76*(1+'1_Assumptions'!$E$15) | AW76: =AV76*(1-('1_Assumptions'!$E$21+$B76)) | AX76: =AV76-AW76-AV76*$B$11+AV76*$B$12 | AY76: =AP76*$B$13 | AZ76: =AV76*'1_Assumptions'!$E$27 | BA76: =AP76+AZ76-AY76 | BB76: =AV76*$B$14 | BC76: =AR76-BB76 | BD76: =AS76+AV76*$B$16-AS76/$B$18 | BE76: =AV76*'1_Assumptions'!$B$56/365+AW76*'1_Assumptions'!$B$57/365+AV76*'1_Assumptions'!$B$54-AW76*'1_Assumptions'!$B$58/365-AV76*'1_Assumptions'!$B$55 | BF76: =AX76*(1-$B$15)+AY76+BB76+IF($B$19=1,AV76*'1_Assumptions'!$E$33,0)-AZ76-(BE76-AT76) | BG76: =N76/(1+$B$21)^(1-0.5*$B$23)+Y76/(1+$B$21)^(2-0.5*$B$23)+AJ76/(1+$B$21)^(3-0.5*$B$23)+AU76/(1+$B$21)^(4-0.5*$B$23)+BF76/(1+$B$21)^(5-0.5*$B$23) | BH76: =BE76+BA76+BC76+$B$9+IF($B$17=1,BD76,0) | BI76: =IF($B$32=2,$B$21+$B$33,IF(BH76=0,0,BL76/BH76)) | BJ76: =IF(BI76=0,9,$C76/BI76) | BK76: =IF(OR(BH76<=0,BI76<=$B$21,BJ76>=1,BJ76<0),1,0) | BL76: =AX76*(1-$B$20) | BM76: =IF(BK76=1,BL76,AX76*(1+$C76)*(1-$B$20)*(1-BJ76)) | BN76: =IF(BK76=1,BL76/$B$21,BM76/($B$21-$C76)) | BO76: =BN76/(1+$B$21)^(5-0.5*$B$23) | BP76: =BG76+BO76 | BQ76: =BP76*(1+$B$21)^$B$24-N76*$B$24*(1+$B$21)^($B$24/2) | BR76: =BQ76-$B$25+$B$26+$B$27 | BS76: =IF($B$28=1,$B$30,BR76*$B$29) | BT76: =BR76-BS76 | BU76: =BT76/$B$31
A77: 3-1 | B77: 0 | C77: 0.01 | D77: =$B$5*(1+'1_Assumptions'!$E$11) | E77: =D77*(1-('1_Assumptions'!$E$17+IF('1_Assumptions'!$B$39=1,0,$B77))) | F77: =D77-E77-D77*$B$11+D77*$B$12 | G77: =$B$6*$B$13 | H77: =D77*'1_Assumptions'!$E$23 | I77: =$B$6+H77-G77 | J77: =D77*$B$14 | K77: =$B$7-J77 | L77: =$B$8+D77*$B$16-$B$8/$B$18 | M77: =D77*'1_Assumptions'!$B$56/365+E77*'1_Assumptions'!$B$57/365+D77*'1_Assumptions'!$B$54-E77*'1_Assumptions'!$B$58/365-D77*'1_Assumptions'!$B$55 | N77: =F77*(1-$B$15)+G77+J77+IF($B$19=1,D77*'1_Assumptions'!$E$29,0)-H77-(M77-$B$10) | O77: =D77*(1+'1_Assumptions'!$E$12) | P77: =O77*(1-('1_Assumptions'!$E$18+$B77)) | Q77: =O77-P77-O77*$B$11+O77*$B$12 | R77: =I77*$B$13 | S77: =O77*'1_Assumptions'!$E$24 | T77: =I77+S77-R77 | U77: =O77*$B$14 | V77: =K77-U77 | W77: =L77+O77*$B$16-L77/$B$18 | X77: =O77*'1_Assumptions'!$B$56/365+P77*'1_Assumptions'!$B$57/365+O77*'1_Assumptions'!$B$54-P77*'1_Assumptions'!$B$58/365-O77*'1_Assumptions'!$B$55 | Y77: =Q77*(1-$B$15)+R77+U77+IF($B$19=1,O77*'1_Assumptions'!$E$30,0)-S77-(X77-M77) | Z77: =O77*(1+'1_Assumptions'!$E$13) | AA77: =Z77*(1-('1_Assumptions'!$E$19+$B77)) | AB77: =Z77-AA77-Z77*$B$11+Z77*$B$12 | AC77: =T77*$B$13 | AD77: =Z77*'1_Assumptions'!$E$25 | AE77: =T77+AD77-AC77 | AF77: =Z77*$B$14 | AG77: =V77-AF77 | AH77: =W77+Z77*$B$16-W77/$B$18 | AI77: =Z77*'1_Assumptions'!$B$56/365+AA77*'1_Assumptions'!$B$57/365+Z77*'1_Assumptions'!$B$54-AA77*'1_Assumptions'!$B$58/365-Z77*'1_Assumptions'!$B$55 | AJ77: =AB77*(1-$B$15)+AC77+AF77+IF($B$19=1,Z77*'1_Assumptions'!$E$31,0)-AD77-(AI77-X77) | AK77: =Z77*(1+'1_Assumptions'!$E$14) | AL77: =AK77*(1-('1_Assumptions'!$E$20+$B77)) | AM77: =AK77-AL77-AK77*$B$11+AK77*$B$12 | AN77: =AE77*$B$13 | AO77: =AK77*'1_Assumptions'!$E$26 | AP77: =AE77+AO77-AN77 | AQ77: =AK77*$B$14 | AR77: =AG77-AQ77 | AS77: =AH77+AK77*$B$16-AH77/$B$18 | AT77: =AK77*'1_Assumptions'!$B$56/365+AL77*'1_Assumptions'!$B$57/365+AK77*'1_Assumptions'!$B$54-AL77*'1_Assumptions'!$B$58/365-AK77*'1_Assumptions'!$B$55 | AU77: =AM77*(1-$B$15)+AN77+AQ77+IF($B$19=1,AK77*'1_Assumptions'!$E$32,0)-AO77-(AT77-AI77) | AV77: =AK77*(1+'1_Assumptions'!$E$15) | AW77: =AV77*(1-('1_Assumptions'!$E$21+$B77)) | AX77: =AV77-AW77-AV77*$B$11+AV77*$B$12 | AY77: =AP77*$B$13 | AZ77: =AV77*'1_Assumptions'!$E$27 | BA77: =AP77+AZ77-AY77 | BB77: =AV77*$B$14 | BC77: =AR77-BB77 | BD77: =AS77+AV77*$B$16-AS77/$B$18 | BE77: =AV77*'1_Assumptions'!$B$56/365+AW77*'1_Assumptions'!$B$57/365+AV77*'1_Assumptions'!$B$54-AW77*'1_Assumptions'!$B$58/365-AV77*'1_Assumptions'!$B$55 | BF77: =AX77*(1-$B$15)+AY77+BB77+IF($B$19=1,AV77*'1_Assumptions'!$E$33,0)-AZ77-(BE77-AT77) | BG77: =N77/(1+$B$21)^(1-0.5*$B$23)+Y77/(1+$B$21)^(2-0.5*$B$23)+AJ77/(1+$B$21)^(3-0.5*$B$23)+AU77/(1+$B$21)^(4-0.5*$B$23)+BF77/(1+$B$21)^(5-0.5*$B$23) | BH77: =BE77+BA77+BC77+$B$9+IF($B$17=1,BD77,0) | BI77: =IF($B$32=2,$B$21+$B$33,IF(BH77=0,0,BL77/BH77)) | BJ77: =IF(BI77=0,9,$C77/BI77) | BK77: =IF(OR(BH77<=0,BI77<=$B$21,BJ77>=1,BJ77<0),1,0) | BL77: =AX77*(1-$B$20) | BM77: =IF(BK77=1,BL77,AX77*(1+$C77)*(1-$B$20)*(1-BJ77)) | BN77: =IF(BK77=1,BL77/$B$21,BM77/($B$21-$C77)) | BO77: =BN77/(1+$B$21)^(5-0.5*$B$23) | BP77: =BG77+BO77 | BQ77: =BP77*(1+$B$21)^$B$24-N77*$B$24*(1+$B$21)^($B$24/2) | BR77: =BQ77-$B$25+$B$26+$B$27 | BS77: =IF($B$28=1,$B$30,BR77*$B$29) | BT77: =BR77-BS77 | BU77: =BT77/$B$31
A78: 3-2 | B78: 0 | C78: 0.0175 | D78: =$B$5*(1+'1_Assumptions'!$E$11) | E78: =D78*(1-('1_Assumptions'!$E$17+IF('1_Assumptions'!$B$39=1,0,$B78))) | F78: =D78-E78-D78*$B$11+D78*$B$12 | G78: =$B$6*$B$13 | H78: =D78*'1_Assumptions'!$E$23 | I78: =$B$6+H78-G78 | J78: =D78*$B$14 | K78: =$B$7-J78 | L78: =$B$8+D78*$B$16-$B$8/$B$18 | M78: =D78*'1_Assumptions'!$B$56/365+E78*'1_Assumptions'!$B$57/365+D78*'1_Assumptions'!$B$54-E78*'1_Assumptions'!$B$58/365-D78*'1_Assumptions'!$B$55 | N78: =F78*(1-$B$15)+G78+J78+IF($B$19=1,D78*'1_Assumptions'!$E$29,0)-H78-(M78-$B$10) | O78: =D78*(1+'1_Assumptions'!$E$12) | P78: =O78*(1-('1_Assumptions'!$E$18+$B78)) | Q78: =O78-P78-O78*$B$11+O78*$B$12 | R78: =I78*$B$13 | S78: =O78*'1_Assumptions'!$E$24 | T78: =I78+S78-R78 | U78: =O78*$B$14 | V78: =K78-U78 | W78: =L78+O78*$B$16-L78/$B$18 | X78: =O78*'1_Assumptions'!$B$56/365+P78*'1_Assumptions'!$B$57/365+O78*'1_Assumptions'!$B$54-P78*'1_Assumptions'!$B$58/365-O78*'1_Assumptions'!$B$55 | Y78: =Q78*(1-$B$15)+R78+U78+IF($B$19=1,O78*'1_Assumptions'!$E$30,0)-S78-(X78-M78) | Z78: =O78*(1+'1_Assumptions'!$E$13) | AA78: =Z78*(1-('1_Assumptions'!$E$19+$B78)) | AB78: =Z78-AA78-Z78*$B$11+Z78*$B$12 | AC78: =T78*$B$13 | AD78: =Z78*'1_Assumptions'!$E$25 | AE78: =T78+AD78-AC78 | AF78: =Z78*$B$14 | AG78: =V78-AF78 | AH78: =W78+Z78*$B$16-W78/$B$18 | AI78: =Z78*'1_Assumptions'!$B$56/365+AA78*'1_Assumptions'!$B$57/365+Z78*'1_Assumptions'!$B$54-AA78*'1_Assumptions'!$B$58/365-Z78*'1_Assumptions'!$B$55 | AJ78: =AB78*(1-$B$15)+AC78+AF78+IF($B$19=1,Z78*'1_Assumptions'!$E$31,0)-AD78-(AI78-X78) | AK78: =Z78*(1+'1_Assumptions'!$E$14) | AL78: =AK78*(1-('1_Assumptions'!$E$20+$B78)) | AM78: =AK78-AL78-AK78*$B$11+AK78*$B$12 | AN78: =AE78*$B$13 | AO78: =AK78*'1_Assumptions'!$E$26 | AP78: =AE78+AO78-AN78 | AQ78: =AK78*$B$14 | AR78: =AG78-AQ78 | AS78: =AH78+AK78*$B$16-AH78/$B$18 | AT78: =AK78*'1_Assumptions'!$B$56/365+AL78*'1_Assumptions'!$B$57/365+AK78*'1_Assumptions'!$B$54-AL78*'1_Assumptions'!$B$58/365-AK78*'1_Assumptions'!$B$55 | AU78: =AM78*(1-$B$15)+AN78+AQ78+IF($B$19=1,AK78*'1_Assumptions'!$E$32,0)-AO78-(AT78-AI78) | AV78: =AK78*(1+'1_Assumptions'!$E$15) | AW78: =AV78*(1-('1_Assumptions'!$E$21+$B78)) | AX78: =AV78-AW78-AV78*$B$11+AV78*$B$12 | AY78: =AP78*$B$13 | AZ78: =AV78*'1_Assumptions'!$E$27 | BA78: =AP78+AZ78-AY78 | BB78: =AV78*$B$14 | BC78: =AR78-BB78 | BD78: =AS78+AV78*$B$16-AS78/$B$18 | BE78: =AV78*'1_Assumptions'!$B$56/365+AW78*'1_Assumptions'!$B$57/365+AV78*'1_Assumptions'!$B$54-AW78*'1_Assumptions'!$B$58/365-AV78*'1_Assumptions'!$B$55 | BF78: =AX78*(1-$B$15)+AY78+BB78+IF($B$19=1,AV78*'1_Assumptions'!$E$33,0)-AZ78-(BE78-AT78) | BG78: =N78/(1+$B$21)^(1-0.5*$B$23)+Y78/(1+$B$21)^(2-0.5*$B$23)+AJ78/(1+$B$21)^(3-0.5*$B$23)+AU78/(1+$B$21)^(4-0.5*$B$23)+BF78/(1+$B$21)^(5-0.5*$B$23) | BH78: =BE78+BA78+BC78+$B$9+IF($B$17=1,BD78,0) | BI78: =IF($B$32=2,$B$21+$B$33,IF(BH78=0,0,BL78/BH78)) | BJ78: =IF(BI78=0,9,$C78/BI78) | BK78: =IF(OR(BH78<=0,BI78<=$B$21,BJ78>=1,BJ78<0),1,0) | BL78: =AX78*(1-$B$20) | BM78: =IF(BK78=1,BL78,AX78*(1+$C78)*(1-$B$20)*(1-BJ78)) | BN78: =IF(BK78=1,BL78/$B$21,BM78/($B$21-$C78)) | BO78: =BN78/(1+$B$21)^(5-0.5*$B$23) | BP78: =BG78+BO78 | BQ78: =BP78*(1+$B$21)^$B$24-N78*$B$24*(1+$B$21)^($B$24/2) | BR78: =BQ78-$B$25+$B$26+$B$27 | BS78: =IF($B$28=1,$B$30,BR78*$B$29) | BT78: =BR78-BS78 | BU78: =BT78/$B$31
... A91: 5-5 | B91: 0.04 | C91: 0.04 | D91: =$B$5*(1+'1_Assumptions'!$E$11) | E91: =D91*(1-('1_Assumptions'!$E$17+IF('1_Assumptions'!$B$39=1,0,$B91))) | F91: =D91-E91-D91*$B$11+D91*$B$12 | G91: =$B$6*$B$13 | H91: =D91*'1_Assumptions'!$E$23 | I91: =$B$6+H91-G91 | J91: =D91*$B$14 | K91: =$B$7-J91 | L91: =$B$8+D91*$B$16-$B$8/$B$18 | M91: =D91*'1_Assumptions'!$B$56/365+E91*'1_Assumptions'!$B$57/365+D91*'1_Assumptions'!$B$54-E91*'1_Assumptions'!$B$58/365-D91*'1_Assumptions'!$B$55 | N91: =F91*(1-$B$15)+G91+J91+IF($B$19=1,D91*'1_Assumptions'!$E$29,0)-H91-(M91-$B$10) | O91: =D91*(1+'1_Assumptions'!$E$12) | P91: =O91*(1-('1_Assumptions'!$E$18+$B91)) | Q91: =O91-P91-O91*$B$11+O91*$B$12 | R91: =I91*$B$13 | S91: =O91*'1_Assumptions'!$E$24 | T91: =I91+S91-R91 | U91: =O91*$B$14 | V91: =K91-U91 | W91: =L91+O91*$B$16-L91/$B$18 | X91: =O91*'1_Assumptions'!$B$56/365+P91*'1_Assumptions'!$B$57/365+O91*'1_Assumptions'!$B$54-P91*'1_Assumptions'!$B$58/365-O91*'1_Assumptions'!$B$55 | Y91: =Q91*(1-$B$15)+R91+U91+IF($B$19=1,O91*'1_Assumptions'!$E$30,0)-S91-(X91-M91) | Z91: =O91*(1+'1_Assumptions'!$E$13) | AA91: =Z91*(1-('1_Assumptions'!$E$19+$B91)) | AB91: =Z91-AA91-Z91*$B$11+Z91*$B$12 | AC91: =T91*$B$13 | AD91: =Z91*'1_Assumptions'!$E$25 | AE91: =T91+AD91-AC91 | AF91: =Z91*$B$14 | AG91: =V91-AF91 | AH91: =W91+Z91*$B$16-W91/$B$18 | AI91: =Z91*'1_Assumptions'!$B$56/365+AA91*'1_Assumptions'!$B$57/365+Z91*'1_Assumptions'!$B$54-AA91*'1_Assumptions'!$B$58/365-Z91*'1_Assumptions'!$B$55 | AJ91: =AB91*(1-$B$15)+AC91+AF91+IF($B$19=1,Z91*'1_Assumptions'!$E$31,0)-AD91-(AI91-X91) | AK91: =Z91*(1+'1_Assumptions'!$E$14) | AL91: =AK91*(1-('1_Assumptions'!$E$20+$B91)) | AM91: =AK91-AL91-AK91*$B$11+AK91*$B$12 | AN91: =AE91*$B$13 | AO91: =AK91*'1_Assumptions'!$E$26 | AP91: =AE91+AO91-AN91 | AQ91: =AK91*$B$14 | AR91: =AG91-AQ91 | AS91: =AH91+AK91*$B$16-AH91/$B$18 | AT91: =AK91*'1_Assumptions'!$B$56/365+AL91*'1_Assumptions'!$B$57/365+AK91*'1_Assumptions'!$B$54-AL91*'1_Assumptions'!$B$58/365-AK91*'1_Assumptions'!$B$55 | AU91: =AM91*(1-$B$15)+AN91+AQ91+IF($B$19=1,AK91*'1_Assumptions'!$E$32,0)-AO91-(AT91-AI91) | AV91: =AK91*(1+'1_Assumptions'!$E$15) | AW91: =AV91*(1-('1_Assumptions'!$E$21+$B91)) | AX91: =AV91-AW91-AV91*$B$11+AV91*$B$12 | AY91: =AP91*$B$13 | AZ91: =AV91*'1_Assumptions'!$E$27 | BA91: =AP91+AZ91-AY91 | BB91: =AV91*$B$14 | BC91: =AR91-BB91 | BD91: =AS91+AV91*$B$16-AS91/$B$18 | BE91: =AV91*'1_Assumptions'!$B$56/365+AW91*'1_Assumptions'!$B$57/365+AV91*'1_Assumptions'!$B$54-AW91*'1_Assumptions'!$B$58/365-AV91*'1_Assumptions'!$B$55 | BF91: =AX91*(1-$B$15)+AY91+BB91+IF($B$19=1,AV91*'1_Assumptions'!$E$33,0)-AZ91-(BE91-AT91) | BG91: =N91/(1+$B$21)^(1-0.5*$B$23)+Y91/(1+$B$21)^(2-0.5*$B$23)+AJ91/(1+$B$21)^(3-0.5*$B$23)+AU91/(1+$B$21)^(4-0.5*$B$23)+BF91/(1+$B$21)^(5-0.5*$B$23) | BH91: =BE91+BA91+BC91+$B$9+IF($B$17=1,BD91,0) | BI91: =IF($B$32=2,$B$21+$B$33,IF(BH91=0,0,BL91/BH91)) | BJ91: =IF(BI91=0,9,$C91/BI91) | BK91: =IF(OR(BH91<=0,BI91<=$B$21,BJ91>=1,BJ91<0),1,0) | BL91: =AX91*(1-$B$20) | BM91: =IF(BK91=1,BL91,AX91*(1+$C91)*(1-$B$20)*(1-BJ91)) | BN91: =IF(BK91=1,BL91/$B$21,BM91/($B$21-$C91)) | BO91: =BN91/(1+$B$21)^(5-0.5*$B$23) | BP91: =BG91+BO91 | BQ91: =BP91*(1+$B$21)^$B$24-N91*$B$24*(1+$B$21)^($B$24/2) | BR91: =BQ91-$B$25+$B$26+$B$27 | BS91: =IF($B$28=1,$B$30,BR91*$B$29) | BT91: =BR91-BS91 | BU91: =BT91/$B$31
A93: 模块 C：营收增速平移 × 毛利率平移
A94: 两个判断项同时动 —— 历史上它们并非独立
A95: 场景 | B95: 营收增速 Δ | C95: 毛利率 Δ | D95: 营收1 | E95: 成本1 | F95: EBIT1 | G95: 折旧1 | H95: 资本开支1 | I95: 期末固资1 | J95: 摊销1 | K95: 商誉无形1 | L95: 研发资本1 | M95: NWC1 | N95: FCFF1 | O95: 营收2 | P95: 成本2 | Q95: EBIT2 | R95: 折旧2 | S95: 资本开支2 | T95: 期末固资2 | U95: 摊销2 | V95: 商誉无形2 | W95: 研发资本2 | X95: NWC2 | Y95: FCFF2 | Z95: 营收3 | AA95: 成本3 | AB95: EBIT3 | AC95: 折旧3 | AD95: 资本开支3 | AE95: 期末固资3 | AF95: 摊销3 | AG95: 商誉无形3 | AH95: 研发资本3 | AI95: NWC3 | AJ95: FCFF3 | AK95: 营收4 | AL95: 成本4 | AM95: EBIT4 | AN95: 折旧4 | AO95: 资本开支4 | AP95: 期末固资4 | AQ95: 摊销4 | AR95: 商誉无形4 | AS95: 研发资本4 | AT95: NWC4 | AU95: FCFF4 | AV95: 营收5 | AW95: 成本5 | AX95: EBIT5 | AY95: 折旧5 | AZ95: 资本开支5 | BA95: 期末固资5 | BB95: 摊销5 | BC95: 商誉无形5 | BD95: 研发资本5 | BE95: NWC5 | BF95: FCFF5 | BG95: PV明确期 | BH95: 终值IC | BI95: 终值ROIC | BJ95: 再投资率 | BK95: 降级 | BL95: 终值NOPAT | BM95: 终值FCFF | BN95: TV | BO95: PV(TV) | BP95: EV0 | BQ95: EV | BR95: 全体权益 | BS95: 少数股东 | BT95: 归母权益 | BU95: 每股
A96: 1-1 | B96: -0.06 | C96: -0.04 | D96: =$B$5*(1+('1_Assumptions'!$E$11+IF('1_Assumptions'!$B$39=1,0,$B96))) | E96: =D96*(1-('1_Assumptions'!$E$17+IF('1_Assumptions'!$B$39=1,0,$C96))) | F96: =D96-E96-D96*$B$11+D96*$B$12 | G96: =$B$6*$B$13 | H96: =D96*'1_Assumptions'!$E$23 | I96: =$B$6+H96-G96 | J96: =D96*$B$14 | K96: =$B$7-J96 | L96: =$B$8+D96*$B$16-$B$8/$B$18 | M96: =D96*'1_Assumptions'!$B$56/365+E96*'1_Assumptions'!$B$57/365+D96*'1_Assumptions'!$B$54-E96*'1_Assumptions'!$B$58/365-D96*'1_Assumptions'!$B$55 | N96: =F96*(1-$B$15)+G96+J96+IF($B$19=1,D96*'1_Assumptions'!$E$29,0)-H96-(M96-$B$10) | O96: =D96*(1+('1_Assumptions'!$E$12+$B96)) | P96: =O96*(1-('1_Assumptions'!$E$18+$C96)) | Q96: =O96-P96-O96*$B$11+O96*$B$12 | R96: =I96*$B$13 | S96: =O96*'1_Assumptions'!$E$24 | T96: =I96+S96-R96 | U96: =O96*$B$14 | V96: =K96-U96 | W96: =L96+O96*$B$16-L96/$B$18 | X96: =O96*'1_Assumptions'!$B$56/365+P96*'1_Assumptions'!$B$57/365+O96*'1_Assumptions'!$B$54-P96*'1_Assumptions'!$B$58/365-O96*'1_Assumptions'!$B$55 | Y96: =Q96*(1-$B$15)+R96+U96+IF($B$19=1,O96*'1_Assumptions'!$E$30,0)-S96-(X96-M96) | Z96: =O96*(1+('1_Assumptions'!$E$13+$B96)) | AA96: =Z96*(1-('1_Assumptions'!$E$19+$C96)) | AB96: =Z96-AA96-Z96*$B$11+Z96*$B$12 | AC96: =T96*$B$13 | AD96: =Z96*'1_Assumptions'!$E$25 | AE96: =T96+AD96-AC96 | AF96: =Z96*$B$14 | AG96: =V96-AF96 | AH96: =W96+Z96*$B$16-W96/$B$18 | AI96: =Z96*'1_Assumptions'!$B$56/365+AA96*'1_Assumptions'!$B$57/365+Z96*'1_Assumptions'!$B$54-AA96*'1_Assumptions'!$B$58/365-Z96*'1_Assumptions'!$B$55 | AJ96: =AB96*(1-$B$15)+AC96+AF96+IF($B$19=1,Z96*'1_Assumptions'!$E$31,0)-AD96-(AI96-X96) | AK96: =Z96*(1+('1_Assumptions'!$E$14+$B96)) | AL96: =AK96*(1-('1_Assumptions'!$E$20+$C96)) | AM96: =AK96-AL96-AK96*$B$11+AK96*$B$12 | AN96: =AE96*$B$13 | AO96: =AK96*'1_Assumptions'!$E$26 | AP96: =AE96+AO96-AN96 | AQ96: =AK96*$B$14 | AR96: =AG96-AQ96 | AS96: =AH96+AK96*$B$16-AH96/$B$18 | AT96: =AK96*'1_Assumptions'!$B$56/365+AL96*'1_Assumptions'!$B$57/365+AK96*'1_Assumptions'!$B$54-AL96*'1_Assumptions'!$B$58/365-AK96*'1_Assumptions'!$B$55 | AU96: =AM96*(1-$B$15)+AN96+AQ96+IF($B$19=1,AK96*'1_Assumptions'!$E$32,0)-AO96-(AT96-AI96) | AV96: =AK96*(1+('1_Assumptions'!$E$15+$B96)) | AW96: =AV96*(1-('1_Assumptions'!$E$21+$C96)) | AX96: =AV96-AW96-AV96*$B$11+AV96*$B$12 | AY96: =AP96*$B$13 | AZ96: =AV96*'1_Assumptions'!$E$27 | BA96: =AP96+AZ96-AY96 | BB96: =AV96*$B$14 | BC96: =AR96-BB96 | BD96: =AS96+AV96*$B$16-AS96/$B$18 | BE96: =AV96*'1_Assumptions'!$B$56/365+AW96*'1_Assumptions'!$B$57/365+AV96*'1_Assumptions'!$B$54-AW96*'1_Assumptions'!$B$58/365-AV96*'1_Assumptions'!$B$55 | BF96: =AX96*(1-$B$15)+AY96+BB96+IF($B$19=1,AV96*'1_Assumptions'!$E$33,0)-AZ96-(BE96-AT96) | BG96: =N96/(1+$B$21)^(1-0.5*$B$23)+Y96/(1+$B$21)^(2-0.5*$B$23)+AJ96/(1+$B$21)^(3-0.5*$B$23)+AU96/(1+$B$21)^(4-0.5*$B$23)+BF96/(1+$B$21)^(5-0.5*$B$23) | BH96: =BE96+BA96+BC96+$B$9+IF($B$17=1,BD96,0) | BI96: =IF($B$32=2,$B$21+$B$33,IF(BH96=0,0,BL96/BH96)) | BJ96: =IF(BI96=0,9,$B$22/BI96) | BK96: =IF(OR(BH96<=0,BI96<=$B$21,BJ96>=1,BJ96<0),1,0) | BL96: =AX96*(1-$B$20) | BM96: =IF(BK96=1,BL96,AX96*(1+$B$22)*(1-$B$20)*(1-BJ96)) | BN96: =IF(BK96=1,BL96/$B$21,BM96/($B$21-$B$22)) | BO96: =BN96/(1+$B$21)^(5-0.5*$B$23) | BP96: =BG96+BO96 | BQ96: =BP96*(1+$B$21)^$B$24-N96*$B$24*(1+$B$21)^($B$24/2) | BR96: =BQ96-$B$25+$B$26+$B$27 | BS96: =IF($B$28=1,$B$30,BR96*$B$29) | BT96: =BR96-BS96 | BU96: =BT96/$B$31
A97: 1-2 | B97: -0.06 | C97: -0.02 | D97: =$B$5*(1+('1_Assumptions'!$E$11+IF('1_Assumptions'!$B$39=1,0,$B97))) | E97: =D97*(1-('1_Assumptions'!$E$17+IF('1_Assumptions'!$B$39=1,0,$C97))) | F97: =D97-E97-D97*$B$11+D97*$B$12 | G97: =$B$6*$B$13 | H97: =D97*'1_Assumptions'!$E$23 | I97: =$B$6+H97-G97 | J97: =D97*$B$14 | K97: =$B$7-J97 | L97: =$B$8+D97*$B$16-$B$8/$B$18 | M97: =D97*'1_Assumptions'!$B$56/365+E97*'1_Assumptions'!$B$57/365+D97*'1_Assumptions'!$B$54-E97*'1_Assumptions'!$B$58/365-D97*'1_Assumptions'!$B$55 | N97: =F97*(1-$B$15)+G97+J97+IF($B$19=1,D97*'1_Assumptions'!$E$29,0)-H97-(M97-$B$10) | O97: =D97*(1+('1_Assumptions'!$E$12+$B97)) | P97: =O97*(1-('1_Assumptions'!$E$18+$C97)) | Q97: =O97-P97-O97*$B$11+O97*$B$12 | R97: =I97*$B$13 | S97: =O97*'1_Assumptions'!$E$24 | T97: =I97+S97-R97 | U97: =O97*$B$14 | V97: =K97-U97 | W97: =L97+O97*$B$16-L97/$B$18 | X97: =O97*'1_Assumptions'!$B$56/365+P97*'1_Assumptions'!$B$57/365+O97*'1_Assumptions'!$B$54-P97*'1_Assumptions'!$B$58/365-O97*'1_Assumptions'!$B$55 | Y97: =Q97*(1-$B$15)+R97+U97+IF($B$19=1,O97*'1_Assumptions'!$E$30,0)-S97-(X97-M97) | Z97: =O97*(1+('1_Assumptions'!$E$13+$B97)) | AA97: =Z97*(1-('1_Assumptions'!$E$19+$C97)) | AB97: =Z97-AA97-Z97*$B$11+Z97*$B$12 | AC97: =T97*$B$13 | AD97: =Z97*'1_Assumptions'!$E$25 | AE97: =T97+AD97-AC97 | AF97: =Z97*$B$14 | AG97: =V97-AF97 | AH97: =W97+Z97*$B$16-W97/$B$18 | AI97: =Z97*'1_Assumptions'!$B$56/365+AA97*'1_Assumptions'!$B$57/365+Z97*'1_Assumptions'!$B$54-AA97*'1_Assumptions'!$B$58/365-Z97*'1_Assumptions'!$B$55 | AJ97: =AB97*(1-$B$15)+AC97+AF97+IF($B$19=1,Z97*'1_Assumptions'!$E$31,0)-AD97-(AI97-X97) | AK97: =Z97*(1+('1_Assumptions'!$E$14+$B97)) | AL97: =AK97*(1-('1_Assumptions'!$E$20+$C97)) | AM97: =AK97-AL97-AK97*$B$11+AK97*$B$12 | AN97: =AE97*$B$13 | AO97: =AK97*'1_Assumptions'!$E$26 | AP97: =AE97+AO97-AN97 | AQ97: =AK97*$B$14 | AR97: =AG97-AQ97 | AS97: =AH97+AK97*$B$16-AH97/$B$18 | AT97: =AK97*'1_Assumptions'!$B$56/365+AL97*'1_Assumptions'!$B$57/365+AK97*'1_Assumptions'!$B$54-AL97*'1_Assumptions'!$B$58/365-AK97*'1_Assumptions'!$B$55 | AU97: =AM97*(1-$B$15)+AN97+AQ97+IF($B$19=1,AK97*'1_Assumptions'!$E$32,0)-AO97-(AT97-AI97) | AV97: =AK97*(1+('1_Assumptions'!$E$15+$B97)) | AW97: =AV97*(1-('1_Assumptions'!$E$21+$C97)) | AX97: =AV97-AW97-AV97*$B$11+AV97*$B$12 | AY97: =AP97*$B$13 | AZ97: =AV97*'1_Assumptions'!$E$27 | BA97: =AP97+AZ97-AY97 | BB97: =AV97*$B$14 | BC97: =AR97-BB97 | BD97: =AS97+AV97*$B$16-AS97/$B$18 | BE97: =AV97*'1_Assumptions'!$B$56/365+AW97*'1_Assumptions'!$B$57/365+AV97*'1_Assumptions'!$B$54-AW97*'1_Assumptions'!$B$58/365-AV97*'1_Assumptions'!$B$55 | BF97: =AX97*(1-$B$15)+AY97+BB97+IF($B$19=1,AV97*'1_Assumptions'!$E$33,0)-AZ97-(BE97-AT97) | BG97: =N97/(1+$B$21)^(1-0.5*$B$23)+Y97/(1+$B$21)^(2-0.5*$B$23)+AJ97/(1+$B$21)^(3-0.5*$B$23)+AU97/(1+$B$21)^(4-0.5*$B$23)+BF97/(1+$B$21)^(5-0.5*$B$23) | BH97: =BE97+BA97+BC97+$B$9+IF($B$17=1,BD97,0) | BI97: =IF($B$32=2,$B$21+$B$33,IF(BH97=0,0,BL97/BH97)) | BJ97: =IF(BI97=0,9,$B$22/BI97) | BK97: =IF(OR(BH97<=0,BI97<=$B$21,BJ97>=1,BJ97<0),1,0) | BL97: =AX97*(1-$B$20) | BM97: =IF(BK97=1,BL97,AX97*(1+$B$22)*(1-$B$20)*(1-BJ97)) | BN97: =IF(BK97=1,BL97/$B$21,BM97/($B$21-$B$22)) | BO97: =BN97/(1+$B$21)^(5-0.5*$B$23) | BP97: =BG97+BO97 | BQ97: =BP97*(1+$B$21)^$B$24-N97*$B$24*(1+$B$21)^($B$24/2) | BR97: =BQ97-$B$25+$B$26+$B$27 | BS97: =IF($B$28=1,$B$30,BR97*$B$29) | BT97: =BR97-BS97 | BU97: =BT97/$B$31
A98: 1-3 | B98: -0.06 | C98: 0 | D98: =$B$5*(1+('1_Assumptions'!$E$11+IF('1_Assumptions'!$B$39=1,0,$B98))) | E98: =D98*(1-('1_Assumptions'!$E$17+IF('1_Assumptions'!$B$39=1,0,$C98))) | F98: =D98-E98-D98*$B$11+D98*$B$12 | G98: =$B$6*$B$13 | H98: =D98*'1_Assumptions'!$E$23 | I98: =$B$6+H98-G98 | J98: =D98*$B$14 | K98: =$B$7-J98 | L98: =$B$8+D98*$B$16-$B$8/$B$18 | M98: =D98*'1_Assumptions'!$B$56/365+E98*'1_Assumptions'!$B$57/365+D98*'1_Assumptions'!$B$54-E98*'1_Assumptions'!$B$58/365-D98*'1_Assumptions'!$B$55 | N98: =F98*(1-$B$15)+G98+J98+IF($B$19=1,D98*'1_Assumptions'!$E$29,0)-H98-(M98-$B$10) | O98: =D98*(1+('1_Assumptions'!$E$12+$B98)) | P98: =O98*(1-('1_Assumptions'!$E$18+$C98)) | Q98: =O98-P98-O98*$B$11+O98*$B$12 | R98: =I98*$B$13 | S98: =O98*'1_Assumptions'!$E$24 | T98: =I98+S98-R98 | U98: =O98*$B$14 | V98: =K98-U98 | W98: =L98+O98*$B$16-L98/$B$18 | X98: =O98*'1_Assumptions'!$B$56/365+P98*'1_Assumptions'!$B$57/365+O98*'1_Assumptions'!$B$54-P98*'1_Assumptions'!$B$58/365-O98*'1_Assumptions'!$B$55 | Y98: =Q98*(1-$B$15)+R98+U98+IF($B$19=1,O98*'1_Assumptions'!$E$30,0)-S98-(X98-M98) | Z98: =O98*(1+('1_Assumptions'!$E$13+$B98)) | AA98: =Z98*(1-('1_Assumptions'!$E$19+$C98)) | AB98: =Z98-AA98-Z98*$B$11+Z98*$B$12 | AC98: =T98*$B$13 | AD98: =Z98*'1_Assumptions'!$E$25 | AE98: =T98+AD98-AC98 | AF98: =Z98*$B$14 | AG98: =V98-AF98 | AH98: =W98+Z98*$B$16-W98/$B$18 | AI98: =Z98*'1_Assumptions'!$B$56/365+AA98*'1_Assumptions'!$B$57/365+Z98*'1_Assumptions'!$B$54-AA98*'1_Assumptions'!$B$58/365-Z98*'1_Assumptions'!$B$55 | AJ98: =AB98*(1-$B$15)+AC98+AF98+IF($B$19=1,Z98*'1_Assumptions'!$E$31,0)-AD98-(AI98-X98) | AK98: =Z98*(1+('1_Assumptions'!$E$14+$B98)) | AL98: =AK98*(1-('1_Assumptions'!$E$20+$C98)) | AM98: =AK98-AL98-AK98*$B$11+AK98*$B$12 | AN98: =AE98*$B$13 | AO98: =AK98*'1_Assumptions'!$E$26 | AP98: =AE98+AO98-AN98 | AQ98: =AK98*$B$14 | AR98: =AG98-AQ98 | AS98: =AH98+AK98*$B$16-AH98/$B$18 | AT98: =AK98*'1_Assumptions'!$B$56/365+AL98*'1_Assumptions'!$B$57/365+AK98*'1_Assumptions'!$B$54-AL98*'1_Assumptions'!$B$58/365-AK98*'1_Assumptions'!$B$55 | AU98: =AM98*(1-$B$15)+AN98+AQ98+IF($B$19=1,AK98*'1_Assumptions'!$E$32,0)-AO98-(AT98-AI98) | AV98: =AK98*(1+('1_Assumptions'!$E$15+$B98)) | AW98: =AV98*(1-('1_Assumptions'!$E$21+$C98)) | AX98: =AV98-AW98-AV98*$B$11+AV98*$B$12 | AY98: =AP98*$B$13 | AZ98: =AV98*'1_Assumptions'!$E$27 | BA98: =AP98+AZ98-AY98 | BB98: =AV98*$B$14 | BC98: =AR98-BB98 | BD98: =AS98+AV98*$B$16-AS98/$B$18 | BE98: =AV98*'1_Assumptions'!$B$56/365+AW98*'1_Assumptions'!$B$57/365+AV98*'1_Assumptions'!$B$54-AW98*'1_Assumptions'!$B$58/365-AV98*'1_Assumptions'!$B$55 | BF98: =AX98*(1-$B$15)+AY98+BB98+IF($B$19=1,AV98*'1_Assumptions'!$E$33,0)-AZ98-(BE98-AT98) | BG98: =N98/(1+$B$21)^(1-0.5*$B$23)+Y98/(1+$B$21)^(2-0.5*$B$23)+AJ98/(1+$B$21)^(3-0.5*$B$23)+AU98/(1+$B$21)^(4-0.5*$B$23)+BF98/(1+$B$21)^(5-0.5*$B$23) | BH98: =BE98+BA98+BC98+$B$9+IF($B$17=1,BD98,0) | BI98: =IF($B$32=2,$B$21+$B$33,IF(BH98=0,0,BL98/BH98)) | BJ98: =IF(BI98=0,9,$B$22/BI98) | BK98: =IF(OR(BH98<=0,BI98<=$B$21,BJ98>=1,BJ98<0),1,0) | BL98: =AX98*(1-$B$20) | BM98: =IF(BK98=1,BL98,AX98*(1+$B$22)*(1-$B$20)*(1-BJ98)) | BN98: =IF(BK98=1,BL98/$B$21,BM98/($B$21-$B$22)) | BO98: =BN98/(1+$B$21)^(5-0.5*$B$23) | BP98: =BG98+BO98 | BQ98: =BP98*(1+$B$21)^$B$24-N98*$B$24*(1+$B$21)^($B$24/2) | BR98: =BQ98-$B$25+$B$26+$B$27 | BS98: =IF($B$28=1,$B$30,BR98*$B$29) | BT98: =BR98-BS98 | BU98: =BT98/$B$31
A99: 1-4 | B99: -0.06 | C99: 0.02 | D99: =$B$5*(1+('1_Assumptions'!$E$11+IF('1_Assumptions'!$B$39=1,0,$B99))) | E99: =D99*(1-('1_Assumptions'!$E$17+IF('1_Assumptions'!$B$39=1,0,$C99))) | F99: =D99-E99-D99*$B$11+D99*$B$12 | G99: =$B$6*$B$13 | H99: =D99*'1_Assumptions'!$E$23 | I99: =$B$6+H99-G99 | J99: =D99*$B$14 | K99: =$B$7-J99 | L99: =$B$8+D99*$B$16-$B$8/$B$18 | M99: =D99*'1_Assumptions'!$B$56/365+E99*'1_Assumptions'!$B$57/365+D99*'1_Assumptions'!$B$54-E99*'1_Assumptions'!$B$58/365-D99*'1_Assumptions'!$B$55 | N99: =F99*(1-$B$15)+G99+J99+IF($B$19=1,D99*'1_Assumptions'!$E$29,0)-H99-(M99-$B$10) | O99: =D99*(1+('1_Assumptions'!$E$12+$B99)) | P99: =O99*(1-('1_Assumptions'!$E$18+$C99)) | Q99: =O99-P99-O99*$B$11+O99*$B$12 | R99: =I99*$B$13 | S99: =O99*'1_Assumptions'!$E$24 | T99: =I99+S99-R99 | U99: =O99*$B$14 | V99: =K99-U99 | W99: =L99+O99*$B$16-L99/$B$18 | X99: =O99*'1_Assumptions'!$B$56/365+P99*'1_Assumptions'!$B$57/365+O99*'1_Assumptions'!$B$54-P99*'1_Assumptions'!$B$58/365-O99*'1_Assumptions'!$B$55 | Y99: =Q99*(1-$B$15)+R99+U99+IF($B$19=1,O99*'1_Assumptions'!$E$30,0)-S99-(X99-M99) | Z99: =O99*(1+('1_Assumptions'!$E$13+$B99)) | AA99: =Z99*(1-('1_Assumptions'!$E$19+$C99)) | AB99: =Z99-AA99-Z99*$B$11+Z99*$B$12 | AC99: =T99*$B$13 | AD99: =Z99*'1_Assumptions'!$E$25 | AE99: =T99+AD99-AC99 | AF99: =Z99*$B$14 | AG99: =V99-AF99 | AH99: =W99+Z99*$B$16-W99/$B$18 | AI99: =Z99*'1_Assumptions'!$B$56/365+AA99*'1_Assumptions'!$B$57/365+Z99*'1_Assumptions'!$B$54-AA99*'1_Assumptions'!$B$58/365-Z99*'1_Assumptions'!$B$55 | AJ99: =AB99*(1-$B$15)+AC99+AF99+IF($B$19=1,Z99*'1_Assumptions'!$E$31,0)-AD99-(AI99-X99) | AK99: =Z99*(1+('1_Assumptions'!$E$14+$B99)) | AL99: =AK99*(1-('1_Assumptions'!$E$20+$C99)) | AM99: =AK99-AL99-AK99*$B$11+AK99*$B$12 | AN99: =AE99*$B$13 | AO99: =AK99*'1_Assumptions'!$E$26 | AP99: =AE99+AO99-AN99 | AQ99: =AK99*$B$14 | AR99: =AG99-AQ99 | AS99: =AH99+AK99*$B$16-AH99/$B$18 | AT99: =AK99*'1_Assumptions'!$B$56/365+AL99*'1_Assumptions'!$B$57/365+AK99*'1_Assumptions'!$B$54-AL99*'1_Assumptions'!$B$58/365-AK99*'1_Assumptions'!$B$55 | AU99: =AM99*(1-$B$15)+AN99+AQ99+IF($B$19=1,AK99*'1_Assumptions'!$E$32,0)-AO99-(AT99-AI99) | AV99: =AK99*(1+('1_Assumptions'!$E$15+$B99)) | AW99: =AV99*(1-('1_Assumptions'!$E$21+$C99)) | AX99: =AV99-AW99-AV99*$B$11+AV99*$B$12 | AY99: =AP99*$B$13 | AZ99: =AV99*'1_Assumptions'!$E$27 | BA99: =AP99+AZ99-AY99 | BB99: =AV99*$B$14 | BC99: =AR99-BB99 | BD99: =AS99+AV99*$B$16-AS99/$B$18 | BE99: =AV99*'1_Assumptions'!$B$56/365+AW99*'1_Assumptions'!$B$57/365+AV99*'1_Assumptions'!$B$54-AW99*'1_Assumptions'!$B$58/365-AV99*'1_Assumptions'!$B$55 | BF99: =AX99*(1-$B$15)+AY99+BB99+IF($B$19=1,AV99*'1_Assumptions'!$E$33,0)-AZ99-(BE99-AT99) | BG99: =N99/(1+$B$21)^(1-0.5*$B$23)+Y99/(1+$B$21)^(2-0.5*$B$23)+AJ99/(1+$B$21)^(3-0.5*$B$23)+AU99/(1+$B$21)^(4-0.5*$B$23)+BF99/(1+$B$21)^(5-0.5*$B$23) | BH99: =BE99+BA99+BC99+$B$9+IF($B$17=1,BD99,0) | BI99: =IF($B$32=2,$B$21+$B$33,IF(BH99=0,0,BL99/BH99)) | BJ99: =IF(BI99=0,9,$B$22/BI99) | BK99: =IF(OR(BH99<=0,BI99<=$B$21,BJ99>=1,BJ99<0),1,0) | BL99: =AX99*(1-$B$20) | BM99: =IF(BK99=1,BL99,AX99*(1+$B$22)*(1-$B$20)*(1-BJ99)) | BN99: =IF(BK99=1,BL99/$B$21,BM99/($B$21-$B$22)) | BO99: =BN99/(1+$B$21)^(5-0.5*$B$23) | BP99: =BG99+BO99 | BQ99: =BP99*(1+$B$21)^$B$24-N99*$B$24*(1+$B$21)^($B$24/2) | BR99: =BQ99-$B$25+$B$26+$B$27 | BS99: =IF($B$28=1,$B$30,BR99*$B$29) | BT99: =BR99-BS99 | BU99: =BT99/$B$31
A100: 1-5 | B100: -0.06 | C100: 0.04 | D100: =$B$5*(1+('1_Assumptions'!$E$11+IF('1_Assumptions'!$B$39=1,0,$B100))) | E100: =D100*(1-('1_Assumptions'!$E$17+IF('1_Assumptions'!$B$39=1,0,$C100))) | F100: =D100-E100-D100*$B$11+D100*$B$12 | G100: =$B$6*$B$13 | H100: =D100*'1_Assumptions'!$E$23 | I100: =$B$6+H100-G100 | J100: =D100*$B$14 | K100: =$B$7-J100 | L100: =$B$8+D100*$B$16-$B$8/$B$18 | M100: =D100*'1_Assumptions'!$B$56/365+E100*'1_Assumptions'!$B$57/365+D100*'1_Assumptions'!$B$54-E100*'1_Assumptions'!$B$58/365-D100*'1_Assumptions'!$B$55 | N100: =F100*(1-$B$15)+G100+J100+IF($B$19=1,D100*'1_Assumptions'!$E$29,0)-H100-(M100-$B$10) | O100: =D100*(1+('1_Assumptions'!$E$12+$B100)) | P100: =O100*(1-('1_Assumptions'!$E$18+$C100)) | Q100: =O100-P100-O100*$B$11+O100*$B$12 | R100: =I100*$B$13 | S100: =O100*'1_Assumptions'!$E$24 | T100: =I100+S100-R100 | U100: =O100*$B$14 | V100: =K100-U100 | W100: =L100+O100*$B$16-L100/$B$18 | X100: =O100*'1_Assumptions'!$B$56/365+P100*'1_Assumptions'!$B$57/365+O100*'1_Assumptions'!$B$54-P100*'1_Assumptions'!$B$58/365-O100*'1_Assumptions'!$B$55 | Y100: =Q100*(1-$B$15)+R100+U100+IF($B$19=1,O100*'1_Assumptions'!$E$30,0)-S100-(X100-M100) | Z100: =O100*(1+('1_Assumptions'!$E$13+$B100)) | AA100: =Z100*(1-('1_Assumptions'!$E$19+$C100)) | AB100: =Z100-AA100-Z100*$B$11+Z100*$B$12 | AC100: =T100*$B$13 | AD100: =Z100*'1_Assumptions'!$E$25 | AE100: =T100+AD100-AC100 | AF100: =Z100*$B$14 | AG100: =V100-AF100 | AH100: =W100+Z100*$B$16-W100/$B$18 | AI100: =Z100*'1_Assumptions'!$B$56/365+AA100*'1_Assumptions'!$B$57/365+Z100*'1_Assumptions'!$B$54-AA100*'1_Assumptions'!$B$58/365-Z100*'1_Assumptions'!$B$55 | AJ100: =AB100*(1-$B$15)+AC100+AF100+IF($B$19=1,Z100*'1_Assumptions'!$E$31,0)-AD100-(AI100-X100) | AK100: =Z100*(1+('1_Assumptions'!$E$14+$B100)) | AL100: =AK100*(1-('1_Assumptions'!$E$20+$C100)) | AM100: =AK100-AL100-AK100*$B$11+AK100*$B$12 | AN100: =AE100*$B$13 | AO100: =AK100*'1_Assumptions'!$E$26 | AP100: =AE100+AO100-AN100 | AQ100: =AK100*$B$14 | AR100: =AG100-AQ100 | AS100: =AH100+AK100*$B$16-AH100/$B$18 | AT100: =AK100*'1_Assumptions'!$B$56/365+AL100*'1_Assumptions'!$B$57/365+AK100*'1_Assumptions'!$B$54-AL100*'1_Assumptions'!$B$58/365-AK100*'1_Assumptions'!$B$55 | AU100: =AM100*(1-$B$15)+AN100+AQ100+IF($B$19=1,AK100*'1_Assumptions'!$E$32,0)-AO100-(AT100-AI100) | AV100: =AK100*(1+('1_Assumptions'!$E$15+$B100)) | AW100: =AV100*(1-('1_Assumptions'!$E$21+$C100)) | AX100: =AV100-AW100-AV100*$B$11+AV100*$B$12 | AY100: =AP100*$B$13 | AZ100: =AV100*'1_Assumptions'!$E$27 | BA100: =AP100+AZ100-AY100 | BB100: =AV100*$B$14 | BC100: =AR100-BB100 | BD100: =AS100+AV100*$B$16-AS100/$B$18 | BE100: =AV100*'1_Assumptions'!$B$56/365+AW100*'1_Assumptions'!$B$57/365+AV100*'1_Assumptions'!$B$54-AW100*'1_Assumptions'!$B$58/365-AV100*'1_Assumptions'!$B$55 | BF100: =AX100*(1-$B$15)+AY100+BB100+IF($B$19=1,AV100*'1_Assumptions'!$E$33,0)-AZ100-(BE100-AT100) | BG100: =N100/(1+$B$21)^(1-0.5*$B$23)+Y100/(1+$B$21)^(2-0.5*$B$23)+AJ100/(1+$B$21)^(3-0.5*$B$23)+AU100/(1+$B$21)^(4-0.5*$B$23)+BF100/(1+$B$21)^(5-0.5*$B$23) | BH100: =BE100+BA100+BC100+$B$9+IF($B$17=1,BD100,0) | BI100: =IF($B$32=2,$B$21+$B$33,IF(BH100=0,0,BL100/BH100)) | BJ100: =IF(BI100=0,9,$B$22/BI100) | BK100: =IF(OR(BH100<=0,BI100<=$B$21,BJ100>=1,BJ100<0),1,0) | BL100: =AX100*(1-$B$20) | BM100: =IF(BK100=1,BL100,AX100*(1+$B$22)*(1-$B$20)*(1-BJ100)) | BN100: =IF(BK100=1,BL100/$B$21,BM100/($B$21-$B$22)) | BO100: =BN100/(1+$B$21)^(5-0.5*$B$23) | BP100: =BG100+BO100 | BQ100: =BP100*(1+$B$21)^$B$24-N100*$B$24*(1+$B$21)^($B$24/2) | BR100: =BQ100-$B$25+$B$26+$B$27 | BS100: =IF($B$28=1,$B$30,BR100*$B$29) | BT100: =BR100-BS100 | BU100: =BT100/$B$31
A101: 2-1 | B101: -0.03 | C101: -0.04 | D101: =$B$5*(1+('1_Assumptions'!$E$11+IF('1_Assumptions'!$B$39=1,0,$B101))) | E101: =D101*(1-('1_Assumptions'!$E$17+IF('1_Assumptions'!$B$39=1,0,$C101))) | F101: =D101-E101-D101*$B$11+D101*$B$12 | G101: =$B$6*$B$13 | H101: =D101*'1_Assumptions'!$E$23 | I101: =$B$6+H101-G101 | J101: =D101*$B$14 | K101: =$B$7-J101 | L101: =$B$8+D101*$B$16-$B$8/$B$18 | M101: =D101*'1_Assumptions'!$B$56/365+E101*'1_Assumptions'!$B$57/365+D101*'1_Assumptions'!$B$54-E101*'1_Assumptions'!$B$58/365-D101*'1_Assumptions'!$B$55 | N101: =F101*(1-$B$15)+G101+J101+IF($B$19=1,D101*'1_Assumptions'!$E$29,0)-H101-(M101-$B$10) | O101: =D101*(1+('1_Assumptions'!$E$12+$B101)) | P101: =O101*(1-('1_Assumptions'!$E$18+$C101)) | Q101: =O101-P101-O101*$B$11+O101*$B$12 | R101: =I101*$B$13 | S101: =O101*'1_Assumptions'!$E$24 | T101: =I101+S101-R101 | U101: =O101*$B$14 | V101: =K101-U101 | W101: =L101+O101*$B$16-L101/$B$18 | X101: =O101*'1_Assumptions'!$B$56/365+P101*'1_Assumptions'!$B$57/365+O101*'1_Assumptions'!$B$54-P101*'1_Assumptions'!$B$58/365-O101*'1_Assumptions'!$B$55 | Y101: =Q101*(1-$B$15)+R101+U101+IF($B$19=1,O101*'1_Assumptions'!$E$30,0)-S101-(X101-M101) | Z101: =O101*(1+('1_Assumptions'!$E$13+$B101)) | AA101: =Z101*(1-('1_Assumptions'!$E$19+$C101)) | AB101: =Z101-AA101-Z101*$B$11+Z101*$B$12 | AC101: =T101*$B$13 | AD101: =Z101*'1_Assumptions'!$E$25 | AE101: =T101+AD101-AC101 | AF101: =Z101*$B$14 | AG101: =V101-AF101 | AH101: =W101+Z101*$B$16-W101/$B$18 | AI101: =Z101*'1_Assumptions'!$B$56/365+AA101*'1_Assumptions'!$B$57/365+Z101*'1_Assumptions'!$B$54-AA101*'1_Assumptions'!$B$58/365-Z101*'1_Assumptions'!$B$55 | AJ101: =AB101*(1-$B$15)+AC101+AF101+IF($B$19=1,Z101*'1_Assumptions'!$E$31,0)-AD101-(AI101-X101) | AK101: =Z101*(1+('1_Assumptions'!$E$14+$B101)) | AL101: =AK101*(1-('1_Assumptions'!$E$20+$C101)) | AM101: =AK101-AL101-AK101*$B$11+AK101*$B$12 | AN101: =AE101*$B$13 | AO101: =AK101*'1_Assumptions'!$E$26 | AP101: =AE101+AO101-AN101 | AQ101: =AK101*$B$14 | AR101: =AG101-AQ101 | AS101: =AH101+AK101*$B$16-AH101/$B$18 | AT101: =AK101*'1_Assumptions'!$B$56/365+AL101*'1_Assumptions'!$B$57/365+AK101*'1_Assumptions'!$B$54-AL101*'1_Assumptions'!$B$58/365-AK101*'1_Assumptions'!$B$55 | AU101: =AM101*(1-$B$15)+AN101+AQ101+IF($B$19=1,AK101*'1_Assumptions'!$E$32,0)-AO101-(AT101-AI101) | AV101: =AK101*(1+('1_Assumptions'!$E$15+$B101)) | AW101: =AV101*(1-('1_Assumptions'!$E$21+$C101)) | AX101: =AV101-AW101-AV101*$B$11+AV101*$B$12 | AY101: =AP101*$B$13 | AZ101: =AV101*'1_Assumptions'!$E$27 | BA101: =AP101+AZ101-AY101 | BB101: =AV101*$B$14 | BC101: =AR101-BB101 | BD101: =AS101+AV101*$B$16-AS101/$B$18 | BE101: =AV101*'1_Assumptions'!$B$56/365+AW101*'1_Assumptions'!$B$57/365+AV101*'1_Assumptions'!$B$54-AW101*'1_Assumptions'!$B$58/365-AV101*'1_Assumptions'!$B$55 | BF101: =AX101*(1-$B$15)+AY101+BB101+IF($B$19=1,AV101*'1_Assumptions'!$E$33,0)-AZ101-(BE101-AT101) | BG101: =N101/(1+$B$21)^(1-0.5*$B$23)+Y101/(1+$B$21)^(2-0.5*$B$23)+AJ101/(1+$B$21)^(3-0.5*$B$23)+AU101/(1+$B$21)^(4-0.5*$B$23)+BF101/(1+$B$21)^(5-0.5*$B$23) | BH101: =BE101+BA101+BC101+$B$9+IF($B$17=1,BD101,0) | BI101: =IF($B$32=2,$B$21+$B$33,IF(BH101=0,0,BL101/BH101)) | BJ101: =IF(BI101=0,9,$B$22/BI101) | BK101: =IF(OR(BH101<=0,BI101<=$B$21,BJ101>=1,BJ101<0),1,0) | BL101: =AX101*(1-$B$20) | BM101: =IF(BK101=1,BL101,AX101*(1+$B$22)*(1-$B$20)*(1-BJ101)) | BN101: =IF(BK101=1,BL101/$B$21,BM101/($B$21-$B$22)) | BO101: =BN101/(1+$B$21)^(5-0.5*$B$23) | BP101: =BG101+BO101 | BQ101: =BP101*(1+$B$21)^$B$24-N101*$B$24*(1+$B$21)^($B$24/2) | BR101: =BQ101-$B$25+$B$26+$B$27 | BS101: =IF($B$28=1,$B$30,BR101*$B$29) | BT101: =BR101-BS101 | BU101: =BT101/$B$31
A102: 2-2 | B102: -0.03 | C102: -0.02 | D102: =$B$5*(1+('1_Assumptions'!$E$11+IF('1_Assumptions'!$B$39=1,0,$B102))) | E102: =D102*(1-('1_Assumptions'!$E$17+IF('1_Assumptions'!$B$39=1,0,$C102))) | F102: =D102-E102-D102*$B$11+D102*$B$12 | G102: =$B$6*$B$13 | H102: =D102*'1_Assumptions'!$E$23 | I102: =$B$6+H102-G102 | J102: =D102*$B$14 | K102: =$B$7-J102 | L102: =$B$8+D102*$B$16-$B$8/$B$18 | M102: =D102*'1_Assumptions'!$B$56/365+E102*'1_Assumptions'!$B$57/365+D102*'1_Assumptions'!$B$54-E102*'1_Assumptions'!$B$58/365-D102*'1_Assumptions'!$B$55 | N102: =F102*(1-$B$15)+G102+J102+IF($B$19=1,D102*'1_Assumptions'!$E$29,0)-H102-(M102-$B$10) | O102: =D102*(1+('1_Assumptions'!$E$12+$B102)) | P102: =O102*(1-('1_Assumptions'!$E$18+$C102)) | Q102: =O102-P102-O102*$B$11+O102*$B$12 | R102: =I102*$B$13 | S102: =O102*'1_Assumptions'!$E$24 | T102: =I102+S102-R102 | U102: =O102*$B$14 | V102: =K102-U102 | W102: =L102+O102*$B$16-L102/$B$18 | X102: =O102*'1_Assumptions'!$B$56/365+P102*'1_Assumptions'!$B$57/365+O102*'1_Assumptions'!$B$54-P102*'1_Assumptions'!$B$58/365-O102*'1_Assumptions'!$B$55 | Y102: =Q102*(1-$B$15)+R102+U102+IF($B$19=1,O102*'1_Assumptions'!$E$30,0)-S102-(X102-M102) | Z102: =O102*(1+('1_Assumptions'!$E$13+$B102)) | AA102: =Z102*(1-('1_Assumptions'!$E$19+$C102)) | AB102: =Z102-AA102-Z102*$B$11+Z102*$B$12 | AC102: =T102*$B$13 | AD102: =Z102*'1_Assumptions'!$E$25 | AE102: =T102+AD102-AC102 | AF102: =Z102*$B$14 | AG102: =V102-AF102 | AH102: =W102+Z102*$B$16-W102/$B$18 | AI102: =Z102*'1_Assumptions'!$B$56/365+AA102*'1_Assumptions'!$B$57/365+Z102*'1_Assumptions'!$B$54-AA102*'1_Assumptions'!$B$58/365-Z102*'1_Assumptions'!$B$55 | AJ102: =AB102*(1-$B$15)+AC102+AF102+IF($B$19=1,Z102*'1_Assumptions'!$E$31,0)-AD102-(AI102-X102) | AK102: =Z102*(1+('1_Assumptions'!$E$14+$B102)) | AL102: =AK102*(1-('1_Assumptions'!$E$20+$C102)) | AM102: =AK102-AL102-AK102*$B$11+AK102*$B$12 | AN102: =AE102*$B$13 | AO102: =AK102*'1_Assumptions'!$E$26 | AP102: =AE102+AO102-AN102 | AQ102: =AK102*$B$14 | AR102: =AG102-AQ102 | AS102: =AH102+AK102*$B$16-AH102/$B$18 | AT102: =AK102*'1_Assumptions'!$B$56/365+AL102*'1_Assumptions'!$B$57/365+AK102*'1_Assumptions'!$B$54-AL102*'1_Assumptions'!$B$58/365-AK102*'1_Assumptions'!$B$55 | AU102: =AM102*(1-$B$15)+AN102+AQ102+IF($B$19=1,AK102*'1_Assumptions'!$E$32,0)-AO102-(AT102-AI102) | AV102: =AK102*(1+('1_Assumptions'!$E$15+$B102)) | AW102: =AV102*(1-('1_Assumptions'!$E$21+$C102)) | AX102: =AV102-AW102-AV102*$B$11+AV102*$B$12 | AY102: =AP102*$B$13 | AZ102: =AV102*'1_Assumptions'!$E$27 | BA102: =AP102+AZ102-AY102 | BB102: =AV102*$B$14 | BC102: =AR102-BB102 | BD102: =AS102+AV102*$B$16-AS102/$B$18 | BE102: =AV102*'1_Assumptions'!$B$56/365+AW102*'1_Assumptions'!$B$57/365+AV102*'1_Assumptions'!$B$54-AW102*'1_Assumptions'!$B$58/365-AV102*'1_Assumptions'!$B$55 | BF102: =AX102*(1-$B$15)+AY102+BB102+IF($B$19=1,AV102*'1_Assumptions'!$E$33,0)-AZ102-(BE102-AT102) | BG102: =N102/(1+$B$21)^(1-0.5*$B$23)+Y102/(1+$B$21)^(2-0.5*$B$23)+AJ102/(1+$B$21)^(3-0.5*$B$23)+AU102/(1+$B$21)^(4-0.5*$B$23)+BF102/(1+$B$21)^(5-0.5*$B$23) | BH102: =BE102+BA102+BC102+$B$9+IF($B$17=1,BD102,0) | BI102: =IF($B$32=2,$B$21+$B$33,IF(BH102=0,0,BL102/BH102)) | BJ102: =IF(BI102=0,9,$B$22/BI102) | BK102: =IF(OR(BH102<=0,BI102<=$B$21,BJ102>=1,BJ102<0),1,0) | BL102: =AX102*(1-$B$20) | BM102: =IF(BK102=1,BL102,AX102*(1+$B$22)*(1-$B$20)*(1-BJ102)) | BN102: =IF(BK102=1,BL102/$B$21,BM102/($B$21-$B$22)) | BO102: =BN102/(1+$B$21)^(5-0.5*$B$23) | BP102: =BG102+BO102 | BQ102: =BP102*(1+$B$21)^$B$24-N102*$B$24*(1+$B$21)^($B$24/2) | BR102: =BQ102-$B$25+$B$26+$B$27 | BS102: =IF($B$28=1,$B$30,BR102*$B$29) | BT102: =BR102-BS102 | BU102: =BT102/$B$31
A103: 2-3 | B103: -0.03 | C103: 0 | D103: =$B$5*(1+('1_Assumptions'!$E$11+IF('1_Assumptions'!$B$39=1,0,$B103))) | E103: =D103*(1-('1_Assumptions'!$E$17+IF('1_Assumptions'!$B$39=1,0,$C103))) | F103: =D103-E103-D103*$B$11+D103*$B$12 | G103: =$B$6*$B$13 | H103: =D103*'1_Assumptions'!$E$23 | I103: =$B$6+H103-G103 | J103: =D103*$B$14 | K103: =$B$7-J103 | L103: =$B$8+D103*$B$16-$B$8/$B$18 | M103: =D103*'1_Assumptions'!$B$56/365+E103*'1_Assumptions'!$B$57/365+D103*'1_Assumptions'!$B$54-E103*'1_Assumptions'!$B$58/365-D103*'1_Assumptions'!$B$55 | N103: =F103*(1-$B$15)+G103+J103+IF($B$19=1,D103*'1_Assumptions'!$E$29,0)-H103-(M103-$B$10) | O103: =D103*(1+('1_Assumptions'!$E$12+$B103)) | P103: =O103*(1-('1_Assumptions'!$E$18+$C103)) | Q103: =O103-P103-O103*$B$11+O103*$B$12 | R103: =I103*$B$13 | S103: =O103*'1_Assumptions'!$E$24 | T103: =I103+S103-R103 | U103: =O103*$B$14 | V103: =K103-U103 | W103: =L103+O103*$B$16-L103/$B$18 | X103: =O103*'1_Assumptions'!$B$56/365+P103*'1_Assumptions'!$B$57/365+O103*'1_Assumptions'!$B$54-P103*'1_Assumptions'!$B$58/365-O103*'1_Assumptions'!$B$55 | Y103: =Q103*(1-$B$15)+R103+U103+IF($B$19=1,O103*'1_Assumptions'!$E$30,0)-S103-(X103-M103) | Z103: =O103*(1+('1_Assumptions'!$E$13+$B103)) | AA103: =Z103*(1-('1_Assumptions'!$E$19+$C103)) | AB103: =Z103-AA103-Z103*$B$11+Z103*$B$12 | AC103: =T103*$B$13 | AD103: =Z103*'1_Assumptions'!$E$25 | AE103: =T103+AD103-AC103 | AF103: =Z103*$B$14 | AG103: =V103-AF103 | AH103: =W103+Z103*$B$16-W103/$B$18 | AI103: =Z103*'1_Assumptions'!$B$56/365+AA103*'1_Assumptions'!$B$57/365+Z103*'1_Assumptions'!$B$54-AA103*'1_Assumptions'!$B$58/365-Z103*'1_Assumptions'!$B$55 | AJ103: =AB103*(1-$B$15)+AC103+AF103+IF($B$19=1,Z103*'1_Assumptions'!$E$31,0)-AD103-(AI103-X103) | AK103: =Z103*(1+('1_Assumptions'!$E$14+$B103)) | AL103: =AK103*(1-('1_Assumptions'!$E$20+$C103)) | AM103: =AK103-AL103-AK103*$B$11+AK103*$B$12 | AN103: =AE103*$B$13 | AO103: =AK103*'1_Assumptions'!$E$26 | AP103: =AE103+AO103-AN103 | AQ103: =AK103*$B$14 | AR103: =AG103-AQ103 | AS103: =AH103+AK103*$B$16-AH103/$B$18 | AT103: =AK103*'1_Assumptions'!$B$56/365+AL103*'1_Assumptions'!$B$57/365+AK103*'1_Assumptions'!$B$54-AL103*'1_Assumptions'!$B$58/365-AK103*'1_Assumptions'!$B$55 | AU103: =AM103*(1-$B$15)+AN103+AQ103+IF($B$19=1,AK103*'1_Assumptions'!$E$32,0)-AO103-(AT103-AI103) | AV103: =AK103*(1+('1_Assumptions'!$E$15+$B103)) | AW103: =AV103*(1-('1_Assumptions'!$E$21+$C103)) | AX103: =AV103-AW103-AV103*$B$11+AV103*$B$12 | AY103: =AP103*$B$13 | AZ103: =AV103*'1_Assumptions'!$E$27 | BA103: =AP103+AZ103-AY103 | BB103: =AV103*$B$14 | BC103: =AR103-BB103 | BD103: =AS103+AV103*$B$16-AS103/$B$18 | BE103: =AV103*'1_Assumptions'!$B$56/365+AW103*'1_Assumptions'!$B$57/365+AV103*'1_Assumptions'!$B$54-AW103*'1_Assumptions'!$B$58/365-AV103*'1_Assumptions'!$B$55 | BF103: =AX103*(1-$B$15)+AY103+BB103+IF($B$19=1,AV103*'1_Assumptions'!$E$33,0)-AZ103-(BE103-AT103) | BG103: =N103/(1+$B$21)^(1-0.5*$B$23)+Y103/(1+$B$21)^(2-0.5*$B$23)+AJ103/(1+$B$21)^(3-0.5*$B$23)+AU103/(1+$B$21)^(4-0.5*$B$23)+BF103/(1+$B$21)^(5-0.5*$B$23) | BH103: =BE103+BA103+BC103+$B$9+IF($B$17=1,BD103,0) | BI103: =IF($B$32=2,$B$21+$B$33,IF(BH103=0,0,BL103/BH103)) | BJ103: =IF(BI103=0,9,$B$22/BI103) | BK103: =IF(OR(BH103<=0,BI103<=$B$21,BJ103>=1,BJ103<0),1,0) | BL103: =AX103*(1-$B$20) | BM103: =IF(BK103=1,BL103,AX103*(1+$B$22)*(1-$B$20)*(1-BJ103)) | BN103: =IF(BK103=1,BL103/$B$21,BM103/($B$21-$B$22)) | BO103: =BN103/(1+$B$21)^(5-0.5*$B$23) | BP103: =BG103+BO103 | BQ103: =BP103*(1+$B$21)^$B$24-N103*$B$24*(1+$B$21)^($B$24/2) | BR103: =BQ103-$B$25+$B$26+$B$27 | BS103: =IF($B$28=1,$B$30,BR103*$B$29) | BT103: =BR103-BS103 | BU103: =BT103/$B$31
A104: 2-4 | B104: -0.03 | C104: 0.02 | D104: =$B$5*(1+('1_Assumptions'!$E$11+IF('1_Assumptions'!$B$39=1,0,$B104))) | E104: =D104*(1-('1_Assumptions'!$E$17+IF('1_Assumptions'!$B$39=1,0,$C104))) | F104: =D104-E104-D104*$B$11+D104*$B$12 | G104: =$B$6*$B$13 | H104: =D104*'1_Assumptions'!$E$23 | I104: =$B$6+H104-G104 | J104: =D104*$B$14 | K104: =$B$7-J104 | L104: =$B$8+D104*$B$16-$B$8/$B$18 | M104: =D104*'1_Assumptions'!$B$56/365+E104*'1_Assumptions'!$B$57/365+D104*'1_Assumptions'!$B$54-E104*'1_Assumptions'!$B$58/365-D104*'1_Assumptions'!$B$55 | N104: =F104*(1-$B$15)+G104+J104+IF($B$19=1,D104*'1_Assumptions'!$E$29,0)-H104-(M104-$B$10) | O104: =D104*(1+('1_Assumptions'!$E$12+$B104)) | P104: =O104*(1-('1_Assumptions'!$E$18+$C104)) | Q104: =O104-P104-O104*$B$11+O104*$B$12 | R104: =I104*$B$13 | S104: =O104*'1_Assumptions'!$E$24 | T104: =I104+S104-R104 | U104: =O104*$B$14 | V104: =K104-U104 | W104: =L104+O104*$B$16-L104/$B$18 | X104: =O104*'1_Assumptions'!$B$56/365+P104*'1_Assumptions'!$B$57/365+O104*'1_Assumptions'!$B$54-P104*'1_Assumptions'!$B$58/365-O104*'1_Assumptions'!$B$55 | Y104: =Q104*(1-$B$15)+R104+U104+IF($B$19=1,O104*'1_Assumptions'!$E$30,0)-S104-(X104-M104) | Z104: =O104*(1+('1_Assumptions'!$E$13+$B104)) | AA104: =Z104*(1-('1_Assumptions'!$E$19+$C104)) | AB104: =Z104-AA104-Z104*$B$11+Z104*$B$12 | AC104: =T104*$B$13 | AD104: =Z104*'1_Assumptions'!$E$25 | AE104: =T104+AD104-AC104 | AF104: =Z104*$B$14 | AG104: =V104-AF104 | AH104: =W104+Z104*$B$16-W104/$B$18 | AI104: =Z104*'1_Assumptions'!$B$56/365+AA104*'1_Assumptions'!$B$57/365+Z104*'1_Assumptions'!$B$54-AA104*'1_Assumptions'!$B$58/365-Z104*'1_Assumptions'!$B$55 | AJ104: =AB104*(1-$B$15)+AC104+AF104+IF($B$19=1,Z104*'1_Assumptions'!$E$31,0)-AD104-(AI104-X104) | AK104: =Z104*(1+('1_Assumptions'!$E$14+$B104)) | AL104: =AK104*(1-('1_Assumptions'!$E$20+$C104)) | AM104: =AK104-AL104-AK104*$B$11+AK104*$B$12 | AN104: =AE104*$B$13 | AO104: =AK104*'1_Assumptions'!$E$26 | AP104: =AE104+AO104-AN104 | AQ104: =AK104*$B$14 | AR104: =AG104-AQ104 | AS104: =AH104+AK104*$B$16-AH104/$B$18 | AT104: =AK104*'1_Assumptions'!$B$56/365+AL104*'1_Assumptions'!$B$57/365+AK104*'1_Assumptions'!$B$54-AL104*'1_Assumptions'!$B$58/365-AK104*'1_Assumptions'!$B$55 | AU104: =AM104*(1-$B$15)+AN104+AQ104+IF($B$19=1,AK104*'1_Assumptions'!$E$32,0)-AO104-(AT104-AI104) | AV104: =AK104*(1+('1_Assumptions'!$E$15+$B104)) | AW104: =AV104*(1-('1_Assumptions'!$E$21+$C104)) | AX104: =AV104-AW104-AV104*$B$11+AV104*$B$12 | AY104: =AP104*$B$13 | AZ104: =AV104*'1_Assumptions'!$E$27 | BA104: =AP104+AZ104-AY104 | BB104: =AV104*$B$14 | BC104: =AR104-BB104 | BD104: =AS104+AV104*$B$16-AS104/$B$18 | BE104: =AV104*'1_Assumptions'!$B$56/365+AW104*'1_Assumptions'!$B$57/365+AV104*'1_Assumptions'!$B$54-AW104*'1_Assumptions'!$B$58/365-AV104*'1_Assumptions'!$B$55 | BF104: =AX104*(1-$B$15)+AY104+BB104+IF($B$19=1,AV104*'1_Assumptions'!$E$33,0)-AZ104-(BE104-AT104) | BG104: =N104/(1+$B$21)^(1-0.5*$B$23)+Y104/(1+$B$21)^(2-0.5*$B$23)+AJ104/(1+$B$21)^(3-0.5*$B$23)+AU104/(1+$B$21)^(4-0.5*$B$23)+BF104/(1+$B$21)^(5-0.5*$B$23) | BH104: =BE104+BA104+BC104+$B$9+IF($B$17=1,BD104,0) | BI104: =IF($B$32=2,$B$21+$B$33,IF(BH104=0,0,BL104/BH104)) | BJ104: =IF(BI104=0,9,$B$22/BI104) | BK104: =IF(OR(BH104<=0,BI104<=$B$21,BJ104>=1,BJ104<0),1,0) | BL104: =AX104*(1-$B$20) | BM104: =IF(BK104=1,BL104,AX104*(1+$B$22)*(1-$B$20)*(1-BJ104)) | BN104: =IF(BK104=1,BL104/$B$21,BM104/($B$21-$B$22)) | BO104: =BN104/(1+$B$21)^(5-0.5*$B$23) | BP104: =BG104+BO104 | BQ104: =BP104*(1+$B$21)^$B$24-N104*$B$24*(1+$B$21)^($B$24/2) | BR104: =BQ104-$B$25+$B$26+$B$27 | BS104: =IF($B$28=1,$B$30,BR104*$B$29) | BT104: =BR104-BS104 | BU104: =BT104/$B$31
A105: 2-5 | B105: -0.03 | C105: 0.04 | D105: =$B$5*(1+('1_Assumptions'!$E$11+IF('1_Assumptions'!$B$39=1,0,$B105))) | E105: =D105*(1-('1_Assumptions'!$E$17+IF('1_Assumptions'!$B$39=1,0,$C105))) | F105: =D105-E105-D105*$B$11+D105*$B$12 | G105: =$B$6*$B$13 | H105: =D105*'1_Assumptions'!$E$23 | I105: =$B$6+H105-G105 | J105: =D105*$B$14 | K105: =$B$7-J105 | L105: =$B$8+D105*$B$16-$B$8/$B$18 | M105: =D105*'1_Assumptions'!$B$56/365+E105*'1_Assumptions'!$B$57/365+D105*'1_Assumptions'!$B$54-E105*'1_Assumptions'!$B$58/365-D105*'1_Assumptions'!$B$55 | N105: =F105*(1-$B$15)+G105+J105+IF($B$19=1,D105*'1_Assumptions'!$E$29,0)-H105-(M105-$B$10) | O105: =D105*(1+('1_Assumptions'!$E$12+$B105)) | P105: =O105*(1-('1_Assumptions'!$E$18+$C105)) | Q105: =O105-P105-O105*$B$11+O105*$B$12 | R105: =I105*$B$13 | S105: =O105*'1_Assumptions'!$E$24 | T105: =I105+S105-R105 | U105: =O105*$B$14 | V105: =K105-U105 | W105: =L105+O105*$B$16-L105/$B$18 | X105: =O105*'1_Assumptions'!$B$56/365+P105*'1_Assumptions'!$B$57/365+O105*'1_Assumptions'!$B$54-P105*'1_Assumptions'!$B$58/365-O105*'1_Assumptions'!$B$55 | Y105: =Q105*(1-$B$15)+R105+U105+IF($B$19=1,O105*'1_Assumptions'!$E$30,0)-S105-(X105-M105) | Z105: =O105*(1+('1_Assumptions'!$E$13+$B105)) | AA105: =Z105*(1-('1_Assumptions'!$E$19+$C105)) | AB105: =Z105-AA105-Z105*$B$11+Z105*$B$12 | AC105: =T105*$B$13 | AD105: =Z105*'1_Assumptions'!$E$25 | AE105: =T105+AD105-AC105 | AF105: =Z105*$B$14 | AG105: =V105-AF105 | AH105: =W105+Z105*$B$16-W105/$B$18 | AI105: =Z105*'1_Assumptions'!$B$56/365+AA105*'1_Assumptions'!$B$57/365+Z105*'1_Assumptions'!$B$54-AA105*'1_Assumptions'!$B$58/365-Z105*'1_Assumptions'!$B$55 | AJ105: =AB105*(1-$B$15)+AC105+AF105+IF($B$19=1,Z105*'1_Assumptions'!$E$31,0)-AD105-(AI105-X105) | AK105: =Z105*(1+('1_Assumptions'!$E$14+$B105)) | AL105: =AK105*(1-('1_Assumptions'!$E$20+$C105)) | AM105: =AK105-AL105-AK105*$B$11+AK105*$B$12 | AN105: =AE105*$B$13 | AO105: =AK105*'1_Assumptions'!$E$26 | AP105: =AE105+AO105-AN105 | AQ105: =AK105*$B$14 | AR105: =AG105-AQ105 | AS105: =AH105+AK105*$B$16-AH105/$B$18 | AT105: =AK105*'1_Assumptions'!$B$56/365+AL105*'1_Assumptions'!$B$57/365+AK105*'1_Assumptions'!$B$54-AL105*'1_Assumptions'!$B$58/365-AK105*'1_Assumptions'!$B$55 | AU105: =AM105*(1-$B$15)+AN105+AQ105+IF($B$19=1,AK105*'1_Assumptions'!$E$32,0)-AO105-(AT105-AI105) | AV105: =AK105*(1+('1_Assumptions'!$E$15+$B105)) | AW105: =AV105*(1-('1_Assumptions'!$E$21+$C105)) | AX105: =AV105-AW105-AV105*$B$11+AV105*$B$12 | AY105: =AP105*$B$13 | AZ105: =AV105*'1_Assumptions'!$E$27 | BA105: =AP105+AZ105-AY105 | BB105: =AV105*$B$14 | BC105: =AR105-BB105 | BD105: =AS105+AV105*$B$16-AS105/$B$18 | BE105: =AV105*'1_Assumptions'!$B$56/365+AW105*'1_Assumptions'!$B$57/365+AV105*'1_Assumptions'!$B$54-AW105*'1_Assumptions'!$B$58/365-AV105*'1_Assumptions'!$B$55 | BF105: =AX105*(1-$B$15)+AY105+BB105+IF($B$19=1,AV105*'1_Assumptions'!$E$33,0)-AZ105-(BE105-AT105) | BG105: =N105/(1+$B$21)^(1-0.5*$B$23)+Y105/(1+$B$21)^(2-0.5*$B$23)+AJ105/(1+$B$21)^(3-0.5*$B$23)+AU105/(1+$B$21)^(4-0.5*$B$23)+BF105/(1+$B$21)^(5-0.5*$B$23) | BH105: =BE105+BA105+BC105+$B$9+IF($B$17=1,BD105,0) | BI105: =IF($B$32=2,$B$21+$B$33,IF(BH105=0,0,BL105/BH105)) | BJ105: =IF(BI105=0,9,$B$22/BI105) | BK105: =IF(OR(BH105<=0,BI105<=$B$21,BJ105>=1,BJ105<0),1,0) | BL105: =AX105*(1-$B$20) | BM105: =IF(BK105=1,BL105,AX105*(1+$B$22)*(1-$B$20)*(1-BJ105)) | BN105: =IF(BK105=1,BL105/$B$21,BM105/($B$21-$B$22)) | BO105: =BN105/(1+$B$21)^(5-0.5*$B$23) | BP105: =BG105+BO105 | BQ105: =BP105*(1+$B$21)^$B$24-N105*$B$24*(1+$B$21)^($B$24/2) | BR105: =BQ105-$B$25+$B$26+$B$27 | BS105: =IF($B$28=1,$B$30,BR105*$B$29) | BT105: =BR105-BS105 | BU105: =BT105/$B$31
A106: 3-1 | B106: 0 | C106: -0.04 | D106: =$B$5*(1+('1_Assumptions'!$E$11+IF('1_Assumptions'!$B$39=1,0,$B106))) | E106: =D106*(1-('1_Assumptions'!$E$17+IF('1_Assumptions'!$B$39=1,0,$C106))) | F106: =D106-E106-D106*$B$11+D106*$B$12 | G106: =$B$6*$B$13 | H106: =D106*'1_Assumptions'!$E$23 | I106: =$B$6+H106-G106 | J106: =D106*$B$14 | K106: =$B$7-J106 | L106: =$B$8+D106*$B$16-$B$8/$B$18 | M106: =D106*'1_Assumptions'!$B$56/365+E106*'1_Assumptions'!$B$57/365+D106*'1_Assumptions'!$B$54-E106*'1_Assumptions'!$B$58/365-D106*'1_Assumptions'!$B$55 | N106: =F106*(1-$B$15)+G106+J106+IF($B$19=1,D106*'1_Assumptions'!$E$29,0)-H106-(M106-$B$10) | O106: =D106*(1+('1_Assumptions'!$E$12+$B106)) | P106: =O106*(1-('1_Assumptions'!$E$18+$C106)) | Q106: =O106-P106-O106*$B$11+O106*$B$12 | R106: =I106*$B$13 | S106: =O106*'1_Assumptions'!$E$24 | T106: =I106+S106-R106 | U106: =O106*$B$14 | V106: =K106-U106 | W106: =L106+O106*$B$16-L106/$B$18 | X106: =O106*'1_Assumptions'!$B$56/365+P106*'1_Assumptions'!$B$57/365+O106*'1_Assumptions'!$B$54-P106*'1_Assumptions'!$B$58/365-O106*'1_Assumptions'!$B$55 | Y106: =Q106*(1-$B$15)+R106+U106+IF($B$19=1,O106*'1_Assumptions'!$E$30,0)-S106-(X106-M106) | Z106: =O106*(1+('1_Assumptions'!$E$13+$B106)) | AA106: =Z106*(1-('1_Assumptions'!$E$19+$C106)) | AB106: =Z106-AA106-Z106*$B$11+Z106*$B$12 | AC106: =T106*$B$13 | AD106: =Z106*'1_Assumptions'!$E$25 | AE106: =T106+AD106-AC106 | AF106: =Z106*$B$14 | AG106: =V106-AF106 | AH106: =W106+Z106*$B$16-W106/$B$18 | AI106: =Z106*'1_Assumptions'!$B$56/365+AA106*'1_Assumptions'!$B$57/365+Z106*'1_Assumptions'!$B$54-AA106*'1_Assumptions'!$B$58/365-Z106*'1_Assumptions'!$B$55 | AJ106: =AB106*(1-$B$15)+AC106+AF106+IF($B$19=1,Z106*'1_Assumptions'!$E$31,0)-AD106-(AI106-X106) | AK106: =Z106*(1+('1_Assumptions'!$E$14+$B106)) | AL106: =AK106*(1-('1_Assumptions'!$E$20+$C106)) | AM106: =AK106-AL106-AK106*$B$11+AK106*$B$12 | AN106: =AE106*$B$13 | AO106: =AK106*'1_Assumptions'!$E$26 | AP106: =AE106+AO106-AN106 | AQ106: =AK106*$B$14 | AR106: =AG106-AQ106 | AS106: =AH106+AK106*$B$16-AH106/$B$18 | AT106: =AK106*'1_Assumptions'!$B$56/365+AL106*'1_Assumptions'!$B$57/365+AK106*'1_Assumptions'!$B$54-AL106*'1_Assumptions'!$B$58/365-AK106*'1_Assumptions'!$B$55 | AU106: =AM106*(1-$B$15)+AN106+AQ106+IF($B$19=1,AK106*'1_Assumptions'!$E$32,0)-AO106-(AT106-AI106) | AV106: =AK106*(1+('1_Assumptions'!$E$15+$B106)) | AW106: =AV106*(1-('1_Assumptions'!$E$21+$C106)) | AX106: =AV106-AW106-AV106*$B$11+AV106*$B$12 | AY106: =AP106*$B$13 | AZ106: =AV106*'1_Assumptions'!$E$27 | BA106: =AP106+AZ106-AY106 | BB106: =AV106*$B$14 | BC106: =AR106-BB106 | BD106: =AS106+AV106*$B$16-AS106/$B$18 | BE106: =AV106*'1_Assumptions'!$B$56/365+AW106*'1_Assumptions'!$B$57/365+AV106*'1_Assumptions'!$B$54-AW106*'1_Assumptions'!$B$58/365-AV106*'1_Assumptions'!$B$55 | BF106: =AX106*(1-$B$15)+AY106+BB106+IF($B$19=1,AV106*'1_Assumptions'!$E$33,0)-AZ106-(BE106-AT106) | BG106: =N106/(1+$B$21)^(1-0.5*$B$23)+Y106/(1+$B$21)^(2-0.5*$B$23)+AJ106/(1+$B$21)^(3-0.5*$B$23)+AU106/(1+$B$21)^(4-0.5*$B$23)+BF106/(1+$B$21)^(5-0.5*$B$23) | BH106: =BE106+BA106+BC106+$B$9+IF($B$17=1,BD106,0) | BI106: =IF($B$32=2,$B$21+$B$33,IF(BH106=0,0,BL106/BH106)) | BJ106: =IF(BI106=0,9,$B$22/BI106) | BK106: =IF(OR(BH106<=0,BI106<=$B$21,BJ106>=1,BJ106<0),1,0) | BL106: =AX106*(1-$B$20) | BM106: =IF(BK106=1,BL106,AX106*(1+$B$22)*(1-$B$20)*(1-BJ106)) | BN106: =IF(BK106=1,BL106/$B$21,BM106/($B$21-$B$22)) | BO106: =BN106/(1+$B$21)^(5-0.5*$B$23) | BP106: =BG106+BO106 | BQ106: =BP106*(1+$B$21)^$B$24-N106*$B$24*(1+$B$21)^($B$24/2) | BR106: =BQ106-$B$25+$B$26+$B$27 | BS106: =IF($B$28=1,$B$30,BR106*$B$29) | BT106: =BR106-BS106 | BU106: =BT106/$B$31
A107: 3-2 | B107: 0 | C107: -0.02 | D107: =$B$5*(1+('1_Assumptions'!$E$11+IF('1_Assumptions'!$B$39=1,0,$B107))) | E107: =D107*(1-('1_Assumptions'!$E$17+IF('1_Assumptions'!$B$39=1,0,$C107))) | F107: =D107-E107-D107*$B$11+D107*$B$12 | G107: =$B$6*$B$13 | H107: =D107*'1_Assumptions'!$E$23 | I107: =$B$6+H107-G107 | J107: =D107*$B$14 | K107: =$B$7-J107 | L107: =$B$8+D107*$B$16-$B$8/$B$18 | M107: =D107*'1_Assumptions'!$B$56/365+E107*'1_Assumptions'!$B$57/365+D107*'1_Assumptions'!$B$54-E107*'1_Assumptions'!$B$58/365-D107*'1_Assumptions'!$B$55 | N107: =F107*(1-$B$15)+G107+J107+IF($B$19=1,D107*'1_Assumptions'!$E$29,0)-H107-(M107-$B$10) | O107: =D107*(1+('1_Assumptions'!$E$12+$B107)) | P107: =O107*(1-('1_Assumptions'!$E$18+$C107)) | Q107: =O107-P107-O107*$B$11+O107*$B$12 | R107: =I107*$B$13 | S107: =O107*'1_Assumptions'!$E$24 | T107: =I107+S107-R107 | U107: =O107*$B$14 | V107: =K107-U107 | W107: =L107+O107*$B$16-L107/$B$18 | X107: =O107*'1_Assumptions'!$B$56/365+P107*'1_Assumptions'!$B$57/365+O107*'1_Assumptions'!$B$54-P107*'1_Assumptions'!$B$58/365-O107*'1_Assumptions'!$B$55 | Y107: =Q107*(1-$B$15)+R107+U107+IF($B$19=1,O107*'1_Assumptions'!$E$30,0)-S107-(X107-M107) | Z107: =O107*(1+('1_Assumptions'!$E$13+$B107)) | AA107: =Z107*(1-('1_Assumptions'!$E$19+$C107)) | AB107: =Z107-AA107-Z107*$B$11+Z107*$B$12 | AC107: =T107*$B$13 | AD107: =Z107*'1_Assumptions'!$E$25 | AE107: =T107+AD107-AC107 | AF107: =Z107*$B$14 | AG107: =V107-AF107 | AH107: =W107+Z107*$B$16-W107/$B$18 | AI107: =Z107*'1_Assumptions'!$B$56/365+AA107*'1_Assumptions'!$B$57/365+Z107*'1_Assumptions'!$B$54-AA107*'1_Assumptions'!$B$58/365-Z107*'1_Assumptions'!$B$55 | AJ107: =AB107*(1-$B$15)+AC107+AF107+IF($B$19=1,Z107*'1_Assumptions'!$E$31,0)-AD107-(AI107-X107) | AK107: =Z107*(1+('1_Assumptions'!$E$14+$B107)) | AL107: =AK107*(1-('1_Assumptions'!$E$20+$C107)) | AM107: =AK107-AL107-AK107*$B$11+AK107*$B$12 | AN107: =AE107*$B$13 | AO107: =AK107*'1_Assumptions'!$E$26 | AP107: =AE107+AO107-AN107 | AQ107: =AK107*$B$14 | AR107: =AG107-AQ107 | AS107: =AH107+AK107*$B$16-AH107/$B$18 | AT107: =AK107*'1_Assumptions'!$B$56/365+AL107*'1_Assumptions'!$B$57/365+AK107*'1_Assumptions'!$B$54-AL107*'1_Assumptions'!$B$58/365-AK107*'1_Assumptions'!$B$55 | AU107: =AM107*(1-$B$15)+AN107+AQ107+IF($B$19=1,AK107*'1_Assumptions'!$E$32,0)-AO107-(AT107-AI107) | AV107: =AK107*(1+('1_Assumptions'!$E$15+$B107)) | AW107: =AV107*(1-('1_Assumptions'!$E$21+$C107)) | AX107: =AV107-AW107-AV107*$B$11+AV107*$B$12 | AY107: =AP107*$B$13 | AZ107: =AV107*'1_Assumptions'!$E$27 | BA107: =AP107+AZ107-AY107 | BB107: =AV107*$B$14 | BC107: =AR107-BB107 | BD107: =AS107+AV107*$B$16-AS107/$B$18 | BE107: =AV107*'1_Assumptions'!$B$56/365+AW107*'1_Assumptions'!$B$57/365+AV107*'1_Assumptions'!$B$54-AW107*'1_Assumptions'!$B$58/365-AV107*'1_Assumptions'!$B$55 | BF107: =AX107*(1-$B$15)+AY107+BB107+IF($B$19=1,AV107*'1_Assumptions'!$E$33,0)-AZ107-(BE107-AT107) | BG107: =N107/(1+$B$21)^(1-0.5*$B$23)+Y107/(1+$B$21)^(2-0.5*$B$23)+AJ107/(1+$B$21)^(3-0.5*$B$23)+AU107/(1+$B$21)^(4-0.5*$B$23)+BF107/(1+$B$21)^(5-0.5*$B$23) | BH107: =BE107+BA107+BC107+$B$9+IF($B$17=1,BD107,0) | BI107: =IF($B$32=2,$B$21+$B$33,IF(BH107=0,0,BL107/BH107)) | BJ107: =IF(BI107=0,9,$B$22/BI107) | BK107: =IF(OR(BH107<=0,BI107<=$B$21,BJ107>=1,BJ107<0),1,0) | BL107: =AX107*(1-$B$20) | BM107: =IF(BK107=1,BL107,AX107*(1+$B$22)*(1-$B$20)*(1-BJ107)) | BN107: =IF(BK107=1,BL107/$B$21,BM107/($B$21-$B$22)) | BO107: =BN107/(1+$B$21)^(5-0.5*$B$23) | BP107: =BG107+BO107 | BQ107: =BP107*(1+$B$21)^$B$24-N107*$B$24*(1+$B$21)^($B$24/2) | BR107: =BQ107-$B$25+$B$26+$B$27 | BS107: =IF($B$28=1,$B$30,BR107*$B$29) | BT107: =BR107-BS107 | BU107: =BT107/$B$31
... A120: 5-5 | B120: 0.06 | C120: 0.04 | D120: =$B$5*(1+('1_Assumptions'!$E$11+IF('1_Assumptions'!$B$39=1,0,$B120))) | E120: =D120*(1-('1_Assumptions'!$E$17+IF('1_Assumptions'!$B$39=1,0,$C120))) | F120: =D120-E120-D120*$B$11+D120*$B$12 | G120: =$B$6*$B$13 | H120: =D120*'1_Assumptions'!$E$23 | I120: =$B$6+H120-G120 | J120: =D120*$B$14 | K120: =$B$7-J120 | L120: =$B$8+D120*$B$16-$B$8/$B$18 | M120: =D120*'1_Assumptions'!$B$56/365+E120*'1_Assumptions'!$B$57/365+D120*'1_Assumptions'!$B$54-E120*'1_Assumptions'!$B$58/365-D120*'1_Assumptions'!$B$55 | N120: =F120*(1-$B$15)+G120+J120+IF($B$19=1,D120*'1_Assumptions'!$E$29,0)-H120-(M120-$B$10) | O120: =D120*(1+('1_Assumptions'!$E$12+$B120)) | P120: =O120*(1-('1_Assumptions'!$E$18+$C120)) | Q120: =O120-P120-O120*$B$11+O120*$B$12 | R120: =I120*$B$13 | S120: =O120*'1_Assumptions'!$E$24 | T120: =I120+S120-R120 | U120: =O120*$B$14 | V120: =K120-U120 | W120: =L120+O120*$B$16-L120/$B$18 | X120: =O120*'1_Assumptions'!$B$56/365+P120*'1_Assumptions'!$B$57/365+O120*'1_Assumptions'!$B$54-P120*'1_Assumptions'!$B$58/365-O120*'1_Assumptions'!$B$55 | Y120: =Q120*(1-$B$15)+R120+U120+IF($B$19=1,O120*'1_Assumptions'!$E$30,0)-S120-(X120-M120) | Z120: =O120*(1+('1_Assumptions'!$E$13+$B120)) | AA120: =Z120*(1-('1_Assumptions'!$E$19+$C120)) | AB120: =Z120-AA120-Z120*$B$11+Z120*$B$12 | AC120: =T120*$B$13 | AD120: =Z120*'1_Assumptions'!$E$25 | AE120: =T120+AD120-AC120 | AF120: =Z120*$B$14 | AG120: =V120-AF120 | AH120: =W120+Z120*$B$16-W120/$B$18 | AI120: =Z120*'1_Assumptions'!$B$56/365+AA120*'1_Assumptions'!$B$57/365+Z120*'1_Assumptions'!$B$54-AA120*'1_Assumptions'!$B$58/365-Z120*'1_Assumptions'!$B$55 | AJ120: =AB120*(1-$B$15)+AC120+AF120+IF($B$19=1,Z120*'1_Assumptions'!$E$31,0)-AD120-(AI120-X120) | AK120: =Z120*(1+('1_Assumptions'!$E$14+$B120)) | AL120: =AK120*(1-('1_Assumptions'!$E$20+$C120)) | AM120: =AK120-AL120-AK120*$B$11+AK120*$B$12 | AN120: =AE120*$B$13 | AO120: =AK120*'1_Assumptions'!$E$26 | AP120: =AE120+AO120-AN120 | AQ120: =AK120*$B$14 | AR120: =AG120-AQ120 | AS120: =AH120+AK120*$B$16-AH120/$B$18 | AT120: =AK120*'1_Assumptions'!$B$56/365+AL120*'1_Assumptions'!$B$57/365+AK120*'1_Assumptions'!$B$54-AL120*'1_Assumptions'!$B$58/365-AK120*'1_Assumptions'!$B$55 | AU120: =AM120*(1-$B$15)+AN120+AQ120+IF($B$19=1,AK120*'1_Assumptions'!$E$32,0)-AO120-(AT120-AI120) | AV120: =AK120*(1+('1_Assumptions'!$E$15+$B120)) | AW120: =AV120*(1-('1_Assumptions'!$E$21+$C120)) | AX120: =AV120-AW120-AV120*$B$11+AV120*$B$12 | AY120: =AP120*$B$13 | AZ120: =AV120*'1_Assumptions'!$E$27 | BA120: =AP120+AZ120-AY120 | BB120: =AV120*$B$14 | BC120: =AR120-BB120 | BD120: =AS120+AV120*$B$16-AS120/$B$18 | BE120: =AV120*'1_Assumptions'!$B$56/365+AW120*'1_Assumptions'!$B$57/365+AV120*'1_Assumptions'!$B$54-AW120*'1_Assumptions'!$B$58/365-AV120*'1_Assumptions'!$B$55 | BF120: =AX120*(1-$B$15)+AY120+BB120+IF($B$19=1,AV120*'1_Assumptions'!$E$33,0)-AZ120-(BE120-AT120) | BG120: =N120/(1+$B$21)^(1-0.5*$B$23)+Y120/(1+$B$21)^(2-0.5*$B$23)+AJ120/(1+$B$21)^(3-0.5*$B$23)+AU120/(1+$B$21)^(4-0.5*$B$23)+BF120/(1+$B$21)^(5-0.5*$B$23) | BH120: =BE120+BA120+BC120+$B$9+IF($B$17=1,BD120,0) | BI120: =IF($B$32=2,$B$21+$B$33,IF(BH120=0,0,BL120/BH120)) | BJ120: =IF(BI120=0,9,$B$22/BI120) | BK120: =IF(OR(BH120<=0,BI120<=$B$21,BJ120>=1,BJ120<0),1,0) | BL120: =AX120*(1-$B$20) | BM120: =IF(BK120=1,BL120,AX120*(1+$B$22)*(1-$B$20)*(1-BJ120)) | BN120: =IF(BK120=1,BL120/$B$21,BM120/($B$21-$B$22)) | BO120: =BN120/(1+$B$21)^(5-0.5*$B$23) | BP120: =BG120+BO120 | BQ120: =BP120*(1+$B$21)^$B$24-N120*$B$24*(1+$B$21)^($B$24/2) | BR120: =BQ120-$B$25+$B$26+$B$27 | BS120: =IF($B$28=1,$B$30,BR120*$B$29) | BT120: =BR120-BS120 | BU120: =BT120/$B$31
A122: 模块 D：WACC × 毛利率平移
A123: WACC 偏移直接加在生效 WACC 上，不改 Beta/ERP
A124: 场景 | B124: WACC 偏移 | C124: 毛利率 Δ | D124: 营收1 | E124: 成本1 | F124: EBIT1 | G124: 折旧1 | H124: 资本开支1 | I124: 期末固资1 | J124: 摊销1 | K124: 商誉无形1 | L124: 研发资本1 | M124: NWC1 | N124: FCFF1 | O124: 营收2 | P124: 成本2 | Q124: EBIT2 | R124: 折旧2 | S124: 资本开支2 | T124: 期末固资2 | U124: 摊销2 | V124: 商誉无形2 | W124: 研发资本2 | X124: NWC2 | Y124: FCFF2 | Z124: 营收3 | AA124: 成本3 | AB124: EBIT3 | AC124: 折旧3 | AD124: 资本开支3 | AE124: 期末固资3 | AF124: 摊销3 | AG124: 商誉无形3 | AH124: 研发资本3 | AI124: NWC3 | AJ124: FCFF3 | AK124: 营收4 | AL124: 成本4 | AM124: EBIT4 | AN124: 折旧4 | AO124: 资本开支4 | AP124: 期末固资4 | AQ124: 摊销4 | AR124: 商誉无形4 | AS124: 研发资本4 | AT124: NWC4 | AU124: FCFF4 | AV124: 营收5 | AW124: 成本5 | AX124: EBIT5 | AY124: 折旧5 | AZ124: 资本开支5 | BA124: 期末固资5 | BB124: 摊销5 | BC124: 商誉无形5 | BD124: 研发资本5 | BE124: NWC5 | BF124: FCFF5 | BG124: PV明确期 | BH124: 终值IC | BI124: 终值ROIC | BJ124: 再投资率 | BK124: 降级 | BL124: 终值NOPAT | BM124: 终值FCFF | BN124: TV | BO124: PV(TV) | BP124: EV0 | BQ124: EV | BR124: 全体权益 | BS124: 少数股东 | BT124: 归母权益 | BU124: 每股
A125: 1-1 | B125: =$B$21+-0.02 | C125: -0.04 | D125: =$B$5*(1+'1_Assumptions'!$E$11) | E125: =D125*(1-('1_Assumptions'!$E$17+IF('1_Assumptions'!$B$39=1,0,$C125))) | F125: =D125-E125-D125*$B$11+D125*$B$12 | G125: =$B$6*$B$13 | H125: =D125*'1_Assumptions'!$E$23 | I125: =$B$6+H125-G125 | J125: =D125*$B$14 | K125: =$B$7-J125 | L125: =$B$8+D125*$B$16-$B$8/$B$18 | M125: =D125*'1_Assumptions'!$B$56/365+E125*'1_Assumptions'!$B$57/365+D125*'1_Assumptions'!$B$54-E125*'1_Assumptions'!$B$58/365-D125*'1_Assumptions'!$B$55 | N125: =F125*(1-$B$15)+G125+J125+IF($B$19=1,D125*'1_Assumptions'!$E$29,0)-H125-(M125-$B$10) | O125: =D125*(1+'1_Assumptions'!$E$12) | P125: =O125*(1-('1_Assumptions'!$E$18+$C125)) | Q125: =O125-P125-O125*$B$11+O125*$B$12 | R125: =I125*$B$13 | S125: =O125*'1_Assumptions'!$E$24 | T125: =I125+S125-R125 | U125: =O125*$B$14 | V125: =K125-U125 | W125: =L125+O125*$B$16-L125/$B$18 | X125: =O125*'1_Assumptions'!$B$56/365+P125*'1_Assumptions'!$B$57/365+O125*'1_Assumptions'!$B$54-P125*'1_Assumptions'!$B$58/365-O125*'1_Assumptions'!$B$55 | Y125: =Q125*(1-$B$15)+R125+U125+IF($B$19=1,O125*'1_Assumptions'!$E$30,0)-S125-(X125-M125) | Z125: =O125*(1+'1_Assumptions'!$E$13) | AA125: =Z125*(1-('1_Assumptions'!$E$19+$C125)) | AB125: =Z125-AA125-Z125*$B$11+Z125*$B$12 | AC125: =T125*$B$13 | AD125: =Z125*'1_Assumptions'!$E$25 | AE125: =T125+AD125-AC125 | AF125: =Z125*$B$14 | AG125: =V125-AF125 | AH125: =W125+Z125*$B$16-W125/$B$18 | AI125: =Z125*'1_Assumptions'!$B$56/365+AA125*'1_Assumptions'!$B$57/365+Z125*'1_Assumptions'!$B$54-AA125*'1_Assumptions'!$B$58/365-Z125*'1_Assumptions'!$B$55 | AJ125: =AB125*(1-$B$15)+AC125+AF125+IF($B$19=1,Z125*'1_Assumptions'!$E$31,0)-AD125-(AI125-X125) | AK125: =Z125*(1+'1_Assumptions'!$E$14) | AL125: =AK125*(1-('1_Assumptions'!$E$20+$C125)) | AM125: =AK125-AL125-AK125*$B$11+AK125*$B$12 | AN125: =AE125*$B$13 | AO125: =AK125*'1_Assumptions'!$E$26 | AP125: =AE125+AO125-AN125 | AQ125: =AK125*$B$14 | AR125: =AG125-AQ125 | AS125: =AH125+AK125*$B$16-AH125/$B$18 | AT125: =AK125*'1_Assumptions'!$B$56/365+AL125*'1_Assumptions'!$B$57/365+AK125*'1_Assumptions'!$B$54-AL125*'1_Assumptions'!$B$58/365-AK125*'1_Assumptions'!$B$55 | AU125: =AM125*(1-$B$15)+AN125+AQ125+IF($B$19=1,AK125*'1_Assumptions'!$E$32,0)-AO125-(AT125-AI125) | AV125: =AK125*(1+'1_Assumptions'!$E$15) | AW125: =AV125*(1-('1_Assumptions'!$E$21+$C125)) | AX125: =AV125-AW125-AV125*$B$11+AV125*$B$12 | AY125: =AP125*$B$13 | AZ125: =AV125*'1_Assumptions'!$E$27 | BA125: =AP125+AZ125-AY125 | BB125: =AV125*$B$14 | BC125: =AR125-BB125 | BD125: =AS125+AV125*$B$16-AS125/$B$18 | BE125: =AV125*'1_Assumptions'!$B$56/365+AW125*'1_Assumptions'!$B$57/365+AV125*'1_Assumptions'!$B$54-AW125*'1_Assumptions'!$B$58/365-AV125*'1_Assumptions'!$B$55 | BF125: =AX125*(1-$B$15)+AY125+BB125+IF($B$19=1,AV125*'1_Assumptions'!$E$33,0)-AZ125-(BE125-AT125) | BG125: =N125/(1+$B125)^(1-0.5*$B$23)+Y125/(1+$B125)^(2-0.5*$B$23)+AJ125/(1+$B125)^(3-0.5*$B$23)+AU125/(1+$B125)^(4-0.5*$B$23)+BF125/(1+$B125)^(5-0.5*$B$23) | BH125: =BE125+BA125+BC125+$B$9+IF($B$17=1,BD125,0) | BI125: =IF($B$32=2,$B125+$B$33,IF(BH125=0,0,BL125/BH125)) | BJ125: =IF(BI125=0,9,$B$22/BI125) | BK125: =IF(OR(BH125<=0,BI125<=$B125,BJ125>=1,BJ125<0),1,0) | BL125: =AX125*(1-$B$20) | BM125: =IF(BK125=1,BL125,AX125*(1+$B$22)*(1-$B$20)*(1-BJ125)) | BN125: =IF(BK125=1,BL125/$B125,BM125/($B125-$B$22)) | BO125: =BN125/(1+$B125)^(5-0.5*$B$23) | BP125: =BG125+BO125 | BQ125: =BP125*(1+$B125)^$B$24-N125*$B$24*(1+$B125)^($B$24/2) | BR125: =BQ125-$B$25+$B$26+$B$27 | BS125: =IF($B$28=1,$B$30,BR125*$B$29) | BT125: =BR125-BS125 | BU125: =BT125/$B$31
A126: 1-2 | B126: =$B$21+-0.02 | C126: -0.02 | D126: =$B$5*(1+'1_Assumptions'!$E$11) | E126: =D126*(1-('1_Assumptions'!$E$17+IF('1_Assumptions'!$B$39=1,0,$C126))) | F126: =D126-E126-D126*$B$11+D126*$B$12 | G126: =$B$6*$B$13 | H126: =D126*'1_Assumptions'!$E$23 | I126: =$B$6+H126-G126 | J126: =D126*$B$14 | K126: =$B$7-J126 | L126: =$B$8+D126*$B$16-$B$8/$B$18 | M126: =D126*'1_Assumptions'!$B$56/365+E126*'1_Assumptions'!$B$57/365+D126*'1_Assumptions'!$B$54-E126*'1_Assumptions'!$B$58/365-D126*'1_Assumptions'!$B$55 | N126: =F126*(1-$B$15)+G126+J126+IF($B$19=1,D126*'1_Assumptions'!$E$29,0)-H126-(M126-$B$10) | O126: =D126*(1+'1_Assumptions'!$E$12) | P126: =O126*(1-('1_Assumptions'!$E$18+$C126)) | Q126: =O126-P126-O126*$B$11+O126*$B$12 | R126: =I126*$B$13 | S126: =O126*'1_Assumptions'!$E$24 | T126: =I126+S126-R126 | U126: =O126*$B$14 | V126: =K126-U126 | W126: =L126+O126*$B$16-L126/$B$18 | X126: =O126*'1_Assumptions'!$B$56/365+P126*'1_Assumptions'!$B$57/365+O126*'1_Assumptions'!$B$54-P126*'1_Assumptions'!$B$58/365-O126*'1_Assumptions'!$B$55 | Y126: =Q126*(1-$B$15)+R126+U126+IF($B$19=1,O126*'1_Assumptions'!$E$30,0)-S126-(X126-M126) | Z126: =O126*(1+'1_Assumptions'!$E$13) | AA126: =Z126*(1-('1_Assumptions'!$E$19+$C126)) | AB126: =Z126-AA126-Z126*$B$11+Z126*$B$12 | AC126: =T126*$B$13 | AD126: =Z126*'1_Assumptions'!$E$25 | AE126: =T126+AD126-AC126 | AF126: =Z126*$B$14 | AG126: =V126-AF126 | AH126: =W126+Z126*$B$16-W126/$B$18 | AI126: =Z126*'1_Assumptions'!$B$56/365+AA126*'1_Assumptions'!$B$57/365+Z126*'1_Assumptions'!$B$54-AA126*'1_Assumptions'!$B$58/365-Z126*'1_Assumptions'!$B$55 | AJ126: =AB126*(1-$B$15)+AC126+AF126+IF($B$19=1,Z126*'1_Assumptions'!$E$31,0)-AD126-(AI126-X126) | AK126: =Z126*(1+'1_Assumptions'!$E$14) | AL126: =AK126*(1-('1_Assumptions'!$E$20+$C126)) | AM126: =AK126-AL126-AK126*$B$11+AK126*$B$12 | AN126: =AE126*$B$13 | AO126: =AK126*'1_Assumptions'!$E$26 | AP126: =AE126+AO126-AN126 | AQ126: =AK126*$B$14 | AR126: =AG126-AQ126 | AS126: =AH126+AK126*$B$16-AH126/$B$18 | AT126: =AK126*'1_Assumptions'!$B$56/365+AL126*'1_Assumptions'!$B$57/365+AK126*'1_Assumptions'!$B$54-AL126*'1_Assumptions'!$B$58/365-AK126*'1_Assumptions'!$B$55 | AU126: =AM126*(1-$B$15)+AN126+AQ126+IF($B$19=1,AK126*'1_Assumptions'!$E$32,0)-AO126-(AT126-AI126) | AV126: =AK126*(1+'1_Assumptions'!$E$15) | AW126: =AV126*(1-('1_Assumptions'!$E$21+$C126)) | AX126: =AV126-AW126-AV126*$B$11+AV126*$B$12 | AY126: =AP126*$B$13 | AZ126: =AV126*'1_Assumptions'!$E$27 | BA126: =AP126+AZ126-AY126 | BB126: =AV126*$B$14 | BC126: =AR126-BB126 | BD126: =AS126+AV126*$B$16-AS126/$B$18 | BE126: =AV126*'1_Assumptions'!$B$56/365+AW126*'1_Assumptions'!$B$57/365+AV126*'1_Assumptions'!$B$54-AW126*'1_Assumptions'!$B$58/365-AV126*'1_Assumptions'!$B$55 | BF126: =AX126*(1-$B$15)+AY126+BB126+IF($B$19=1,AV126*'1_Assumptions'!$E$33,0)-AZ126-(BE126-AT126) | BG126: =N126/(1+$B126)^(1-0.5*$B$23)+Y126/(1+$B126)^(2-0.5*$B$23)+AJ126/(1+$B126)^(3-0.5*$B$23)+AU126/(1+$B126)^(4-0.5*$B$23)+BF126/(1+$B126)^(5-0.5*$B$23) | BH126: =BE126+BA126+BC126+$B$9+IF($B$17=1,BD126,0) | BI126: =IF($B$32=2,$B126+$B$33,IF(BH126=0,0,BL126/BH126)) | BJ126: =IF(BI126=0,9,$B$22/BI126) | BK126: =IF(OR(BH126<=0,BI126<=$B126,BJ126>=1,BJ126<0),1,0) | BL126: =AX126*(1-$B$20) | BM126: =IF(BK126=1,BL126,AX126*(1+$B$22)*(1-$B$20)*(1-BJ126)) | BN126: =IF(BK126=1,BL126/$B126,BM126/($B126-$B$22)) | BO126: =BN126/(1+$B126)^(5-0.5*$B$23) | BP126: =BG126+BO126 | BQ126: =BP126*(1+$B126)^$B$24-N126*$B$24*(1+$B126)^($B$24/2) | BR126: =BQ126-$B$25+$B$26+$B$27 | BS126: =IF($B$28=1,$B$30,BR126*$B$29) | BT126: =BR126-BS126 | BU126: =BT126/$B$31
A127: 1-3 | B127: =$B$21+-0.02 | C127: 0 | D127: =$B$5*(1+'1_Assumptions'!$E$11) | E127: =D127*(1-('1_Assumptions'!$E$17+IF('1_Assumptions'!$B$39=1,0,$C127))) | F127: =D127-E127-D127*$B$11+D127*$B$12 | G127: =$B$6*$B$13 | H127: =D127*'1_Assumptions'!$E$23 | I127: =$B$6+H127-G127 | J127: =D127*$B$14 | K127: =$B$7-J127 | L127: =$B$8+D127*$B$16-$B$8/$B$18 | M127: =D127*'1_Assumptions'!$B$56/365+E127*'1_Assumptions'!$B$57/365+D127*'1_Assumptions'!$B$54-E127*'1_Assumptions'!$B$58/365-D127*'1_Assumptions'!$B$55 | N127: =F127*(1-$B$15)+G127+J127+IF($B$19=1,D127*'1_Assumptions'!$E$29,0)-H127-(M127-$B$10) | O127: =D127*(1+'1_Assumptions'!$E$12) | P127: =O127*(1-('1_Assumptions'!$E$18+$C127)) | Q127: =O127-P127-O127*$B$11+O127*$B$12 | R127: =I127*$B$13 | S127: =O127*'1_Assumptions'!$E$24 | T127: =I127+S127-R127 | U127: =O127*$B$14 | V127: =K127-U127 | W127: =L127+O127*$B$16-L127/$B$18 | X127: =O127*'1_Assumptions'!$B$56/365+P127*'1_Assumptions'!$B$57/365+O127*'1_Assumptions'!$B$54-P127*'1_Assumptions'!$B$58/365-O127*'1_Assumptions'!$B$55 | Y127: =Q127*(1-$B$15)+R127+U127+IF($B$19=1,O127*'1_Assumptions'!$E$30,0)-S127-(X127-M127) | Z127: =O127*(1+'1_Assumptions'!$E$13) | AA127: =Z127*(1-('1_Assumptions'!$E$19+$C127)) | AB127: =Z127-AA127-Z127*$B$11+Z127*$B$12 | AC127: =T127*$B$13 | AD127: =Z127*'1_Assumptions'!$E$25 | AE127: =T127+AD127-AC127 | AF127: =Z127*$B$14 | AG127: =V127-AF127 | AH127: =W127+Z127*$B$16-W127/$B$18 | AI127: =Z127*'1_Assumptions'!$B$56/365+AA127*'1_Assumptions'!$B$57/365+Z127*'1_Assumptions'!$B$54-AA127*'1_Assumptions'!$B$58/365-Z127*'1_Assumptions'!$B$55 | AJ127: =AB127*(1-$B$15)+AC127+AF127+IF($B$19=1,Z127*'1_Assumptions'!$E$31,0)-AD127-(AI127-X127) | AK127: =Z127*(1+'1_Assumptions'!$E$14) | AL127: =AK127*(1-('1_Assumptions'!$E$20+$C127)) | AM127: =AK127-AL127-AK127*$B$11+AK127*$B$12 | AN127: =AE127*$B$13 | AO127: =AK127*'1_Assumptions'!$E$26 | AP127: =AE127+AO127-AN127 | AQ127: =AK127*$B$14 | AR127: =AG127-AQ127 | AS127: =AH127+AK127*$B$16-AH127/$B$18 | AT127: =AK127*'1_Assumptions'!$B$56/365+AL127*'1_Assumptions'!$B$57/365+AK127*'1_Assumptions'!$B$54-AL127*'1_Assumptions'!$B$58/365-AK127*'1_Assumptions'!$B$55 | AU127: =AM127*(1-$B$15)+AN127+AQ127+IF($B$19=1,AK127*'1_Assumptions'!$E$32,0)-AO127-(AT127-AI127) | AV127: =AK127*(1+'1_Assumptions'!$E$15) | AW127: =AV127*(1-('1_Assumptions'!$E$21+$C127)) | AX127: =AV127-AW127-AV127*$B$11+AV127*$B$12 | AY127: =AP127*$B$13 | AZ127: =AV127*'1_Assumptions'!$E$27 | BA127: =AP127+AZ127-AY127 | BB127: =AV127*$B$14 | BC127: =AR127-BB127 | BD127: =AS127+AV127*$B$16-AS127/$B$18 | BE127: =AV127*'1_Assumptions'!$B$56/365+AW127*'1_Assumptions'!$B$57/365+AV127*'1_Assumptions'!$B$54-AW127*'1_Assumptions'!$B$58/365-AV127*'1_Assumptions'!$B$55 | BF127: =AX127*(1-$B$15)+AY127+BB127+IF($B$19=1,AV127*'1_Assumptions'!$E$33,0)-AZ127-(BE127-AT127) | BG127: =N127/(1+$B127)^(1-0.5*$B$23)+Y127/(1+$B127)^(2-0.5*$B$23)+AJ127/(1+$B127)^(3-0.5*$B$23)+AU127/(1+$B127)^(4-0.5*$B$23)+BF127/(1+$B127)^(5-0.5*$B$23) | BH127: =BE127+BA127+BC127+$B$9+IF($B$17=1,BD127,0) | BI127: =IF($B$32=2,$B127+$B$33,IF(BH127=0,0,BL127/BH127)) | BJ127: =IF(BI127=0,9,$B$22/BI127) | BK127: =IF(OR(BH127<=0,BI127<=$B127,BJ127>=1,BJ127<0),1,0) | BL127: =AX127*(1-$B$20) | BM127: =IF(BK127=1,BL127,AX127*(1+$B$22)*(1-$B$20)*(1-BJ127)) | BN127: =IF(BK127=1,BL127/$B127,BM127/($B127-$B$22)) | BO127: =BN127/(1+$B127)^(5-0.5*$B$23) | BP127: =BG127+BO127 | BQ127: =BP127*(1+$B127)^$B$24-N127*$B$24*(1+$B127)^($B$24/2) | BR127: =BQ127-$B$25+$B$26+$B$27 | BS127: =IF($B$28=1,$B$30,BR127*$B$29) | BT127: =BR127-BS127 | BU127: =BT127/$B$31
